Workbook

Sheet Read Me
B2: Virginia Retail Sales Tax by Locality — 10-Year History, 20-Year Projection, and 1%-for-Schools Profile
B5: What this workbook contains
B6: Assumptions — statewide control totals and every growth lever the model uses. Yellow cells are yours to change.
B7: Historical FY16-FY25 — retail sales tax distributed to each of Virginia's 95 counties and 38 independent cities.
B8: Projection FY26-FY45 — 20-year forward projection of that distribution, locality by locality.
B9: Schools 1pct Profile — what a dedicated 1% school sales tax would raise in each locality, per year and cumulatively.
B11: Source data
B12: Virginia Department of Taxation, Annual Report, Table 4.3 'Local Sales Tax Distribution'.
B13: https://www.tax.virginia.gov/annual-reports
B14: FY2025 report (pp. 32-33) and FY2019 report (pp. 29-30) — full locality detail, entered as actuals (blue text).
B15: Table 4.1 of the FY2025 report — statewide Local Option totals for every year FY2016-FY2025, entered as actuals.
B16: Transcription check: the 133 locality figures sum to the published statewide totals within $5 (report rounding).
... B76: Status flags are only as good as the referendum filings behind them — update the Status column.

Sheet Assumptions
A1: Assumptions & Statewide Control Totals
A2: Yellow cells are inputs you can change. Everything downstream recalculates.
A4: Fiscal Year | B4: Statewide Local Option 1% ($) | C4: Ratio: Ed Share / Local Option | D4: Statewide State 1% Education Share ($) | E4: Statewide Total Distributed to Localities ($)
A5: 2016 | B5: 1188704000 | C5: =$C$8 -> 0.99807159 | D5: =B5*C5 -> 1.1864117e+09 | E5: =B5+D5 -> 2.3751157e+09
A6: 2017 | B6: 1213929000 | C6: =$C$8 -> 0.99807159 | D6: =B6*C6 -> 1.211588e+09 | E6: =B6+D6 -> 2.425517e+09
A7: 2018 | B7: 1243480000 | C7: =$C$8 -> 0.99807159 | D7: =B7*C7 -> 1.2410821e+09 | E7: =B7+D7 -> 2.4845621e+09
A8: 2019 | B8: 1292804000 | C8: =D8/B8 -> 0.99807159 | D8: 1290310945 | E8: =B8+D8 -> 2583114945
A9: 2020 | B9: 1358988000 | C9: =$C$8 -> 0.99807159 | D9: =B9*C9 -> 1.3563673e+09 | E9: =B9+D9 -> 2.7153553e+09
A10: 2021 | B10: 1477201000 | C10: =$C$8 -> 0.99807159 | D10: =B10*C10 -> 1.4743524e+09 | E10: =B10+D10 -> 2.9515534e+09
A11: 2022 | B11: 1662897000 | C11: =$C$8 -> 0.99807159 | D11: =B11*C11 -> 1.6596903e+09 | E11: =B11+D11 -> 3.3225873e+09
A12: 2023 | B12: 1770842000 | C12: =$C$8+($C$14-$C$8)*(A12-2022)/3 -> 0.94318166 | D12: =B12*C12 -> 1.6702257e+09 | E12: =B12+D12 -> 3.4410677e+09
A13: 2024 | B13: 1808583000 | C13: =$C$8+($C$14-$C$8)*(A13-2022)/3 -> 0.88829172 | D13: =B13*C13 -> 1.6065493e+09 | E13: =B13+D13 -> 3.4151323e+09
A14: 2025 | B14: 1876913000 | C14: =D14/B14 -> 0.83340179 | D14: 1564222650 | E14: =B14+D14 -> 3441135650
A15: Blue = published actual. FY2019 and FY2025 education-share figures are the Table 4.3 aggregates;
A16: Other years are modelled. The education share tracked Local Option almost 1:1 through FY2022, so the ratio is
A17: held flat to FY2022, then interpolated down to the FY2025 actual — the drop follows the Jan-2023 grocery tax repeal.
A18: Derived growth rates
A19: Statewide Local Option CAGR, FY2016-FY2025 (9 yrs) | B19: =(B14/B5)^(1/9)-1 -> 0.052061572
A20: Statewide Local Option CAGR, FY2019-FY2025 (6 yrs) | B20: =(B14/B8)^(1/6)-1 -> 0.064106859
A21: Statewide Total Distribution CAGR, FY2019-FY2025 | B21: =(E14/E8)^(1/6)-1 -> 0.04896181
A23: Projection levers (edit these)
A24: Baseline statewide growth rate applied to all localities | B24: =B19 -> 0.052061572 | C24: Defaults to the 9-year statewide CAGR. Lower to ~3.5% for a conservative case.
A25: Locality trend weight (0 = flat statewide rate, 1 = full local trend) | B25: 0.5 | C25: Damps extreme six-year local growth rates before running them out 20 years.
A26: Floor on any locality's growth rate | B26: 0 | C26: No locality is projected to shrink.
A27: Ceiling on any locality's growth rate | B27: 0.08 | C27: Caps runaway extrapolation for small, volatile localities.
A28: New school sales tax rate (percentage points) | B28: 0.01 | C28: The dedicated levy being modelled. Va. Code 58.1-605.1 caps this at 1%.
A29: Existing local option rate (basis for scaling) | B29: 0.01 | C29: Local Option is a 1% tax, so a new 1% levy on the same base yields ~the same amount.

Sheet Historical FY16-FY25
A1: Retail Sales Tax Distributed to Virginia Localities — FY2016 to FY2025
A2: Columns C-H are published actuals (blue). The FY2016-FY2025 series at right is modelled: actual statewide totals allocated on each locality's interpolated share. FY2019 and FY2025 reproduce the actuals exactly.
A4: Locality | B4: Type | C4: FY2019 Local Option ($) | D4: FY2025 Local Option ($) | E4: FY2019 State 1% Ed Share ($) | F4: FY2025 State 1% Ed Share ($) | G4: FY2019 Total ($) | H4: FY2025 Total ($) | I4: Local Option CAGR FY19-25 | J4: Total CAGR FY19-25 | K4: 2016 | L4: 2017 | M4: 2018 | N4: 2019 | O4: 2020 | P4: 2021 | Q4: 2022 | R4: 2023 | S4: 2024 | T4: 2025
A5: Accomack County | B5: County | C5: 4721028 | D5: 6374893 | E5: 4678123 | F5: 5447703 | G5: =C5+E5 -> 9399151 | H5: =D5+F5 -> 11822596 | I5: =IFERROR((D5/C5)^(1/6)-1,0) -> 0.051330799 | J5: =IFERROR((H5/G5)^(1/6)-1,0) -> 0.038972463 | K5: =($G5/Assumptions!$E$8+($H5/Assumptions!$E$14-$G5/Assumptions!$E$8)*(K$4-2019)/6)*INDEX(Assumptions!$E$5:$E$14,MATCH(K$4,Assumptions!$A$5:$A$14,0)) -> 8883406.5 | L5: =($G5/Assumptions!$E$8+($H5/Assumptions!$E$14-$G5/Assumptions!$E$8)*(L$4-2019)/6)*INDEX(Assumptions!$E$5:$E$14,MATCH(L$4,Assumptions!$A$5:$A$14,0)) -> 8989845.5 | M5: =($G5/Assumptions!$E$8+($H5/Assumptions!$E$14-$G5/Assumptions!$E$8)*(M$4-2019)/6)*INDEX(Assumptions!$E$5:$E$14,MATCH(M$4,Assumptions!$A$5:$A$14,0)) -> 9124617.7 | N5: =($G5/Assumptions!$E$8+($H5/Assumptions!$E$14-$G5/Assumptions!$E$8)*(N$4-2019)/6)*INDEX(Assumptions!$E$5:$E$14,MATCH(N$4,Assumptions!$A$5:$A$14,0)) -> 9399151 | O5: =($G5/Assumptions!$E$8+($H5/Assumptions!$E$14-$G5/Assumptions!$E$8)*(O$4-2019)/6)*INDEX(Assumptions!$E$5:$E$14,MATCH(O$4,Assumptions!$A$5:$A$14,0)) -> 9788453.2 | P5: =($G5/Assumptions!$E$8+($H5/Assumptions!$E$14-$G5/Assumptions!$E$8)*(P$4-2019)/6)*INDEX(Assumptions!$E$5:$E$14,MATCH(P$4,Assumptions!$A$5:$A$14,0)) -> 10540041 | Q5: =($G5/Assumptions!$E$8+($H5/Assumptions!$E$14-$G5/Assumptions!$E$8)*(Q$4-2019)/6)*INDEX(Assumptions!$E$5:$E$14,MATCH(Q$4,Assumptions!$A$5:$A$14,0)) -> 11752582 | R5: =($G5/Assumptions!$E$8+($H5/Assumptions!$E$14-$G5/Assumptions!$E$8)*(R$4-2019)/6)*INDEX(Assumptions!$E$5:$E$14,MATCH(R$4,Assumptions!$A$5:$A$14,0)) -> 12055233 | ... T5: =($G5/Assumptions!$E$8+($H5/Assumptions!$E$14-$G5/Assumptions!$E$8)*(T$4-2019)/6)*INDEX(Assumptions!$E$5:$E$14,MATCH(T$4,Assumptions!$A$5:$A$14,0)) -> 11822596
A6: Albemarle County | B6: County | C6: 17038808 | D6: 26225183 | E6: 15252442 | F6: 19212745 | G6: =C6+E6 -> 32291250 | H6: =D6+F6 -> 45437928 | I6: =IFERROR((D6/C6)^(1/6)-1,0) -> 0.074516824 | J6: =IFERROR((H6/G6)^(1/6)-1,0) -> 0.058576569 | K6: =($G6/Assumptions!$E$8+($H6/Assumptions!$E$14-$G6/Assumptions!$E$8)*(K$4-2019)/6)*INDEX(Assumptions!$E$5:$E$14,MATCH(K$4,Assumptions!$A$5:$A$14,0)) -> 28855691 | L6: =($G6/Assumptions!$E$8+($H6/Assumptions!$E$14-$G6/Assumptions!$E$8)*(L$4-2019)/6)*INDEX(Assumptions!$E$5:$E$14,MATCH(L$4,Assumptions!$A$5:$A$14,0)) -> 29752396 | M6: =($G6/Assumptions!$E$8+($H6/Assumptions!$E$14-$G6/Assumptions!$E$8)*(M$4-2019)/6)*INDEX(Assumptions!$E$5:$E$14,MATCH(M$4,Assumptions!$A$5:$A$14,0)) -> 30767958 | N6: =($G6/Assumptions!$E$8+($H6/Assumptions!$E$14-$G6/Assumptions!$E$8)*(N$4-2019)/6)*INDEX(Assumptions!$E$5:$E$14,MATCH(N$4,Assumptions!$A$5:$A$14,0)) -> 32291250 | O6: =($G6/Assumptions!$E$8+($H6/Assumptions!$E$14-$G6/Assumptions!$E$8)*(O$4-2019)/6)*INDEX(Assumptions!$E$5:$E$14,MATCH(O$4,Assumptions!$A$5:$A$14,0)) -> 34262724 | P6: =($G6/Assumptions!$E$8+($H6/Assumptions!$E$14-$G6/Assumptions!$E$8)*(P$4-2019)/6)*INDEX(Assumptions!$E$5:$E$14,MATCH(P$4,Assumptions!$A$5:$A$14,0)) -> 37589146 | Q6: =($G6/Assumptions!$E$8+($H6/Assumptions!$E$14-$G6/Assumptions!$E$8)*(Q$4-2019)/6)*INDEX(Assumptions!$E$5:$E$14,MATCH(Q$4,Assumptions!$A$5:$A$14,0)) -> 42703945 | R6: =($G6/Assumptions!$E$8+($H6/Assumptions!$E$14-$G6/Assumptions!$E$8)*(R$4-2019)/6)*INDEX(Assumptions!$E$5:$E$14,MATCH(R$4,Assumptions!$A$5:$A$14,0)) -> 44630163 | ... T6: =($G6/Assumptions!$E$8+($H6/Assumptions!$E$14-$G6/Assumptions!$E$8)*(T$4-2019)/6)*INDEX(Assumptions!$E$5:$E$14,MATCH(T$4,Assumptions!$A$5:$A$14,0)) -> 45437928
A7: Alleghany County | B7: County | C7: 958820 | D7: 1288843 | E7: 2224841 | F7: 2315274 | G7: =C7+E7 -> 3183661 | H7: =D7+F7 -> 3604117 | I7: =IFERROR((D7/C7)^(1/6)-1,0) -> 0.05053491 | J7: =IFERROR((H7/G7)^(1/6)-1,0) -> 0.020889359 | K7: =($G7/Assumptions!$E$8+($H7/Assumptions!$E$14-$G7/Assumptions!$E$8)*(K$4-2019)/6)*INDEX(Assumptions!$E$5:$E$14,MATCH(K$4,Assumptions!$A$5:$A$14,0)) -> 3147152.5 | L7: =($G7/Assumptions!$E$8+($H7/Assumptions!$E$14-$G7/Assumptions!$E$8)*(L$4-2019)/6)*INDEX(Assumptions!$E$5:$E$14,MATCH(L$4,Assumptions!$A$5:$A$14,0)) -> 3139099.1 | M7: =($G7/Assumptions!$E$8+($H7/Assumptions!$E$14-$G7/Assumptions!$E$8)*(M$4-2019)/6)*INDEX(Assumptions!$E$5:$E$14,MATCH(M$4,Assumptions!$A$5:$A$14,0)) -> 3138855.3 | N7: =($G7/Assumptions!$E$8+($H7/Assumptions!$E$14-$G7/Assumptions!$E$8)*(N$4-2019)/6)*INDEX(Assumptions!$E$5:$E$14,MATCH(N$4,Assumptions!$A$5:$A$14,0)) -> 3183661 | O7: =($G7/Assumptions!$E$8+($H7/Assumptions!$E$14-$G7/Assumptions!$E$8)*(O$4-2019)/6)*INDEX(Assumptions!$E$5:$E$14,MATCH(O$4,Assumptions!$A$5:$A$14,0)) -> 3262865.1 | P7: =($G7/Assumptions!$E$8+($H7/Assumptions!$E$14-$G7/Assumptions!$E$8)*(P$4-2019)/6)*INDEX(Assumptions!$E$5:$E$14,MATCH(P$4,Assumptions!$A$5:$A$14,0)) -> 3455620.5 | Q7: =($G7/Assumptions!$E$8+($H7/Assumptions!$E$14-$G7/Assumptions!$E$8)*(Q$4-2019)/6)*INDEX(Assumptions!$E$5:$E$14,MATCH(Q$4,Assumptions!$A$5:$A$14,0)) -> 3787503.2 | R7: =($G7/Assumptions!$E$8+($H7/Assumptions!$E$14-$G7/Assumptions!$E$8)*(R$4-2019)/6)*INDEX(Assumptions!$E$5:$E$14,MATCH(R$4,Assumptions!$A$5:$A$14,0)) -> 3816390 | ... T7: =($G7/Assumptions!$E$8+($H7/Assumptions!$E$14-$G7/Assumptions!$E$8)*(T$4-2019)/6)*INDEX(Assumptions!$E$5:$E$14,MATCH(T$4,Assumptions!$A$5:$A$14,0)) -> 3604117
A8: Amelia County | B8: County | C8: 821928 | D8: 1519698 | E8: 1893604 | F8: 2174286 | G8: =C8+E8 -> 2715532 | H8: =D8+F8 -> 3693984 | I8: =IFERROR((D8/C8)^(1/6)-1,0) -> 0.10786605 | J8: =IFERROR((H8/G8)^(1/6)-1,0) -> 0.052624193 | K8: =($G8/Assumptions!$E$8+($H8/Assumptions!$E$14-$G8/Assumptions!$E$8)*(K$4-2019)/6)*INDEX(Assumptions!$E$5:$E$14,MATCH(K$4,Assumptions!$A$5:$A$14,0)) -> 2470487.8 | L8: =($G8/Assumptions!$E$8+($H8/Assumptions!$E$14-$G8/Assumptions!$E$8)*(L$4-2019)/6)*INDEX(Assumptions!$E$5:$E$14,MATCH(L$4,Assumptions!$A$5:$A$14,0)) -> 2531893.8 | M8: =($G8/Assumptions!$E$8+($H8/Assumptions!$E$14-$G8/Assumptions!$E$8)*(M$4-2019)/6)*INDEX(Assumptions!$E$5:$E$14,MATCH(M$4,Assumptions!$A$5:$A$14,0)) -> 2602727.7 | N8: =($G8/Assumptions!$E$8+($H8/Assumptions!$E$14-$G8/Assumptions!$E$8)*(N$4-2019)/6)*INDEX(Assumptions!$E$5:$E$14,MATCH(N$4,Assumptions!$A$5:$A$14,0)) -> 2715532 | O8: =($G8/Assumptions!$E$8+($H8/Assumptions!$E$14-$G8/Assumptions!$E$8)*(O$4-2019)/6)*INDEX(Assumptions!$E$5:$E$14,MATCH(O$4,Assumptions!$A$5:$A$14,0)) -> 2864605.2 | P8: =($G8/Assumptions!$E$8+($H8/Assumptions!$E$14-$G8/Assumptions!$E$8)*(P$4-2019)/6)*INDEX(Assumptions!$E$5:$E$14,MATCH(P$4,Assumptions!$A$5:$A$14,0)) -> 3124714.4 | Q8: =($G8/Assumptions!$E$8+($H8/Assumptions!$E$14-$G8/Assumptions!$E$8)*(Q$4-2019)/6)*INDEX(Assumptions!$E$5:$E$14,MATCH(Q$4,Assumptions!$A$5:$A$14,0)) -> 3529818.2 | R8: =($G8/Assumptions!$E$8+($H8/Assumptions!$E$14-$G8/Assumptions!$E$8)*(R$4-2019)/6)*INDEX(Assumptions!$E$5:$E$14,MATCH(R$4,Assumptions!$A$5:$A$14,0)) -> 3668429.2 | ... T8: =($G8/Assumptions!$E$8+($H8/Assumptions!$E$14-$G8/Assumptions!$E$8)*(T$4-2019)/6)*INDEX(Assumptions!$E$5:$E$14,MATCH(T$4,Assumptions!$A$5:$A$14,0)) -> 3693984
A9: Amherst County | B9: County | C9: 2895601 | D9: 4726734 | E9: 4519031 | F9: 5146545 | G9: =C9+E9 -> 7414632 | H9: =D9+F9 -> 9873279 | I9: =IFERROR((D9/C9)^(1/6)-1,0) -> 0.085101609 | J9: =IFERROR((H9/G9)^(1/6)-1,0) -> 0.048886836 | K9: =($G9/Assumptions!$E$8+($H9/Assumptions!$E$14-$G9/Assumptions!$E$8)*(K$4-2019)/6)*INDEX(Assumptions!$E$5:$E$14,MATCH(K$4,Assumptions!$A$5:$A$14,0)) -> 6819047.8 | L9: =($G9/Assumptions!$E$8+($H9/Assumptions!$E$14-$G9/Assumptions!$E$8)*(L$4-2019)/6)*INDEX(Assumptions!$E$5:$E$14,MATCH(L$4,Assumptions!$A$5:$A$14,0)) -> 6963254.5 | M9: =($G9/Assumptions!$E$8+($H9/Assumptions!$E$14-$G9/Assumptions!$E$8)*(M$4-2019)/6)*INDEX(Assumptions!$E$5:$E$14,MATCH(M$4,Assumptions!$A$5:$A$14,0)) -> 7132253.2 | N9: =($G9/Assumptions!$E$8+($H9/Assumptions!$E$14-$G9/Assumptions!$E$8)*(N$4-2019)/6)*INDEX(Assumptions!$E$5:$E$14,MATCH(N$4,Assumptions!$A$5:$A$14,0)) -> 7414632 | O9: =($G9/Assumptions!$E$8+($H9/Assumptions!$E$14-$G9/Assumptions!$E$8)*(O$4-2019)/6)*INDEX(Assumptions!$E$5:$E$14,MATCH(O$4,Assumptions!$A$5:$A$14,0)) -> 7793660.8 | P9: =($G9/Assumptions!$E$8+($H9/Assumptions!$E$14-$G9/Assumptions!$E$8)*(P$4-2019)/6)*INDEX(Assumptions!$E$5:$E$14,MATCH(P$4,Assumptions!$A$5:$A$14,0)) -> 8470995.1 | Q9: =($G9/Assumptions!$E$8+($H9/Assumptions!$E$14-$G9/Assumptions!$E$8)*(Q$4-2019)/6)*INDEX(Assumptions!$E$5:$E$14,MATCH(Q$4,Assumptions!$A$5:$A$14,0)) -> 9535185.5 | R9: =($G9/Assumptions!$E$8+($H9/Assumptions!$E$14-$G9/Assumptions!$E$8)*(R$4-2019)/6)*INDEX(Assumptions!$E$5:$E$14,MATCH(R$4,Assumptions!$A$5:$A$14,0)) -> 9874495.7 | ... T9: =($G9/Assumptions!$E$8+($H9/Assumptions!$E$14-$G9/Assumptions!$E$8)*(T$4-2019)/6)*INDEX(Assumptions!$E$5:$E$14,MATCH(T$4,Assumptions!$A$5:$A$14,0)) -> 9873279
A10: Appomattox County | B10: County | C10: 1385301 | D10: 2192135 | E10: 2330903 | F10: 2958832 | G10: =C10+E10 -> 3716204 | H10: =D10+F10 -> 5150967 | I10: =IFERROR((D10/C10)^(1/6)-1,0) -> 0.079494726 | J10: =IFERROR((H10/G10)^(1/6)-1,0) -> 0.055921267 | K10: =($G10/Assumptions!$E$8+($H10/Assumptions!$E$14-$G10/Assumptions!$E$8)*(K$4-2019)/6)*INDEX(Assumptions!$E$5:$E$14,MATCH(K$4,Assumptions!$A$5:$A$14,0)) -> 3347816.6 | L10: =($G10/Assumptions!$E$8+($H10/Assumptions!$E$14-$G10/Assumptions!$E$8)*(L$4-2019)/6)*INDEX(Assumptions!$E$5:$E$14,MATCH(L$4,Assumptions!$A$5:$A$14,0)) -> 3442398 | M10: =($G10/Assumptions!$E$8+($H10/Assumptions!$E$14-$G10/Assumptions!$E$8)*(M$4-2019)/6)*INDEX(Assumptions!$E$5:$E$14,MATCH(M$4,Assumptions!$A$5:$A$14,0)) -> 3550308.9 | N10: =($G10/Assumptions!$E$8+($H10/Assumptions!$E$14-$G10/Assumptions!$E$8)*(N$4-2019)/6)*INDEX(Assumptions!$E$5:$E$14,MATCH(N$4,Assumptions!$A$5:$A$14,0)) -> 3716204 | O10: =($G10/Assumptions!$E$8+($H10/Assumptions!$E$14-$G10/Assumptions!$E$8)*(O$4-2019)/6)*INDEX(Assumptions!$E$5:$E$14,MATCH(O$4,Assumptions!$A$5:$A$14,0)) -> 3932803.4 | P10: =($G10/Assumptions!$E$8+($H10/Assumptions!$E$14-$G10/Assumptions!$E$8)*(P$4-2019)/6)*INDEX(Assumptions!$E$5:$E$14,MATCH(P$4,Assumptions!$A$5:$A$14,0)) -> 4303546.2 | Q10: =($G10/Assumptions!$E$8+($H10/Assumptions!$E$14-$G10/Assumptions!$E$8)*(Q$4-2019)/6)*INDEX(Assumptions!$E$5:$E$14,MATCH(Q$4,Assumptions!$A$5:$A$14,0)) -> 4876780.9 | R10: =($G10/Assumptions!$E$8+($H10/Assumptions!$E$14-$G10/Assumptions!$E$8)*(R$4-2019)/6)*INDEX(Assumptions!$E$5:$E$14,MATCH(R$4,Assumptions!$A$5:$A$14,0)) -> 5084076.7 | ... T10: =($G10/Assumptions!$E$8+($H10/Assumptions!$E$14-$G10/Assumptions!$E$8)*(T$4-2019)/6)*INDEX(Assumptions!$E$5:$E$14,MATCH(T$4,Assumptions!$A$5:$A$14,0)) -> 5150967
A11: Arlington County | B11: County | C11: 43737164 | D11: 55138617 | E11: 25689698 | F11: 34138301 | G11: =C11+E11 -> 69426862 | H11: =D11+F11 -> 89276918 | I11: =IFERROR((D11/C11)^(1/6)-1,0) -> 0.039363692 | J11: =IFERROR((H11/G11)^(1/6)-1,0) -> 0.042802208 | K11: =($G11/Assumptions!$E$8+($H11/Assumptions!$E$14-$G11/Assumptions!$E$8)*(K$4-2019)/6)*INDEX(Assumptions!$E$5:$E$14,MATCH(K$4,Assumptions!$A$5:$A$14,0)) -> 64944608 | L11: =($G11/Assumptions!$E$8+($H11/Assumptions!$E$14-$G11/Assumptions!$E$8)*(L$4-2019)/6)*INDEX(Assumptions!$E$5:$E$14,MATCH(L$4,Assumptions!$A$5:$A$14,0)) -> 65945538 | M11: =($G11/Assumptions!$E$8+($H11/Assumptions!$E$14-$G11/Assumptions!$E$8)*(M$4-2019)/6)*INDEX(Assumptions!$E$5:$E$14,MATCH(M$4,Assumptions!$A$5:$A$14,0)) -> 67164453 | N11: =($G11/Assumptions!$E$8+($H11/Assumptions!$E$14-$G11/Assumptions!$E$8)*(N$4-2019)/6)*INDEX(Assumptions!$E$5:$E$14,MATCH(N$4,Assumptions!$A$5:$A$14,0)) -> 69426862 | O11: =($G11/Assumptions!$E$8+($H11/Assumptions!$E$14-$G11/Assumptions!$E$8)*(O$4-2019)/6)*INDEX(Assumptions!$E$5:$E$14,MATCH(O$4,Assumptions!$A$5:$A$14,0)) -> 72558801 | P11: =($G11/Assumptions!$E$8+($H11/Assumptions!$E$14-$G11/Assumptions!$E$8)*(P$4-2019)/6)*INDEX(Assumptions!$E$5:$E$14,MATCH(P$4,Assumptions!$A$5:$A$14,0)) -> 78411360 | Q11: =($G11/Assumptions!$E$8+($H11/Assumptions!$E$14-$G11/Assumptions!$E$8)*(Q$4-2019)/6)*INDEX(Assumptions!$E$5:$E$14,MATCH(Q$4,Assumptions!$A$5:$A$14,0)) -> 87751546 | R11: =($G11/Assumptions!$E$8+($H11/Assumptions!$E$14-$G11/Assumptions!$E$8)*(R$4-2019)/6)*INDEX(Assumptions!$E$5:$E$14,MATCH(R$4,Assumptions!$A$5:$A$14,0)) -> 90345509 | ... T11: =($G11/Assumptions!$E$8+($H11/Assumptions!$E$14-$G11/Assumptions!$E$8)*(T$4-2019)/6)*INDEX(Assumptions!$E$5:$E$14,MATCH(T$4,Assumptions!$A$5:$A$14,0)) -> 89276918
A12: Augusta County | B12: County | C12: 6229458 | D12: 9993991 | E12: 10569425 | F12: 12920072 | G12: =C12+E12 -> 16798883 | H12: =D12+F12 -> 22914063 | I12: =IFERROR((D12/C12)^(1/6)-1,0) -> 0.081968911 | J12: =IFERROR((H12/G12)^(1/6)-1,0) -> 0.053101625 | K12: =($G12/Assumptions!$E$8+($H12/Assumptions!$E$14-$G12/Assumptions!$E$8)*(K$4-2019)/6)*INDEX(Assumptions!$E$5:$E$14,MATCH(K$4,Assumptions!$A$5:$A$14,0)) -> 15261500 | L12: =($G12/Assumptions!$E$8+($H12/Assumptions!$E$14-$G12/Assumptions!$E$8)*(L$4-2019)/6)*INDEX(Assumptions!$E$5:$E$14,MATCH(L$4,Assumptions!$A$5:$A$14,0)) -> 15648228 | M12: =($G12/Assumptions!$E$8+($H12/Assumptions!$E$14-$G12/Assumptions!$E$8)*(M$4-2019)/6)*INDEX(Assumptions!$E$5:$E$14,MATCH(M$4,Assumptions!$A$5:$A$14,0)) -> 16093559 | N12: =($G12/Assumptions!$E$8+($H12/Assumptions!$E$14-$G12/Assumptions!$E$8)*(N$4-2019)/6)*INDEX(Assumptions!$E$5:$E$14,MATCH(N$4,Assumptions!$A$5:$A$14,0)) -> 16798883 | O12: =($G12/Assumptions!$E$8+($H12/Assumptions!$E$14-$G12/Assumptions!$E$8)*(O$4-2019)/6)*INDEX(Assumptions!$E$5:$E$14,MATCH(O$4,Assumptions!$A$5:$A$14,0)) -> 17729271 | P12: =($G12/Assumptions!$E$8+($H12/Assumptions!$E$14-$G12/Assumptions!$E$8)*(P$4-2019)/6)*INDEX(Assumptions!$E$5:$E$14,MATCH(P$4,Assumptions!$A$5:$A$14,0)) -> 19347976 | Q12: =($G12/Assumptions!$E$8+($H12/Assumptions!$E$14-$G12/Assumptions!$E$8)*(Q$4-2019)/6)*INDEX(Assumptions!$E$5:$E$14,MATCH(Q$4,Assumptions!$A$5:$A$14,0)) -> 21866295 | R12: =($G12/Assumptions!$E$8+($H12/Assumptions!$E$14-$G12/Assumptions!$E$8)*(R$4-2019)/6)*INDEX(Assumptions!$E$5:$E$14,MATCH(R$4,Assumptions!$A$5:$A$14,0)) -> 22735222 | ... T12: =($G12/Assumptions!$E$8+($H12/Assumptions!$E$14-$G12/Assumptions!$E$8)*(T$4-2019)/6)*INDEX(Assumptions!$E$5:$E$14,MATCH(T$4,Assumptions!$A$5:$A$14,0)) -> 22914063
A13: Bath County | B13: County | C13: 822596 | D13: 1312575 | E13: 528675 | F13: 572584 | G13: =C13+E13 -> 1351271 | H13: =D13+F13 -> 1885159 | I13: =IFERROR((D13/C13)^(1/6)-1,0) -> 0.080993102 | J13: =IFERROR((H13/G13)^(1/6)-1,0) -> 0.057063122 | K13: =($G13/Assumptions!$E$8+($H13/Assumptions!$E$14-$G13/Assumptions!$E$8)*(K$4-2019)/6)*INDEX(Assumptions!$E$5:$E$14,MATCH(K$4,Assumptions!$A$5:$A$14,0)) -> 1213114.2 | L13: =($G13/Assumptions!$E$8+($H13/Assumptions!$E$14-$G13/Assumptions!$E$8)*(L$4-2019)/6)*INDEX(Assumptions!$E$5:$E$14,MATCH(L$4,Assumptions!$A$5:$A$14,0)) -> 1248847.8 | M13: =($G13/Assumptions!$E$8+($H13/Assumptions!$E$14-$G13/Assumptions!$E$8)*(M$4-2019)/6)*INDEX(Assumptions!$E$5:$E$14,MATCH(M$4,Assumptions!$A$5:$A$14,0)) -> 1289482.6 | N13: =($G13/Assumptions!$E$8+($H13/Assumptions!$E$14-$G13/Assumptions!$E$8)*(N$4-2019)/6)*INDEX(Assumptions!$E$5:$E$14,MATCH(N$4,Assumptions!$A$5:$A$14,0)) -> 1351271 | O13: =($G13/Assumptions!$E$8+($H13/Assumptions!$E$14-$G13/Assumptions!$E$8)*(O$4-2019)/6)*INDEX(Assumptions!$E$5:$E$14,MATCH(O$4,Assumptions!$A$5:$A$14,0)) -> 1431632.5 | P13: =($G13/Assumptions!$E$8+($H13/Assumptions!$E$14-$G13/Assumptions!$E$8)*(P$4-2019)/6)*INDEX(Assumptions!$E$5:$E$14,MATCH(P$4,Assumptions!$A$5:$A$14,0)) -> 1568321.9 | Q13: =($G13/Assumptions!$E$8+($H13/Assumptions!$E$14-$G13/Assumptions!$E$8)*(Q$4-2019)/6)*INDEX(Assumptions!$E$5:$E$14,MATCH(Q$4,Assumptions!$A$5:$A$14,0)) -> 1779158 | R13: =($G13/Assumptions!$E$8+($H13/Assumptions!$E$14-$G13/Assumptions!$E$8)*(R$4-2019)/6)*INDEX(Assumptions!$E$5:$E$14,MATCH(R$4,Assumptions!$A$5:$A$14,0)) -> 1856774.7 | ... T13: =($G13/Assumptions!$E$8+($H13/Assumptions!$E$14-$G13/Assumptions!$E$8)*(T$4-2019)/6)*INDEX(Assumptions!$E$5:$E$14,MATCH(T$4,Assumptions!$A$5:$A$14,0)) -> 1885159
A14: Bedford County | B14: County | C14: 6395201 | D14: 10883951 | E14: 11604747 | F14: 13413051 | G14: =C14+E14 -> 17999948 | H14: =D14+F14 -> 24297002 | I14: =IFERROR((D14/C14)^(1/6)-1,0) -> 0.092669272 | J14: =IFERROR((H14/G14)^(1/6)-1,0) -> 0.05126831 | K14: =($G14/Assumptions!$E$8+($H14/Assumptions!$E$14-$G14/Assumptions!$E$8)*(K$4-2019)/6)*INDEX(Assumptions!$E$5:$E$14,MATCH(K$4,Assumptions!$A$5:$A$14,0)) -> 16440767 | L14: =($G14/Assumptions!$E$8+($H14/Assumptions!$E$14-$G14/Assumptions!$E$8)*(L$4-2019)/6)*INDEX(Assumptions!$E$5:$E$14,MATCH(L$4,Assumptions!$A$5:$A$14,0)) -> 16827019 | M14: =($G14/Assumptions!$E$8+($H14/Assumptions!$E$14-$G14/Assumptions!$E$8)*(M$4-2019)/6)*INDEX(Assumptions!$E$5:$E$14,MATCH(M$4,Assumptions!$A$5:$A$14,0)) -> 17274922 | N14: =($G14/Assumptions!$E$8+($H14/Assumptions!$E$14-$G14/Assumptions!$E$8)*(N$4-2019)/6)*INDEX(Assumptions!$E$5:$E$14,MATCH(N$4,Assumptions!$A$5:$A$14,0)) -> 17999948 | O14: =($G14/Assumptions!$E$8+($H14/Assumptions!$E$14-$G14/Assumptions!$E$8)*(O$4-2019)/6)*INDEX(Assumptions!$E$5:$E$14,MATCH(O$4,Assumptions!$A$5:$A$14,0)) -> 18963275 | P14: =($G14/Assumptions!$E$8+($H14/Assumptions!$E$14-$G14/Assumptions!$E$8)*(P$4-2019)/6)*INDEX(Assumptions!$E$5:$E$14,MATCH(P$4,Assumptions!$A$5:$A$14,0)) -> 20658289 | Q14: =($G14/Assumptions!$E$8+($H14/Assumptions!$E$14-$G14/Assumptions!$E$8)*(Q$4-2019)/6)*INDEX(Assumptions!$E$5:$E$14,MATCH(Q$4,Assumptions!$A$5:$A$14,0)) -> 23306391 | R14: =($G14/Assumptions!$E$8+($H14/Assumptions!$E$14-$G14/Assumptions!$E$8)*(R$4-2019)/6)*INDEX(Assumptions!$E$5:$E$14,MATCH(R$4,Assumptions!$A$5:$A$14,0)) -> 24190491 | ... T14: =($G14/Assumptions!$E$8+($H14/Assumptions!$E$14-$G14/Assumptions!$E$8)*(T$4-2019)/6)*INDEX(Assumptions!$E$5:$E$14,MATCH(T$4,Assumptions!$A$5:$A$14,0)) -> 24297002
A15: Bland County | B15: County | C15: 378149 | D15: 607811 | E15: 784038 | F15: 797014 | G15: =C15+E15 -> 1162187 | H15: =D15+F15 -> 1404825 | I15: =IFERROR((D15/C15)^(1/6)-1,0) -> 0.082308161 | J15: =IFERROR((H15/G15)^(1/6)-1,0) -> 0.032106157 | K15: =($G15/Assumptions!$E$8+($H15/Assumptions!$E$14-$G15/Assumptions!$E$8)*(K$4-2019)/6)*INDEX(Assumptions!$E$5:$E$14,MATCH(K$4,Assumptions!$A$5:$A$14,0)) -> 1118092.9 | L15: =($G15/Assumptions!$E$8+($H15/Assumptions!$E$14-$G15/Assumptions!$E$8)*(L$4-2019)/6)*INDEX(Assumptions!$E$5:$E$14,MATCH(L$4,Assumptions!$A$5:$A$14,0)) -> 1124973.3 | M15: =($G15/Assumptions!$E$8+($H15/Assumptions!$E$14-$G15/Assumptions!$E$8)*(M$4-2019)/6)*INDEX(Assumptions!$E$5:$E$14,MATCH(M$4,Assumptions!$A$5:$A$14,0)) -> 1135102.6 | N15: =($G15/Assumptions!$E$8+($H15/Assumptions!$E$14-$G15/Assumptions!$E$8)*(N$4-2019)/6)*INDEX(Assumptions!$E$5:$E$14,MATCH(N$4,Assumptions!$A$5:$A$14,0)) -> 1162187 | O15: =($G15/Assumptions!$E$8+($H15/Assumptions!$E$14-$G15/Assumptions!$E$8)*(O$4-2019)/6)*INDEX(Assumptions!$E$5:$E$14,MATCH(O$4,Assumptions!$A$5:$A$14,0)) -> 1202825 | P15: =($G15/Assumptions!$E$8+($H15/Assumptions!$E$14-$G15/Assumptions!$E$8)*(P$4-2019)/6)*INDEX(Assumptions!$E$5:$E$14,MATCH(P$4,Assumptions!$A$5:$A$14,0)) -> 1286954.3 | Q15: =($G15/Assumptions!$E$8+($H15/Assumptions!$E$14-$G15/Assumptions!$E$8)*(Q$4-2019)/6)*INDEX(Assumptions!$E$5:$E$14,MATCH(Q$4,Assumptions!$A$5:$A$14,0)) -> 1425658.2 | R15: =($G15/Assumptions!$E$8+($H15/Assumptions!$E$14-$G15/Assumptions!$E$8)*(R$4-2019)/6)*INDEX(Assumptions!$E$5:$E$14,MATCH(R$4,Assumptions!$A$5:$A$14,0)) -> 1452596.3 | ... T15: =($G15/Assumptions!$E$8+($H15/Assumptions!$E$14-$G15/Assumptions!$E$8)*(T$4-2019)/6)*INDEX(Assumptions!$E$5:$E$14,MATCH(T$4,Assumptions!$A$5:$A$14,0)) -> 1404825
A16: Botetourt County | B16: County | C16: 3006691 | D16: 4739530 | E16: 5018335 | F16: 5714334 | G16: =C16+E16 -> 8025026 | H16: =D16+F16 -> 10453864 | I16: =IFERROR((D16/C16)^(1/6)-1,0) -> 0.078800353 | J16: =IFERROR((H16/G16)^(1/6)-1,0) -> 0.0450532 | K16: =($G16/Assumptions!$E$8+($H16/Assumptions!$E$14-$G16/Assumptions!$E$8)*(K$4-2019)/6)*INDEX(Assumptions!$E$5:$E$14,MATCH(K$4,Assumptions!$A$5:$A$14,0)) -> 7460549.4 | L16: =($G16/Assumptions!$E$8+($H16/Assumptions!$E$14-$G16/Assumptions!$E$8)*(L$4-2019)/6)*INDEX(Assumptions!$E$5:$E$14,MATCH(L$4,Assumptions!$A$5:$A$14,0)) -> 7591048.7 | M16: =($G16/Assumptions!$E$8+($H16/Assumptions!$E$14-$G16/Assumptions!$E$8)*(M$4-2019)/6)*INDEX(Assumptions!$E$5:$E$14,MATCH(M$4,Assumptions!$A$5:$A$14,0)) -> 7747344.5 | N16: =($G16/Assumptions!$E$8+($H16/Assumptions!$E$14-$G16/Assumptions!$E$8)*(N$4-2019)/6)*INDEX(Assumptions!$E$5:$E$14,MATCH(N$4,Assumptions!$A$5:$A$14,0)) -> 8025026 | O16: =($G16/Assumptions!$E$8+($H16/Assumptions!$E$14-$G16/Assumptions!$E$8)*(O$4-2019)/6)*INDEX(Assumptions!$E$5:$E$14,MATCH(O$4,Assumptions!$A$5:$A$14,0)) -> 8404718.3 | P16: =($G16/Assumptions!$E$8+($H16/Assumptions!$E$14-$G16/Assumptions!$E$8)*(P$4-2019)/6)*INDEX(Assumptions!$E$5:$E$14,MATCH(P$4,Assumptions!$A$5:$A$14,0)) -> 9101960.5 | Q16: =($G16/Assumptions!$E$8+($H16/Assumptions!$E$14-$G16/Assumptions!$E$8)*(Q$4-2019)/6)*INDEX(Assumptions!$E$5:$E$14,MATCH(Q$4,Assumptions!$A$5:$A$14,0)) -> 10208044 | R16: =($G16/Assumptions!$E$8+($H16/Assumptions!$E$14-$G16/Assumptions!$E$8)*(R$4-2019)/6)*INDEX(Assumptions!$E$5:$E$14,MATCH(R$4,Assumptions!$A$5:$A$14,0)) -> 10532588 | ... T16: =($G16/Assumptions!$E$8+($H16/Assumptions!$E$14-$G16/Assumptions!$E$8)*(T$4-2019)/6)*INDEX(Assumptions!$E$5:$E$14,MATCH(T$4,Assumptions!$A$5:$A$14,0)) -> 10453864
... A137: Winchester City | B137: City | C137: 9951036 | D137: 13385081 | E137: 4037675 | F137: 4875119 | G137: =C137+E137 -> 13988711 | H137: =D137+F137 -> 18260200 | I137: =IFERROR((D137/C137)^(1/6)-1,0) -> 0.050651741 | J137: =IFERROR((H137/G137)^(1/6)-1,0) -> 0.045413182 | K137: =($G137/Assumptions!$E$8+($H137/Assumptions!$E$14-$G137/Assumptions!$E$8)*(K$4-2019)/6)*INDEX(Assumptions!$E$5:$E$14,MATCH(K$4,Assumptions!$A$5:$A$14,0)) -> 12991743 | L137: =($G137/Assumptions!$E$8+($H137/Assumptions!$E$14-$G137/Assumptions!$E$8)*(L$4-2019)/6)*INDEX(Assumptions!$E$5:$E$14,MATCH(L$4,Assumptions!$A$5:$A$14,0)) -> 13223373 | M137: =($G137/Assumptions!$E$8+($H137/Assumptions!$E$14-$G137/Assumptions!$E$8)*(M$4-2019)/6)*INDEX(Assumptions!$E$5:$E$14,MATCH(M$4,Assumptions!$A$5:$A$14,0)) -> 13500138 | N137: =($G137/Assumptions!$E$8+($H137/Assumptions!$E$14-$G137/Assumptions!$E$8)*(N$4-2019)/6)*INDEX(Assumptions!$E$5:$E$14,MATCH(N$4,Assumptions!$A$5:$A$14,0)) -> 13988711 | O137: =($G137/Assumptions!$E$8+($H137/Assumptions!$E$14-$G137/Assumptions!$E$8)*(O$4-2019)/6)*INDEX(Assumptions!$E$5:$E$14,MATCH(O$4,Assumptions!$A$5:$A$14,0)) -> 14655524 | P137: =($G137/Assumptions!$E$8+($H137/Assumptions!$E$14-$G137/Assumptions!$E$8)*(P$4-2019)/6)*INDEX(Assumptions!$E$5:$E$14,MATCH(P$4,Assumptions!$A$5:$A$14,0)) -> 15876731 | Q137: =($G137/Assumptions!$E$8+($H137/Assumptions!$E$14-$G137/Assumptions!$E$8)*(Q$4-2019)/6)*INDEX(Assumptions!$E$5:$E$14,MATCH(Q$4,Assumptions!$A$5:$A$14,0)) -> 17812205 | R137: =($G137/Assumptions!$E$8+($H137/Assumptions!$E$14-$G137/Assumptions!$E$8)*(R$4-2019)/6)*INDEX(Assumptions!$E$5:$E$14,MATCH(R$4,Assumptions!$A$5:$A$14,0)) -> 18384861 | ... T137: =($G137/Assumptions!$E$8+($H137/Assumptions!$E$14-$G137/Assumptions!$E$8)*(T$4-2019)/6)*INDEX(Assumptions!$E$5:$E$14,MATCH(T$4,Assumptions!$A$5:$A$14,0)) -> 18260200
A138: TOTAL — all localities | C138: =SUM(C5:C137) -> 1292803735 | D138: =SUM(D5:D137) -> 1876912593 | E138: =SUM(E5:E137) -> 1290310946 | F138: =SUM(F5:F137) -> 1564222649 | G138: =SUM(G5:G137) -> 2583114681 | H138: =SUM(H5:H137) -> 3441135242 | K138: =SUM(K5:K137) -> 2.3751155e+09 | L138: =SUM(L5:L137) -> 2.4255168e+09 | M138: =SUM(M5:M137) -> 2.4845618e+09 | N138: =SUM(N5:N137) -> 2583114681 | O138: =SUM(O5:O137) -> 2.715355e+09 | P138: =SUM(P5:P137) -> 2.951553e+09 | Q138: =SUM(Q5:Q137) -> 3.3225869e+09 | R138: =SUM(R5:R137) -> 3.4410673e+09 | ... T138: =SUM(T5:T137) -> 3441135242

Sheet Projection FY26-FY45
A1: Projected Retail Sales Tax Distribution by Locality — FY2026 to FY2045
A2: Total of both streams (state 1% education share + 1% local option), nominal dollars. Growth rate per locality is built from the Assumptions tab — change the levers there, not here.
A4: Locality | B4: Type | C4: FY2025 Total ($) — actual | D4: Applied annual growth rate | E4: 2026 | F4: 2027 | G4: 2028 | H4: 2029 | I4: 2030 | J4: 2031 | K4: 2032 | L4: 2033 | M4: 2034 | N4: 2035 | O4: 2036 | P4: 2037 | Q4: 2038 | R4: 2039 | S4: 2040 | T4: 2041 | U4: 2042 | V4: 2043 | W4: 2044 | X4: 2045
A5: ='Historical FY16-FY25'!A5 -> Accomack County | B5: ='Historical FY16-FY25'!B5 -> County | C5: ='Historical FY16-FY25'!H5 -> 11822596 | D5: =MIN(Assumptions!$B$27,MAX(Assumptions!$B$26,Assumptions!$B$24+Assumptions!$B$25*('Historical FY16-FY25'!J5-Assumptions!$B$20))) -> 0.039494374 | E5: =$C5*(1+$D5)^(E$4-2025) -> 12289522 | F5: =$C5*(1+$D5)^(F$4-2025) -> 12774889 | G5: =$C5*(1+$D5)^(G$4-2025) -> 13279425 | H5: =$C5*(1+$D5)^(H$4-2025) -> 13803888 | I5: =$C5*(1+$D5)^(I$4-2025) -> 14349064 | J5: =$C5*(1+$D5)^(J$4-2025) -> 14915771 | K5: =$C5*(1+$D5)^(K$4-2025) -> 15504860 | L5: =$C5*(1+$D5)^(L$4-2025) -> 16117215 | ... X5: =$C5*(1+$D5)^(X$4-2025) -> 25654037
A6: ='Historical FY16-FY25'!A6 -> Albemarle County | B6: ='Historical FY16-FY25'!B6 -> County | C6: ='Historical FY16-FY25'!H6 -> 45437928 | D6: =MIN(Assumptions!$B$27,MAX(Assumptions!$B$26,Assumptions!$B$24+Assumptions!$B$25*('Historical FY16-FY25'!J6-Assumptions!$B$20))) -> 0.049296427 | E6: =$C6*(1+$D6)^(E$4-2025) -> 47677855 | F6: =$C6*(1+$D6)^(F$4-2025) -> 50028203 | G6: =$C6*(1+$D6)^(G$4-2025) -> 52494415 | H6: =$C6*(1+$D6)^(H$4-2025) -> 55082202 | I6: =$C6*(1+$D6)^(I$4-2025) -> 57797558 | J6: =$C6*(1+$D6)^(J$4-2025) -> 60646771 | K6: =$C6*(1+$D6)^(K$4-2025) -> 63636440 | L6: =$C6*(1+$D6)^(L$4-2025) -> 66773489 | ... X6: =$C6*(1+$D6)^(X$4-2025) -> 1.1895492e+08
A7: ='Historical FY16-FY25'!A7 -> Alleghany County | B7: ='Historical FY16-FY25'!B7 -> County | C7: ='Historical FY16-FY25'!H7 -> 3604117 | D7: =MIN(Assumptions!$B$27,MAX(Assumptions!$B$26,Assumptions!$B$24+Assumptions!$B$25*('Historical FY16-FY25'!J7-Assumptions!$B$20))) -> 0.030452822 | E7: =$C7*(1+$D7)^(E$4-2025) -> 3713872.5 | F7: =$C7*(1+$D7)^(F$4-2025) -> 3826970.4 | G7: =$C7*(1+$D7)^(G$4-2025) -> 3943512.5 | H7: =$C7*(1+$D7)^(H$4-2025) -> 4063603.6 | I7: =$C7*(1+$D7)^(I$4-2025) -> 4187351.8 | J7: =$C7*(1+$D7)^(J$4-2025) -> 4314868.4 | K7: =$C7*(1+$D7)^(K$4-2025) -> 4446268.4 | L7: =$C7*(1+$D7)^(L$4-2025) -> 4581669.8 | ... X7: =$C7*(1+$D7)^(X$4-2025) -> 6566911.1
A8: ='Historical FY16-FY25'!A8 -> Amelia County | B8: ='Historical FY16-FY25'!B8 -> County | C8: ='Historical FY16-FY25'!H8 -> 3693984 | D8: =MIN(Assumptions!$B$27,MAX(Assumptions!$B$26,Assumptions!$B$24+Assumptions!$B$25*('Historical FY16-FY25'!J8-Assumptions!$B$20))) -> 0.046320239 | E8: =$C8*(1+$D8)^(E$4-2025) -> 3865090.2 | F8: =$C8*(1+$D8)^(F$4-2025) -> 4044122.1 | G8: =$C8*(1+$D8)^(G$4-2025) -> 4231446.8 | H8: =$C8*(1+$D8)^(H$4-2025) -> 4427448.5 | I8: =$C8*(1+$D8)^(I$4-2025) -> 4632528.9 | J8: =$C8*(1+$D8)^(J$4-2025) -> 4847108.8 | K8: =$C8*(1+$D8)^(K$4-2025) -> 5071628 | L8: =$C8*(1+$D8)^(L$4-2025) -> 5306547 | ... X8: =$C8*(1+$D8)^(X$4-2025) -> 9136661.4
A9: ='Historical FY16-FY25'!A9 -> Amherst County | B9: ='Historical FY16-FY25'!B9 -> County | C9: ='Historical FY16-FY25'!H9 -> 9873279 | D9: =MIN(Assumptions!$B$27,MAX(Assumptions!$B$26,Assumptions!$B$24+Assumptions!$B$25*('Historical FY16-FY25'!J9-Assumptions!$B$20))) -> 0.04445156 | E9: =$C9*(1+$D9)^(E$4-2025) -> 10312162 | F9: =$C9*(1+$D9)^(F$4-2025) -> 10770553 | G9: =$C9*(1+$D9)^(G$4-2025) -> 11249321 | H9: =$C9*(1+$D9)^(H$4-2025) -> 11749371 | I9: =$C9*(1+$D9)^(I$4-2025) -> 12271649 | J9: =$C9*(1+$D9)^(J$4-2025) -> 12817143 | K9: =$C9*(1+$D9)^(K$4-2025) -> 13386885 | L9: =$C9*(1+$D9)^(L$4-2025) -> 13981953 | ... X9: =$C9*(1+$D9)^(X$4-2025) -> 23562831
A10: ='Historical FY16-FY25'!A10 -> Appomattox County | B10: ='Historical FY16-FY25'!B10 -> County | C10: ='Historical FY16-FY25'!H10 -> 5150967 | D10: =MIN(Assumptions!$B$27,MAX(Assumptions!$B$26,Assumptions!$B$24+Assumptions!$B$25*('Historical FY16-FY25'!J10-Assumptions!$B$20))) -> 0.047968776 | E10: =$C10*(1+$D10)^(E$4-2025) -> 5398052.6 | F10: =$C10*(1+$D10)^(F$4-2025) -> 5656990.6 | G10: =$C10*(1+$D10)^(G$4-2025) -> 5928349.5 | H10: =$C10*(1+$D10)^(H$4-2025) -> 6212725.1 | I10: =$C10*(1+$D10)^(I$4-2025) -> 6510741.9 | J10: =$C10*(1+$D10)^(J$4-2025) -> 6823054.3 | K10: =$C10*(1+$D10)^(K$4-2025) -> 7150347.8 | L10: =$C10*(1+$D10)^(L$4-2025) -> 7493341.3 | ... X10: =$C10*(1+$D10)^(X$4-2025) -> 13147877
A11: ='Historical FY16-FY25'!A11 -> Arlington County | B11: ='Historical FY16-FY25'!B11 -> County | C11: ='Historical FY16-FY25'!H11 -> 89276918 | D11: =MIN(Assumptions!$B$27,MAX(Assumptions!$B$26,Assumptions!$B$24+Assumptions!$B$25*('Historical FY16-FY25'!J11-Assumptions!$B$20))) -> 0.041409246 | E11: =$C11*(1+$D11)^(E$4-2025) -> 92973808 | F11: =$C11*(1+$D11)^(F$4-2025) -> 96823783 | G11: =$C11*(1+$D11)^(G$4-2025) -> 1.0083318e+08 | H11: =$C11*(1+$D11)^(H$4-2025) -> 1.0500861e+08 | I11: =$C11*(1+$D11)^(I$4-2025) -> 1.0935694e+08 | J11: =$C11*(1+$D11)^(J$4-2025) -> 1.1388532e+08 | K11: =$C11*(1+$D11)^(K$4-2025) -> 1.1860123e+08 | L11: =$C11*(1+$D11)^(L$4-2025) -> 1.2351242e+08 | ... X11: =$C11*(1+$D11)^(X$4-2025) -> 2.0098691e+08
A12: ='Historical FY16-FY25'!A12 -> Augusta County | B12: ='Historical FY16-FY25'!B12 -> County | C12: ='Historical FY16-FY25'!H12 -> 22914063 | D12: =MIN(Assumptions!$B$27,MAX(Assumptions!$B$26,Assumptions!$B$24+Assumptions!$B$25*('Historical FY16-FY25'!J12-Assumptions!$B$20))) -> 0.046558955 | E12: =$C12*(1+$D12)^(E$4-2025) -> 23980918 | F12: =$C12*(1+$D12)^(F$4-2025) -> 25097444 | G12: =$C12*(1+$D12)^(G$4-2025) -> 26265955 | H12: =$C12*(1+$D12)^(H$4-2025) -> 27488870 | I12: =$C12*(1+$D12)^(I$4-2025) -> 28768724 | J12: =$C12*(1+$D12)^(J$4-2025) -> 30108165 | K12: =$C12*(1+$D12)^(K$4-2025) -> 31509970 | L12: =$C12*(1+$D12)^(L$4-2025) -> 32977041 | ... X12: =$C12*(1+$D12)^(X$4-2025) -> 56934572
A13: ='Historical FY16-FY25'!A13 -> Bath County | B13: ='Historical FY16-FY25'!B13 -> County | C13: ='Historical FY16-FY25'!H13 -> 1885159 | D13: =MIN(Assumptions!$B$27,MAX(Assumptions!$B$26,Assumptions!$B$24+Assumptions!$B$25*('Historical FY16-FY25'!J13-Assumptions!$B$20))) -> 0.048539703 | E13: =$C13*(1+$D13)^(E$4-2025) -> 1976664.1 | F13: =$C13*(1+$D13)^(F$4-2025) -> 2072610.7 | G13: =$C13*(1+$D13)^(G$4-2025) -> 2173214.7 | H13: =$C13*(1+$D13)^(H$4-2025) -> 2278701.8 | I13: =$C13*(1+$D13)^(I$4-2025) -> 2389309.4 | J13: =$C13*(1+$D13)^(J$4-2025) -> 2505285.7 | K13: =$C13*(1+$D13)^(K$4-2025) -> 2626891.6 | L13: =$C13*(1+$D13)^(L$4-2025) -> 2754400.1 | ... X13: =$C13*(1+$D13)^(X$4-2025) -> 4864582.6
A14: ='Historical FY16-FY25'!A14 -> Bedford County | B14: ='Historical FY16-FY25'!B14 -> County | C14: ='Historical FY16-FY25'!H14 -> 24297002 | D14: =MIN(Assumptions!$B$27,MAX(Assumptions!$B$26,Assumptions!$B$24+Assumptions!$B$25*('Historical FY16-FY25'!J14-Assumptions!$B$20))) -> 0.045642297 | E14: =$C14*(1+$D14)^(E$4-2025) -> 25405973 | F14: =$C14*(1+$D14)^(F$4-2025) -> 26565560 | G14: =$C14*(1+$D14)^(G$4-2025) -> 27778073 | H14: =$C14*(1+$D14)^(H$4-2025) -> 29045928 | I14: =$C14*(1+$D14)^(I$4-2025) -> 30371651 | J14: =$C14*(1+$D14)^(J$4-2025) -> 31757883 | K14: =$C14*(1+$D14)^(K$4-2025) -> 33207386 | L14: =$C14*(1+$D14)^(L$4-2025) -> 34723047 | ... X14: =$C14*(1+$D14)^(X$4-2025) -> 59321967
A15: ='Historical FY16-FY25'!A15 -> Bland County | B15: ='Historical FY16-FY25'!B15 -> County | C15: ='Historical FY16-FY25'!H15 -> 1404825 | D15: =MIN(Assumptions!$B$27,MAX(Assumptions!$B$26,Assumptions!$B$24+Assumptions!$B$25*('Historical FY16-FY25'!J15-Assumptions!$B$20))) -> 0.036061221 | E15: =$C15*(1+$D15)^(E$4-2025) -> 1455484.7 | F15: =$C15*(1+$D15)^(F$4-2025) -> 1507971.3 | G15: =$C15*(1+$D15)^(G$4-2025) -> 1562350.5 | H15: =$C15*(1+$D15)^(H$4-2025) -> 1618690.8 | I15: =$C15*(1+$D15)^(I$4-2025) -> 1677062.8 | J15: =$C15*(1+$D15)^(J$4-2025) -> 1737539.7 | K15: =$C15*(1+$D15)^(K$4-2025) -> 1800197.5 | L15: =$C15*(1+$D15)^(L$4-2025) -> 1865114.8 | ... X15: =$C15*(1+$D15)^(X$4-2025) -> 2853189.4
A16: ='Historical FY16-FY25'!A16 -> Botetourt County | B16: ='Historical FY16-FY25'!B16 -> County | C16: ='Historical FY16-FY25'!H16 -> 10453864 | D16: =MIN(Assumptions!$B$27,MAX(Assumptions!$B$26,Assumptions!$B$24+Assumptions!$B$25*('Historical FY16-FY25'!J16-Assumptions!$B$20))) -> 0.042534743 | E16: =$C16*(1+$D16)^(E$4-2025) -> 10898516 | F16: =$C16*(1+$D16)^(F$4-2025) -> 11362082 | G16: =$C16*(1+$D16)^(G$4-2025) -> 11845365 | H16: =$C16*(1+$D16)^(H$4-2025) -> 12349205 | I16: =$C16*(1+$D16)^(I$4-2025) -> 12874475 | J16: =$C16*(1+$D16)^(J$4-2025) -> 13422088 | K16: =$C16*(1+$D16)^(K$4-2025) -> 13992993 | L16: =$C16*(1+$D16)^(L$4-2025) -> 14588181 | ... X16: =$C16*(1+$D16)^(X$4-2025) -> 24048477
... A137: ='Historical FY16-FY25'!A137 -> Winchester City | B137: ='Historical FY16-FY25'!B137 -> City | C137: ='Historical FY16-FY25'!H137 -> 18260200 | D137: =MIN(Assumptions!$B$27,MAX(Assumptions!$B$26,Assumptions!$B$24+Assumptions!$B$25*('Historical FY16-FY25'!J137-Assumptions!$B$20))) -> 0.042714733 | E137: =$C137*(1+$D137)^(E$4-2025) -> 19040180 | F137: =$C137*(1+$D137)^(F$4-2025) -> 19853476 | G137: =$C137*(1+$D137)^(G$4-2025) -> 20701512 | H137: =$C137*(1+$D137)^(H$4-2025) -> 21585771 | I137: =$C137*(1+$D137)^(I$4-2025) -> 22507802 | J137: =$C137*(1+$D137)^(J$4-2025) -> 23469216 | K137: =$C137*(1+$D137)^(K$4-2025) -> 24471698 | L137: =$C137*(1+$D137)^(L$4-2025) -> 25517000 | ... X137: =$C137*(1+$D137)^(X$4-2025) -> 42151762
A138: TOTAL — all localities | C138: =SUM(C5:C137) -> 3441135242 | E138: =SUM(E5:E137) -> 3.5948234e+09 | F138: =SUM(F5:F137) -> 3.7554672e+09 | G138: =SUM(G5:G137) -> 3.9233859e+09 | H138: =SUM(H5:H137) -> 4.0989134e+09 | I138: =SUM(I5:I137) -> 4.2823992e+09 | J138: =SUM(J5:J137) -> 4.4742092e+09 | K138: =SUM(K5:K137) -> 4.674726e+09 | L138: =SUM(L5:L137) -> 4.8843506e+09 | ... X138: =SUM(X5:X137) -> 8.2845453e+09

Sheet Schools 1pct Profile
A1: Dedicated 1% Sales Tax for Schools — Locality Profile
A2: Main columns model a NEW 1% local sales tax for schools (Va. Code 58.1-605.1), estimated at the same yield as the existing 1% Local Option because it shares the base and the point-of-sale distribution.
A3: Final column shows the other reading of the request: setting aside 1% OF projected sales tax revenue. Read the caveats on the Read Me tab before circulating any of these numbers.
A5: Locality | B5: Type | C5: FY2025 Local Option 1% collected ($) — actual | D5: Applied annual growth rate | E5: Est. FY2027 yield of new 1% school levy ($) | F5: Est. FY2035 yield ($) | G5: Est. FY2045 yield ($) | H5: 20-year cumulative FY2026-FY2045 ($) | I5: Average per year over 20 yrs ($) | J5: Share of statewide school-levy pot | K5: ALT READING: 1% of FY2026 projected total distribution ($)
A6: ='Historical FY16-FY25'!A5 -> Accomack County | B6: ='Historical FY16-FY25'!B5 -> County | C6: ='Historical FY16-FY25'!D5 -> 6374893 | D6: ='Projection FY26-FY45'!D5 -> 0.039494374 | E6: =$C6*(Assumptions!$B$28/Assumptions!$B$29)*(1+$D6)^2 -> 6888381.4 | F6: =$C6*(Assumptions!$B$28/Assumptions!$B$29)*(1+$D6)^10 -> 9390621.4 | G6: =$C6*(Assumptions!$B$28/Assumptions!$B$29)*(1+$D6)^20 -> 13832980 | H6: =IF($D6=0,$C6*(Assumptions!$B$28/Assumptions!$B$29)*20,$C6*(Assumptions!$B$28/Assumptions!$B$29)*(1+$D6)*((1+$D6)^20-1)/$D6) -> 1.9629732e+08 | I6: =H6/20 -> 9814866.2 | J6: =IFERROR(H6/$H$139,0) -> 0.0031985218 | K6: ='Projection FY26-FY45'!E5*0.01 -> 122895.22
A7: ='Historical FY16-FY25'!A6 -> Albemarle County | B7: ='Historical FY16-FY25'!B6 -> County | C7: ='Historical FY16-FY25'!D6 -> 26225183 | D7: ='Projection FY26-FY45'!D6 -> 0.049296427 | E7: =$C7*(Assumptions!$B$28/Assumptions!$B$29)*(1+$D7)^2 -> 28874529 | F7: =$C7*(Assumptions!$B$28/Assumptions!$B$29)*(1+$D7)^10 -> 42432681 | G7: =$C7*(Assumptions!$B$28/Assumptions!$B$29)*(1+$D7)^20 -> 68656618 | H7: =IF($D7=0,$C7*(Assumptions!$B$28/Assumptions!$B$29)*20,$C7*(Assumptions!$B$28/Assumptions!$B$29)*(1+$D7)*((1+$D7)^20-1)/$D7) -> 9.0317202e+08 | I7: =H7/20 -> 45158601 | J7: =IFERROR(H7/$H$139,0) -> 0.01471653 | K7: ='Projection FY26-FY45'!E6*0.01 -> 476778.55
A8: ='Historical FY16-FY25'!A7 -> Alleghany County | B8: ='Historical FY16-FY25'!B7 -> County | C8: ='Historical FY16-FY25'!D7 -> 1288843 | D8: ='Projection FY26-FY45'!D7 -> 0.030452822 | E8: =$C8*(Assumptions!$B$28/Assumptions!$B$29)*(1+$D8)^2 -> 1368536.1 | F8: =$C8*(Assumptions!$B$28/Assumptions!$B$29)*(1+$D8)^10 -> 1739727.2 | G8: =$C8*(Assumptions!$B$28/Assumptions!$B$29)*(1+$D8)^20 -> 2348347 | H8: =IF($D8=0,$C8*(Assumptions!$B$28/Assumptions!$B$29)*20,$C8*(Assumptions!$B$28/Assumptions!$B$29)*(1+$D8)*((1+$D8)^20-1)/$D8) -> 35851158 | I8: =H8/20 -> 1792557.9 | J8: =IFERROR(H8/$H$139,0) -> 0.00058416848 | K8: ='Projection FY26-FY45'!E7*0.01 -> 37138.725
A9: ='Historical FY16-FY25'!A8 -> Amelia County | B9: ='Historical FY16-FY25'!B8 -> County | C9: ='Historical FY16-FY25'!D8 -> 1519698 | D9: ='Projection FY26-FY45'!D8 -> 0.046320239 | E9: =$C9*(Assumptions!$B$28/Assumptions!$B$29)*(1+$D9)^2 -> 1663744.2 | F9: =$C9*(Assumptions!$B$28/Assumptions!$B$29)*(1+$D9)^10 -> 2390031.1 | G9: =$C9*(Assumptions!$B$28/Assumptions!$B$29)*(1+$D9)^20 -> 3758805.1 | H9: =IF($D9=0,$C9*(Assumptions!$B$28/Assumptions!$B$29)*20,$C9*(Assumptions!$B$28/Assumptions!$B$29)*(1+$D9)*((1+$D9)^20-1)/$D9) -> 50578822 | I9: =H9/20 -> 2528941.1 | J9: =IFERROR(H9/$H$139,0) -> 0.00082414503 | K9: ='Projection FY26-FY45'!E8*0.01 -> 38650.902
A10: ='Historical FY16-FY25'!A9 -> Amherst County | B10: ='Historical FY16-FY25'!B9 -> County | C10: ='Historical FY16-FY25'!D9 -> 4726734 | D10: ='Projection FY26-FY45'!D9 -> 0.04445156 | E10: =$C10*(Assumptions!$B$28/Assumptions!$B$29)*(1+$D10)^2 -> 5156295.1 | F10: =$C10*(Assumptions!$B$28/Assumptions!$B$29)*(1+$D10)^10 -> 7302039.7 | G10: =$C10*(Assumptions!$B$28/Assumptions!$B$29)*(1+$D10)^20 -> 11280471 | H10: =IF($D10=0,$C10*(Assumptions!$B$28/Assumptions!$B$29)*20,$C10*(Assumptions!$B$28/Assumptions!$B$29)*(1+$D10)*((1+$D10)^20-1)/$D10) -> 1.5398921e+08 | I10: =H10/20 -> 7699460.4 | J10: =IFERROR(H10/$H$139,0) -> 0.0025091419 | K10: ='Projection FY26-FY45'!E9*0.01 -> 103121.62
A11: ='Historical FY16-FY25'!A10 -> Appomattox County | B11: ='Historical FY16-FY25'!B10 -> County | C11: ='Historical FY16-FY25'!D10 -> 2192135 | D11: ='Projection FY26-FY45'!D10 -> 0.047968776 | E11: =$C11*(Assumptions!$B$28/Assumptions!$B$29)*(1+$D11)^2 -> 2407487.2 | F11: =$C11*(Assumptions!$B$28/Assumptions!$B$29)*(1+$D11)^10 -> 3502278.9 | G11: =$C11*(Assumptions!$B$28/Assumptions!$B$29)*(1+$D11)^20 -> 5595438.9 | H11: =IF($D11=0,$C11*(Assumptions!$B$28/Assumptions!$B$29)*20,$C11*(Assumptions!$B$28/Assumptions!$B$29)*(1+$D11)*((1+$D11)^20-1)/$D11) -> 74351620 | I11: =H11/20 -> 3717581 | J11: =IFERROR(H11/$H$139,0) -> 0.0012115055 | K11: ='Projection FY26-FY45'!E10*0.01 -> 53980.526
A12: ='Historical FY16-FY25'!A11 -> Arlington County | B12: ='Historical FY16-FY25'!B11 -> County | C12: ='Historical FY16-FY25'!D11 -> 55138617 | D12: ='Projection FY26-FY45'!D11 -> 0.041409246 | E12: =$C12*(Assumptions!$B$28/Assumptions!$B$29)*(1+$D12)^2 -> 59799662 | F12: =$C12*(Assumptions!$B$28/Assumptions!$B$29)*(1+$D12)^10 -> 82731360 | G12: =$C12*(Assumptions!$B$28/Assumptions!$B$29)*(1+$D12)^20 -> 1.241322e+08 | H12: =IF($D12=0,$C12*(Assumptions!$B$28/Assumptions!$B$29)*20,$C12*(Assumptions!$B$28/Assumptions!$B$29)*(1+$D12)*((1+$D12)^20-1)/$D12) -> 1.7351332e+09 | I12: =H12/20 -> 86756658 | J12: =IFERROR(H12/$H$139,0) -> 0.02827273 | K12: ='Projection FY26-FY45'!E11*0.01 -> 929738.08
A13: ='Historical FY16-FY25'!A12 -> Augusta County | B13: ='Historical FY16-FY25'!B12 -> County | C13: ='Historical FY16-FY25'!D12 -> 9993991 | D13: ='Projection FY26-FY45'!D12 -> 0.046558955 | E13: =$C13*(Assumptions!$B$28/Assumptions!$B$29)*(1+$D13)^2 -> 10946275 | F13: =$C13*(Assumptions!$B$28/Assumptions!$B$29)*(1+$D13)^10 -> 15753459 | G13: =$C13*(Assumptions!$B$28/Assumptions!$B$29)*(1+$D13)^20 -> 24832070 | H13: =IF($D13=0,$C13*(Assumptions!$B$28/Assumptions!$B$29)*20,$C13*(Assumptions!$B$28/Assumptions!$B$29)*(1+$D13)*((1+$D13)^20-1)/$D13) -> 3.3353249e+08 | I13: =H13/20 -> 16676624 | J13: =IFERROR(H13/$H$139,0) -> 0.0054346687 | K13: ='Projection FY26-FY45'!E12*0.01 -> 239809.18
A14: ='Historical FY16-FY25'!A13 -> Bath County | B14: ='Historical FY16-FY25'!B13 -> County | C14: ='Historical FY16-FY25'!D13 -> 1312575 | D14: ='Projection FY26-FY45'!D13 -> 0.048539703 | E14: =$C14*(Assumptions!$B$28/Assumptions!$B$29)*(1+$D14)^2 -> 1443091.6 | F14: =$C14*(Assumptions!$B$28/Assumptions!$B$29)*(1+$D14)^10 -> 2108496.7 | G14: =$C14*(Assumptions!$B$28/Assumptions!$B$29)*(1+$D14)^20 -> 3387050.9 | H14: =IF($D14=0,$C14*(Assumptions!$B$28/Assumptions!$B$29)*20,$C14*(Assumptions!$B$28/Assumptions!$B$29)*(1+$D14)*((1+$D14)^20-1)/$D14) -> 44812189 | I14: =H14/20 -> 2240609.4 | J14: =IFERROR(H14/$H$139,0) -> 0.00073018195 | K14: ='Projection FY26-FY45'!E13*0.01 -> 19766.641
A15: ='Historical FY16-FY25'!A14 -> Bedford County | B15: ='Historical FY16-FY25'!B14 -> County | C15: ='Historical FY16-FY25'!D14 -> 10883951 | D15: ='Projection FY26-FY45'!D14 -> 0.045642297 | E15: =$C15*(Assumptions!$B$28/Assumptions!$B$29)*(1+$D15)^2 -> 11900162 | F15: =$C15*(Assumptions!$B$28/Assumptions!$B$29)*(1+$D15)^10 -> 17006620 | G15: =$C15*(Assumptions!$B$28/Assumptions!$B$29)*(1+$D15)^20 -> 26573541 | H15: =IF($D15=0,$C15*(Assumptions!$B$28/Assumptions!$B$29)*20,$C15*(Assumptions!$B$28/Assumptions!$B$29)*(1+$D15)*((1+$D15)^20-1)/$D15) -> 3.5944069e+08 | I15: =H15/20 -> 17972035 | J15: =IFERROR(H15/$H$139,0) -> 0.0058568241 | K15: ='Projection FY26-FY45'!E14*0.01 -> 254059.73
A16: ='Historical FY16-FY25'!A15 -> Bland County | B16: ='Historical FY16-FY25'!B15 -> County | C16: ='Historical FY16-FY25'!D15 -> 607811 | D16: ='Projection FY26-FY45'!D15 -> 0.036061221 | E16: =$C16*(Assumptions!$B$28/Assumptions!$B$29)*(1+$D16)^2 -> 652438.22 | F16: =$C16*(Assumptions!$B$28/Assumptions!$B$29)*(1+$D16)^10 -> 866209.1 | G16: =$C16*(Assumptions!$B$28/Assumptions!$B$29)*(1+$D16)^20 -> 1234459.7 | H16: =IF($D16=0,$C16*(Assumptions!$B$28/Assumptions!$B$29)*20,$C16*(Assumptions!$B$28/Assumptions!$B$29)*(1+$D16)*((1+$D16)^20-1)/$D16) -> 18004006 | I16: =H16/20 -> 900200.32 | J16: =IFERROR(H16/$H$139,0) -> 0.00029336216 | K16: ='Projection FY26-FY45'!E15*0.01 -> 14554.847
A17: ='Historical FY16-FY25'!A16 -> Botetourt County | B17: ='Historical FY16-FY25'!B16 -> County | C17: ='Historical FY16-FY25'!D16 -> 4739530 | D17: ='Projection FY26-FY45'!D16 -> 0.042534743 | E17: =$C17*(Assumptions!$B$28/Assumptions!$B$29)*(1+$D17)^2 -> 5151294.2 | F17: =$C17*(Assumptions!$B$28/Assumptions!$B$29)*(1+$D17)^10 -> 7188539.2 | G17: =$C17*(Assumptions!$B$28/Assumptions!$B$29)*(1+$D17)^20 -> 10903000 | H17: =IF($D17=0,$C17*(Assumptions!$B$28/Assumptions!$B$29)*20,$C17*(Assumptions!$B$28/Assumptions!$B$29)*(1+$D17)*((1+$D17)^20-1)/$D17) -> 1.5106784e+08 | I17: =H17/20 -> 7553391.9 | J17: =IFERROR(H17/$H$139,0) -> 0.0024615403 | K17: ='Projection FY26-FY45'!E16*0.01 -> 108985.16
... A138: ='Historical FY16-FY25'!A137 -> Winchester City | B138: ='Historical FY16-FY25'!B137 -> City | C138: ='Historical FY16-FY25'!D137 -> 13385081 | D138: ='Projection FY26-FY45'!D137 -> 0.042714733 | E138: =$C138*(Assumptions!$B$28/Assumptions!$B$29)*(1+$D138)^2 -> 14552983 | F138: =$C138*(Assumptions!$B$28/Assumptions!$B$29)*(1+$D138)^10 -> 20336495 | G138: =$C138*(Assumptions!$B$28/Assumptions!$B$29)*(1+$D138)^20 -> 30898059 | H138: =IF($D138=0,$C138*(Assumptions!$B$28/Assumptions!$B$29)*20,$C138*(Assumptions!$B$28/Assumptions!$B$29)*(1+$D138)*((1+$D138)^20-1)/$D138) -> 4.2751152e+08 | I138: =H138/20 -> 21375576 | J138: =IFERROR(H138/$H$139,0) -> 0.0069659886 | K138: ='Projection FY26-FY45'!E137*0.01 -> 190401.8
A139: TOTAL — all localities | C139: =SUM(C6:C138) -> 1876912593 | E139: =SUM(E6:E138) -> 2.0481156e+09 | F139: =SUM(F6:F138) -> 2.9067944e+09 | G139: =SUM(G6:G138) -> 4.512886e+09 | H139: =SUM(H6:H138) -> 6.1371263e+10 | I139: =SUM(I6:I138) -> 3.0685632e+09 | J139: =SUM(J6:J138) -> 1 | K139: =SUM(K6:K138) -> 35948234
A141: How to read this tab for one locality: column E is roughly what the first full year of a new 1% school levy would
A142: raise there; column H is what it would raise across the whole 20-year window; column I is the level annual figure a
A143: bond-capacity conversation would start from. Column K is the far smaller 'set aside 1% of revenue' reading.
A144: Assumption: the school levy has the same tax base as the existing local option. Check current statute — some
A145: formulations exempt food and essential personal hygiene products, which would reduce these figures materially.
A146: A new levy requires enabling authority and, in Virginia, a local referendum. These are revenue estimates only.

Sheet Opportunity Controls
A1: Opportunity Model — Controls
A2: Everything on the Opportunity Model tab is driven from here. Yellow cells are yours to change.
A4: Access multipliers by status
A5: Status | B5: Multiplier | C5: What it means
A6: On Nov 2026 ballot | B6: 1 | C6: Referendum filed for the Nov 3, 2026 ballot. Funding decision imminent; procurement follows in 2027.
A7: Deferred, eyeing 2027 | B7: 0.8 | C7: Publicly discussed and deferred, generally to a 2027 referendum. Known intent, longer cycle.
A8: No public action found | B8: 0.7 | C8: Nothing found in reporting. UNVERIFIED, not confirmed inactive — many of these have almost certainly filed.
A9: Levying since 2020-23 | B9: =IF($B$12="Yes",$B$13,1) -> 0.35 | C9: Levying since 2020-23 under the original nine-locality authority. Capital programme already underway.
A11: Model levers
A12: Treat already-levying localities as exhausted? | B12: Yes | C12: Yes or No. Your original question said "if previous opportunities have not been exhausted" — Yes reflects that.
A13: ...if Yes, multiplier applied to them | B13: 0.35 | C13: 0 would remove them from contention entirely; 1 would treat prior adoption as no disadvantage.
A14: Capacity compression exponent | B14: 0.38 | C14: 1.00 = raw dollars, so Fairfax swamps everything. Lower values pull mid-size localities into view. 0.38 is the default.
A15: Minimum FY2027 yield to shortlist ($) | B15: 3000000 | C15: Used by the Shortlist flag. Below this, a standalone performance contract is unlikely to pencil.
A16: Scope: Counties, Cities, or Both | B16: Counties | C16: Controls which rows are ranked and which feed the Region Summary. Type one of the three words exactly.
A18: Where the status flags came from
A19: Levying since 2020-23 — Virginia Tax FY2025 Annual Report, Table 4.1 note 15. Eight localities. Solid.
A20: On Nov 2026 ballot / Deferred — only the localities named individually in reporting through 10 Aug 2026.
A21: That is 16 confirmed of the 40+ that had filed as of 7 Aug. The rest sit in 'No public action found'.
A22: The 2026-28 state budget opened Va. Code 58.1-605.1 to every county and city, effective 1 July 2026.
A23: Filing deadline for the 3 Nov 2026 ballot was 14 Aug 2026 — the authoritative list settles after that.
A24: ACTION: pull the Department of Elections referendum filings and update the Status column. Everything recalculates.
A26: What this model does not know
A27: This ranks FUNDING CAPACITY, not facility need. It carries no building age, no deferred-maintenance
A28: backlog, no existing ESCO contracts and no current energy spend — the things that decide whether a
A29: performance contract actually pencils. Layer in VDOE's school building needs and conditions survey and
A30: the list of divisions already under state energy performance contracts before this drives a call plan.

Sheet Opportunity Model
A1: Performance Contracting Opportunity — Virginia Localities
A2: Heat = opportunity score: 20-year capacity of a 1% school levy, discounted by how far the locality has already used the option. Edit the Status column as referendum filings are confirmed.
A3: Colour bands are septiles of the localities currently IN SCOPE, so the ramp always spans the full set — a red row is top-seventh of what's ranked, not an absolute threshold.
A5: Locality | B5: Type | C5: Region | D5: Status (edit me) | E5: In scope | F5: FY2027 levy yield ($) | G5: 20-yr capacity ($) | H5: Capacity index | I5: Access multiplier | J5: Opportunity score | K5: Rank | L5: Septile | M5: Priority | N5: Shortlist | O5: Score (numeric helper)
A6: ='Historical FY16-FY25'!A5 -> Accomack County | B6: ='Historical FY16-FY25'!B5 -> County | C6: Eastern Shore | D6: No public action found | E6: =IF(OR('Opportunity Controls'!$B$16="Both",AND('Opportunity Controls'!$B$16="Counties",$B6="County"),AND('Opportunity Controls'!$B$16="Cities",$B6="City")),1,0) -> 1 | F6: ='Schools 1pct Profile'!E6 -> 6888381.4 | G6: ='Schools 1pct Profile'!H6 -> 1.9629732e+08 | H6: =IFERROR(($G6/MAX($G$6:$G$138))^'Opportunity Controls'!$B$14*100,0) -> 24.609716 | I6: =IFERROR(INDEX('Opportunity Controls'!$B$6:$B$9,MATCH($D6,'Opportunity Controls'!$A$6:$A$9,0)),1) -> 0.7 | J6: =IF($E6=0,"",$H6*$I6) -> 17.226801 | K6: =IF($E6=0,"",RANK($J6,$J$6:$J$138)) -> 38 | L6: =IF($E6=0,"",8-ROUNDUP($K6/COUNT($J$6:$J$138)*7,0)) -> 5 | M6: =IF($E6=0,"",IF($L6>=6,"Priority 1",IF($L6>=5,"Priority 2",IF($L6>=3,"Watch","Low")))) -> Priority 2 | N6: =IF($E6=0,"",IF(AND($F6>='Opportunity Controls'!$B$15,$L6>=6),"YES","")) | O6: =IF($E6=0,0,$H6*$I6) -> 17.226801
A7: ='Historical FY16-FY25'!A6 -> Albemarle County | B7: ='Historical FY16-FY25'!B6 -> County | C7: Central Piedmont | D7: No public action found | E7: =IF(OR('Opportunity Controls'!$B$16="Both",AND('Opportunity Controls'!$B$16="Counties",$B7="County"),AND('Opportunity Controls'!$B$16="Cities",$B7="City")),1,0) -> 1 | F7: ='Schools 1pct Profile'!E7 -> 28874529 | G7: ='Schools 1pct Profile'!H7 -> 9.0317202e+08 | H7: =IFERROR(($G7/MAX($G$6:$G$138))^'Opportunity Controls'!$B$14*100,0) -> 43.953344 | I7: =IFERROR(INDEX('Opportunity Controls'!$B$6:$B$9,MATCH($D7,'Opportunity Controls'!$A$6:$A$9,0)),1) -> 0.7 | J7: =IF($E7=0,"",$H7*$I7) -> 30.767341 | K7: =IF($E7=0,"",RANK($J7,$J$6:$J$138)) -> 10 | L7: =IF($E7=0,"",8-ROUNDUP($K7/COUNT($J$6:$J$138)*7,0)) -> 7 | M7: =IF($E7=0,"",IF($L7>=6,"Priority 1",IF($L7>=5,"Priority 2",IF($L7>=3,"Watch","Low")))) -> Priority 1 | N7: =IF($E7=0,"",IF(AND($F7>='Opportunity Controls'!$B$15,$L7>=6),"YES","")) -> YES | O7: =IF($E7=0,0,$H7*$I7) -> 30.767341
A8: ='Historical FY16-FY25'!A7 -> Alleghany County | B8: ='Historical FY16-FY25'!B7 -> County | C8: Shenandoah Valley & Alleghany | D8: No public action found | E8: =IF(OR('Opportunity Controls'!$B$16="Both",AND('Opportunity Controls'!$B$16="Counties",$B8="County"),AND('Opportunity Controls'!$B$16="Cities",$B8="City")),1,0) -> 1 | F8: ='Schools 1pct Profile'!E8 -> 1368536.1 | G8: ='Schools 1pct Profile'!H8 -> 35851158 | H8: =IFERROR(($G8/MAX($G$6:$G$138))^'Opportunity Controls'!$B$14*100,0) -> 12.897643 | I8: =IFERROR(INDEX('Opportunity Controls'!$B$6:$B$9,MATCH($D8,'Opportunity Controls'!$A$6:$A$9,0)),1) -> 0.7 | J8: =IF($E8=0,"",$H8*$I8) -> 9.02835 | K8: =IF($E8=0,"",RANK($J8,$J$6:$J$138)) -> 80 | L8: =IF($E8=0,"",8-ROUNDUP($K8/COUNT($J$6:$J$138)*7,0)) -> 2 | M8: =IF($E8=0,"",IF($L8>=6,"Priority 1",IF($L8>=5,"Priority 2",IF($L8>=3,"Watch","Low")))) -> Low | N8: =IF($E8=0,"",IF(AND($F8>='Opportunity Controls'!$B$15,$L8>=6),"YES","")) | O8: =IF($E8=0,0,$H8*$I8) -> 9.02835
A9: ='Historical FY16-FY25'!A8 -> Amelia County | B9: ='Historical FY16-FY25'!B8 -> County | C9: Richmond Metro | D9: No public action found | E9: =IF(OR('Opportunity Controls'!$B$16="Both",AND('Opportunity Controls'!$B$16="Counties",$B9="County"),AND('Opportunity Controls'!$B$16="Cities",$B9="City")),1,0) -> 1 | F9: ='Schools 1pct Profile'!E9 -> 1663744.2 | G9: ='Schools 1pct Profile'!H9 -> 50578822 | H9: =IFERROR(($G9/MAX($G$6:$G$138))^'Opportunity Controls'!$B$14*100,0) -> 14.699659 | I9: =IFERROR(INDEX('Opportunity Controls'!$B$6:$B$9,MATCH($D9,'Opportunity Controls'!$A$6:$A$9,0)),1) -> 0.7 | J9: =IF($E9=0,"",$H9*$I9) -> 10.289761 | K9: =IF($E9=0,"",RANK($J9,$J$6:$J$138)) -> 69 | L9: =IF($E9=0,"",8-ROUNDUP($K9/COUNT($J$6:$J$138)*7,0)) -> 2 | M9: =IF($E9=0,"",IF($L9>=6,"Priority 1",IF($L9>=5,"Priority 2",IF($L9>=3,"Watch","Low")))) -> Low | N9: =IF($E9=0,"",IF(AND($F9>='Opportunity Controls'!$B$15,$L9>=6),"YES","")) | O9: =IF($E9=0,0,$H9*$I9) -> 10.289761
A10: ='Historical FY16-FY25'!A9 -> Amherst County | B10: ='Historical FY16-FY25'!B9 -> County | C10: Southside | D10: Deferred, eyeing 2027 | E10: =IF(OR('Opportunity Controls'!$B$16="Both",AND('Opportunity Controls'!$B$16="Counties",$B10="County"),AND('Opportunity Controls'!$B$16="Cities",$B10="City")),1,0) -> 1 | F10: ='Schools 1pct Profile'!E10 -> 5156295.1 | G10: ='Schools 1pct Profile'!H10 -> 1.5398921e+08 | H10: =IFERROR(($G10/MAX($G$6:$G$138))^'Opportunity Controls'!$B$14*100,0) -> 22.441168 | I10: =IFERROR(INDEX('Opportunity Controls'!$B$6:$B$9,MATCH($D10,'Opportunity Controls'!$A$6:$A$9,0)),1) -> 0.8 | J10: =IF($E10=0,"",$H10*$I10) -> 17.952934 | K10: =IF($E10=0,"",RANK($J10,$J$6:$J$138)) -> 37 | L10: =IF($E10=0,"",8-ROUNDUP($K10/COUNT($J$6:$J$138)*7,0)) -> 5 | M10: =IF($E10=0,"",IF($L10>=6,"Priority 1",IF($L10>=5,"Priority 2",IF($L10>=3,"Watch","Low")))) -> Priority 2 | N10: =IF($E10=0,"",IF(AND($F10>='Opportunity Controls'!$B$15,$L10>=6),"YES","")) | O10: =IF($E10=0,0,$H10*$I10) -> 17.952934
A11: ='Historical FY16-FY25'!A10 -> Appomattox County | B11: ='Historical FY16-FY25'!B10 -> County | C11: Southside | D11: No public action found | E11: =IF(OR('Opportunity Controls'!$B$16="Both",AND('Opportunity Controls'!$B$16="Counties",$B11="County"),AND('Opportunity Controls'!$B$16="Cities",$B11="City")),1,0) -> 1 | F11: ='Schools 1pct Profile'!E11 -> 2407487.2 | G11: ='Schools 1pct Profile'!H11 -> 74351620 | H11: =IFERROR(($G11/MAX($G$6:$G$138))^'Opportunity Controls'!$B$14*100,0) -> 17.017255 | I11: =IFERROR(INDEX('Opportunity Controls'!$B$6:$B$9,MATCH($D11,'Opportunity Controls'!$A$6:$A$9,0)),1) -> 0.7 | J11: =IF($E11=0,"",$H11*$I11) -> 11.912078 | K11: =IF($E11=0,"",RANK($J11,$J$6:$J$138)) -> 61 | L11: =IF($E11=0,"",8-ROUNDUP($K11/COUNT($J$6:$J$138)*7,0)) -> 3 | M11: =IF($E11=0,"",IF($L11>=6,"Priority 1",IF($L11>=5,"Priority 2",IF($L11>=3,"Watch","Low")))) -> Watch | N11: =IF($E11=0,"",IF(AND($F11>='Opportunity Controls'!$B$15,$L11>=6),"YES","")) | O11: =IF($E11=0,0,$H11*$I11) -> 11.912078
A12: ='Historical FY16-FY25'!A11 -> Arlington County | B12: ='Historical FY16-FY25'!B11 -> County | C12: Northern Virginia | D12: Deferred, eyeing 2027 | E12: =IF(OR('Opportunity Controls'!$B$16="Both",AND('Opportunity Controls'!$B$16="Counties",$B12="County"),AND('Opportunity Controls'!$B$16="Cities",$B12="City")),1,0) -> 1 | F12: ='Schools 1pct Profile'!E12 -> 59799662 | G12: ='Schools 1pct Profile'!H12 -> 1.7351332e+09 | H12: =IFERROR(($G12/MAX($G$6:$G$138))^'Opportunity Controls'!$B$14*100,0) -> 56.330759 | I12: =IFERROR(INDEX('Opportunity Controls'!$B$6:$B$9,MATCH($D12,'Opportunity Controls'!$A$6:$A$9,0)),1) -> 0.8 | J12: =IF($E12=0,"",$H12*$I12) -> 45.064608 | K12: =IF($E12=0,"",RANK($J12,$J$6:$J$138)) -> 6 | L12: =IF($E12=0,"",8-ROUNDUP($K12/COUNT($J$6:$J$138)*7,0)) -> 7 | M12: =IF($E12=0,"",IF($L12>=6,"Priority 1",IF($L12>=5,"Priority 2",IF($L12>=3,"Watch","Low")))) -> Priority 1 | N12: =IF($E12=0,"",IF(AND($F12>='Opportunity Controls'!$B$15,$L12>=6),"YES","")) -> YES | O12: =IF($E12=0,0,$H12*$I12) -> 45.064608
A13: ='Historical FY16-FY25'!A12 -> Augusta County | B13: ='Historical FY16-FY25'!B12 -> County | C13: Shenandoah Valley & Alleghany | D13: No public action found | E13: =IF(OR('Opportunity Controls'!$B$16="Both",AND('Opportunity Controls'!$B$16="Counties",$B13="County"),AND('Opportunity Controls'!$B$16="Cities",$B13="City")),1,0) -> 1 | F13: ='Schools 1pct Profile'!E13 -> 10946275 | G13: ='Schools 1pct Profile'!H13 -> 3.3353249e+08 | H13: =IFERROR(($G13/MAX($G$6:$G$138))^'Opportunity Controls'!$B$14*100,0) -> 30.101742 | I13: =IFERROR(INDEX('Opportunity Controls'!$B$6:$B$9,MATCH($D13,'Opportunity Controls'!$A$6:$A$9,0)),1) -> 0.7 | J13: =IF($E13=0,"",$H13*$I13) -> 21.07122 | K13: =IF($E13=0,"",RANK($J13,$J$6:$J$138)) -> 28 | L13: =IF($E13=0,"",8-ROUNDUP($K13/COUNT($J$6:$J$138)*7,0)) -> 5 | M13: =IF($E13=0,"",IF($L13>=6,"Priority 1",IF($L13>=5,"Priority 2",IF($L13>=3,"Watch","Low")))) -> Priority 2 | N13: =IF($E13=0,"",IF(AND($F13>='Opportunity Controls'!$B$15,$L13>=6),"YES","")) | O13: =IF($E13=0,0,$H13*$I13) -> 21.07122
A14: ='Historical FY16-FY25'!A13 -> Bath County | B14: ='Historical FY16-FY25'!B13 -> County | C14: Shenandoah Valley & Alleghany | D14: No public action found | E14: =IF(OR('Opportunity Controls'!$B$16="Both",AND('Opportunity Controls'!$B$16="Counties",$B14="County"),AND('Opportunity Controls'!$B$16="Cities",$B14="City")),1,0) -> 1 | F14: ='Schools 1pct Profile'!E14 -> 1443091.6 | G14: ='Schools 1pct Profile'!H14 -> 44812189 | H14: =IFERROR(($G14/MAX($G$6:$G$138))^'Opportunity Controls'!$B$14*100,0) -> 14.03879 | I14: =IFERROR(INDEX('Opportunity Controls'!$B$6:$B$9,MATCH($D14,'Opportunity Controls'!$A$6:$A$9,0)),1) -> 0.7 | J14: =IF($E14=0,"",$H14*$I14) -> 9.827153 | K14: =IF($E14=0,"",RANK($J14,$J$6:$J$138)) -> 74 | L14: =IF($E14=0,"",8-ROUNDUP($K14/COUNT($J$6:$J$138)*7,0)) -> 2 | M14: =IF($E14=0,"",IF($L14>=6,"Priority 1",IF($L14>=5,"Priority 2",IF($L14>=3,"Watch","Low")))) -> Low | N14: =IF($E14=0,"",IF(AND($F14>='Opportunity Controls'!$B$15,$L14>=6),"YES","")) | O14: =IF($E14=0,0,$H14*$I14) -> 9.827153
A15: ='Historical FY16-FY25'!A14 -> Bedford County | B15: ='Historical FY16-FY25'!B14 -> County | C15: Southside | D15: No public action found | E15: =IF(OR('Opportunity Controls'!$B$16="Both",AND('Opportunity Controls'!$B$16="Counties",$B15="County"),AND('Opportunity Controls'!$B$16="Cities",$B15="City")),1,0) -> 1 | F15: ='Schools 1pct Profile'!E15 -> 11900162 | G15: ='Schools 1pct Profile'!H15 -> 3.5944069e+08 | H15: =IFERROR(($G15/MAX($G$6:$G$138))^'Opportunity Controls'!$B$14*100,0) -> 30.969735 | I15: =IFERROR(INDEX('Opportunity Controls'!$B$6:$B$9,MATCH($D15,'Opportunity Controls'!$A$6:$A$9,0)),1) -> 0.7 | J15: =IF($E15=0,"",$H15*$I15) -> 21.678815 | K15: =IF($E15=0,"",RANK($J15,$J$6:$J$138)) -> 27 | L15: =IF($E15=0,"",8-ROUNDUP($K15/COUNT($J$6:$J$138)*7,0)) -> 6 | M15: =IF($E15=0,"",IF($L15>=6,"Priority 1",IF($L15>=5,"Priority 2",IF($L15>=3,"Watch","Low")))) -> Priority 1 | N15: =IF($E15=0,"",IF(AND($F15>='Opportunity Controls'!$B$15,$L15>=6),"YES","")) -> YES | O15: =IF($E15=0,0,$H15*$I15) -> 21.678815
A16: ='Historical FY16-FY25'!A15 -> Bland County | B16: ='Historical FY16-FY25'!B15 -> County | C16: Southwest & New River | D16: No public action found | E16: =IF(OR('Opportunity Controls'!$B$16="Both",AND('Opportunity Controls'!$B$16="Counties",$B16="County"),AND('Opportunity Controls'!$B$16="Cities",$B16="City")),1,0) -> 1 | F16: ='Schools 1pct Profile'!E16 -> 652438.22 | G16: ='Schools 1pct Profile'!H16 -> 18004006 | H16: =IFERROR(($G16/MAX($G$6:$G$138))^'Opportunity Controls'!$B$14*100,0) -> 9.9274891 | I16: =IFERROR(INDEX('Opportunity Controls'!$B$6:$B$9,MATCH($D16,'Opportunity Controls'!$A$6:$A$9,0)),1) -> 0.7 | J16: =IF($E16=0,"",$H16*$I16) -> 6.9492424 | K16: =IF($E16=0,"",RANK($J16,$J$6:$J$138)) -> 90 | L16: =IF($E16=0,"",8-ROUNDUP($K16/COUNT($J$6:$J$138)*7,0)) -> 1 | M16: =IF($E16=0,"",IF($L16>=6,"Priority 1",IF($L16>=5,"Priority 2",IF($L16>=3,"Watch","Low")))) -> Low | N16: =IF($E16=0,"",IF(AND($F16>='Opportunity Controls'!$B$15,$L16>=6),"YES","")) | O16: =IF($E16=0,0,$H16*$I16) -> 6.9492424
A17: ='Historical FY16-FY25'!A16 -> Botetourt County | B17: ='Historical FY16-FY25'!B16 -> County | C17: Shenandoah Valley & Alleghany | D17: No public action found | E17: =IF(OR('Opportunity Controls'!$B$16="Both",AND('Opportunity Controls'!$B$16="Counties",$B17="County"),AND('Opportunity Controls'!$B$16="Cities",$B17="City")),1,0) -> 1 | F17: ='Schools 1pct Profile'!E17 -> 5151294.2 | G17: ='Schools 1pct Profile'!H17 -> 1.5106784e+08 | H17: =IFERROR(($G17/MAX($G$6:$G$138))^'Opportunity Controls'!$B$14*100,0) -> 22.278426 | I17: =IFERROR(INDEX('Opportunity Controls'!$B$6:$B$9,MATCH($D17,'Opportunity Controls'!$A$6:$A$9,0)),1) -> 0.7 | J17: =IF($E17=0,"",$H17*$I17) -> 15.594898 | K17: =IF($E17=0,"",RANK($J17,$J$6:$J$138)) -> 46 | L17: =IF($E17=0,"",8-ROUNDUP($K17/COUNT($J$6:$J$138)*7,0)) -> 4 | M17: =IF($E17=0,"",IF($L17>=6,"Priority 1",IF($L17>=5,"Priority 2",IF($L17>=3,"Watch","Low")))) -> Watch | N17: =IF($E17=0,"",IF(AND($F17>='Opportunity Controls'!$B$15,$L17>=6),"YES","")) | O17: =IF($E17=0,0,$H17*$I17) -> 15.594898
... A138: ='Historical FY16-FY25'!A137 -> Winchester City | B138: ='Historical FY16-FY25'!B137 -> City | C138: Shenandoah Valley & Alleghany | D138: No public action found | E138: =IF(OR('Opportunity Controls'!$B$16="Both",AND('Opportunity Controls'!$B$16="Counties",$B138="County"),AND('Opportunity Controls'!$B$16="Cities",$B138="City")),1,0) -> 0 | F138: ='Schools 1pct Profile'!E138 -> 14552983 | G138: ='Schools 1pct Profile'!H138 -> 4.2751152e+08 | H138: =IFERROR(($G138/MAX($G$6:$G$138))^'Opportunity Controls'!$B$14*100,0) -> 33.079529 | I138: =IFERROR(INDEX('Opportunity Controls'!$B$6:$B$9,MATCH($D138,'Opportunity Controls'!$A$6:$A$9,0)),1) -> 0.7 | J138: =IF($E138=0,"",$H138*$I138) | K138: =IF($E138=0,"",RANK($J138,$J$6:$J$138)) | L138: =IF($E138=0,"",8-ROUNDUP($K138/COUNT($J$6:$J$138)*7,0)) | M138: =IF($E138=0,"",IF($L138>=6,"Priority 1",IF($L138>=5,"Priority 2",IF($L138>=3,"Watch","Low")))) | N138: =IF($E138=0,"",IF(AND($F138>='Opportunity Controls'!$B$15,$L138>=6),"YES","")) | O138: =IF($E138=0,0,$H138*$I138) -> 0
A140: Sort by Rank ascending (or Opportunity score descending) to see the board in order — the filter is on row 5.
A141: Rows greyed to near-white are out of scope. Rows in grey italic are already levying.

Sheet Region Summary
A1: Opportunity by Region
A2: Counts respect the Scope setting on the Opportunity Controls tab.
A4: Region | B4: In scope | C4: On Nov 2026 ballot | D4: Deferred, eyeing 2027 | E4: No public action found | F4: Levying since 2020-23 | G4: 20-yr capacity in scope ($) | H4: FY2027 yield in scope ($) | I4: Avg score | J4: Best score
A5: Northern Virginia | B5: =COUNTIFS('Opportunity Model'!$C$6:$C$138,$A5,'Opportunity Model'!$E$6:$E$138,1) -> 12 | C5: =COUNTIFS('Opportunity Model'!$C$6:$C$138,$A5,'Opportunity Model'!$E$6:$E$138,1,'Opportunity Model'!$D$6:$D$138,"On Nov 2026 ballot") -> 0 | D5: =COUNTIFS('Opportunity Model'!$C$6:$C$138,$A5,'Opportunity Model'!$E$6:$E$138,1,'Opportunity Model'!$D$6:$D$138,"Deferred, eyeing 2027") -> 2 | E5: =COUNTIFS('Opportunity Model'!$C$6:$C$138,$A5,'Opportunity Model'!$E$6:$E$138,1,'Opportunity Model'!$D$6:$D$138,"No public action found") -> 10 | F5: =COUNTIFS('Opportunity Model'!$C$6:$C$138,$A5,'Opportunity Model'!$E$6:$E$138,1,'Opportunity Model'!$D$6:$D$138,"Levying since 2020-23") -> 0 | G5: =SUMIFS('Opportunity Model'!$G$6:$G$138,'Opportunity Model'!$C$6:$C$138,$A5,'Opportunity Model'!$E$6:$E$138,1) -> 2.0487771e+10 | H5: =SUMIFS('Opportunity Model'!$F$6:$F$138,'Opportunity Model'!$C$6:$C$138,$A5,'Opportunity Model'!$E$6:$E$138,1) -> 6.8777118e+08 | I5: =IFERROR(AVERAGEIFS('Opportunity Model'!$O$6:$O$138,'Opportunity Model'!$C$6:$C$138,$A5,'Opportunity Model'!$E$6:$E$138,1),0) -> 33.043209 | J5: =IFERROR(SUMPRODUCT(MAX(('Opportunity Model'!$C$6:$C$138=$A5)*('Opportunity Model'!$E$6:$E$138=1)*'Opportunity Model'!$O$6:$O$138)),0) -> 70
A6: Richmond Metro | B6: =COUNTIFS('Opportunity Model'!$C$6:$C$138,$A6,'Opportunity Model'!$E$6:$E$138,1) -> 10 | C6: =COUNTIFS('Opportunity Model'!$C$6:$C$138,$A6,'Opportunity Model'!$E$6:$E$138,1,'Opportunity Model'!$D$6:$D$138,"On Nov 2026 ballot") -> 3 | D6: =COUNTIFS('Opportunity Model'!$C$6:$C$138,$A6,'Opportunity Model'!$E$6:$E$138,1,'Opportunity Model'!$D$6:$D$138,"Deferred, eyeing 2027") -> 0 | E6: =COUNTIFS('Opportunity Model'!$C$6:$C$138,$A6,'Opportunity Model'!$E$6:$E$138,1,'Opportunity Model'!$D$6:$D$138,"No public action found") -> 7 | F6: =COUNTIFS('Opportunity Model'!$C$6:$C$138,$A6,'Opportunity Model'!$E$6:$E$138,1,'Opportunity Model'!$D$6:$D$138,"Levying since 2020-23") -> 0 | G6: =SUMIFS('Opportunity Model'!$G$6:$G$138,'Opportunity Model'!$C$6:$C$138,$A6,'Opportunity Model'!$E$6:$E$138,1) -> 8.0308982e+09 | H6: =SUMIFS('Opportunity Model'!$F$6:$F$138,'Opportunity Model'!$C$6:$C$138,$A6,'Opportunity Model'!$E$6:$E$138,1) -> 2.5964812e+08 | I6: =IFERROR(AVERAGEIFS('Opportunity Model'!$O$6:$O$138,'Opportunity Model'!$C$6:$C$138,$A6,'Opportunity Model'!$E$6:$E$138,1),0) -> 26.168485 | J6: =IFERROR(SUMPRODUCT(MAX(('Opportunity Model'!$C$6:$C$138=$A6)*('Opportunity Model'!$E$6:$E$138=1)*'Opportunity Model'!$O$6:$O$138)),0) -> 67.387215
A7: Hampton Roads | B7: =COUNTIFS('Opportunity Model'!$C$6:$C$138,$A7,'Opportunity Model'!$E$6:$E$138,1) -> 5 | C7: =COUNTIFS('Opportunity Model'!$C$6:$C$138,$A7,'Opportunity Model'!$E$6:$E$138,1,'Opportunity Model'!$D$6:$D$138,"On Nov 2026 ballot") -> 1 | D7: =COUNTIFS('Opportunity Model'!$C$6:$C$138,$A7,'Opportunity Model'!$E$6:$E$138,1,'Opportunity Model'!$D$6:$D$138,"Deferred, eyeing 2027") -> 0 | E7: =COUNTIFS('Opportunity Model'!$C$6:$C$138,$A7,'Opportunity Model'!$E$6:$E$138,1,'Opportunity Model'!$D$6:$D$138,"No public action found") -> 3 | F7: =COUNTIFS('Opportunity Model'!$C$6:$C$138,$A7,'Opportunity Model'!$E$6:$E$138,1,'Opportunity Model'!$D$6:$D$138,"Levying since 2020-23") -> 1 | G7: =SUMIFS('Opportunity Model'!$G$6:$G$138,'Opportunity Model'!$C$6:$C$138,$A7,'Opportunity Model'!$E$6:$E$138,1) -> 1.495074e+09 | H7: =SUMIFS('Opportunity Model'!$F$6:$F$138,'Opportunity Model'!$C$6:$C$138,$A7,'Opportunity Model'!$E$6:$E$138,1) -> 49442752 | I7: =IFERROR(AVERAGEIFS('Opportunity Model'!$O$6:$O$138,'Opportunity Model'!$C$6:$C$138,$A7,'Opportunity Model'!$E$6:$E$138,1),0) -> 19.189497 | J7: =IFERROR(SUMPRODUCT(MAX(('Opportunity Model'!$C$6:$C$138=$A7)*('Opportunity Model'!$E$6:$E$138=1)*'Opportunity Model'!$O$6:$O$138)),0) -> 34.294705
A8: Central Piedmont | B8: =COUNTIFS('Opportunity Model'!$C$6:$C$138,$A8,'Opportunity Model'!$E$6:$E$138,1) -> 7 | C8: =COUNTIFS('Opportunity Model'!$C$6:$C$138,$A8,'Opportunity Model'!$E$6:$E$138,1,'Opportunity Model'!$D$6:$D$138,"On Nov 2026 ballot") -> 2 | D8: =COUNTIFS('Opportunity Model'!$C$6:$C$138,$A8,'Opportunity Model'!$E$6:$E$138,1,'Opportunity Model'!$D$6:$D$138,"Deferred, eyeing 2027") -> 0 | E8: =COUNTIFS('Opportunity Model'!$C$6:$C$138,$A8,'Opportunity Model'!$E$6:$E$138,1,'Opportunity Model'!$D$6:$D$138,"No public action found") -> 5 | F8: =COUNTIFS('Opportunity Model'!$C$6:$C$138,$A8,'Opportunity Model'!$E$6:$E$138,1,'Opportunity Model'!$D$6:$D$138,"Levying since 2020-23") -> 0 | G8: =SUMIFS('Opportunity Model'!$G$6:$G$138,'Opportunity Model'!$C$6:$C$138,$A8,'Opportunity Model'!$E$6:$E$138,1) -> 1.7474337e+09 | H8: =SUMIFS('Opportunity Model'!$F$6:$F$138,'Opportunity Model'!$C$6:$C$138,$A8,'Opportunity Model'!$E$6:$E$138,1) -> 55268961 | I8: =IFERROR(AVERAGEIFS('Opportunity Model'!$O$6:$O$138,'Opportunity Model'!$C$6:$C$138,$A8,'Opportunity Model'!$E$6:$E$138,1),0) -> 18.716324 | J8: =IFERROR(SUMPRODUCT(MAX(('Opportunity Model'!$C$6:$C$138=$A8)*('Opportunity Model'!$E$6:$E$138=1)*'Opportunity Model'!$O$6:$O$138)),0) -> 30.767341
A9: Shenandoah Valley & Alleghany | B9: =COUNTIFS('Opportunity Model'!$C$6:$C$138,$A9,'Opportunity Model'!$E$6:$E$138,1) -> 10 | C9: =COUNTIFS('Opportunity Model'!$C$6:$C$138,$A9,'Opportunity Model'!$E$6:$E$138,1,'Opportunity Model'!$D$6:$D$138,"On Nov 2026 ballot") -> 0 | D9: =COUNTIFS('Opportunity Model'!$C$6:$C$138,$A9,'Opportunity Model'!$E$6:$E$138,1,'Opportunity Model'!$D$6:$D$138,"Deferred, eyeing 2027") -> 0 | E9: =COUNTIFS('Opportunity Model'!$C$6:$C$138,$A9,'Opportunity Model'!$E$6:$E$138,1,'Opportunity Model'!$D$6:$D$138,"No public action found") -> 10 | F9: =COUNTIFS('Opportunity Model'!$C$6:$C$138,$A9,'Opportunity Model'!$E$6:$E$138,1,'Opportunity Model'!$D$6:$D$138,"Levying since 2020-23") -> 0 | G9: =SUMIFS('Opportunity Model'!$G$6:$G$138,'Opportunity Model'!$C$6:$C$138,$A9,'Opportunity Model'!$E$6:$E$138,1) -> 2.4590161e+09 | H9: =SUMIFS('Opportunity Model'!$F$6:$F$138,'Opportunity Model'!$C$6:$C$138,$A9,'Opportunity Model'!$E$6:$E$138,1) -> 78052113 | I9: =IFERROR(AVERAGEIFS('Opportunity Model'!$O$6:$O$138,'Opportunity Model'!$C$6:$C$138,$A9,'Opportunity Model'!$E$6:$E$138,1),0) -> 16.424367 | J9: =IFERROR(SUMPRODUCT(MAX(('Opportunity Model'!$C$6:$C$138=$A9)*('Opportunity Model'!$E$6:$E$138=1)*'Opportunity Model'!$O$6:$O$138)),0) -> 29.857339
A10: Southwest & New River | B10: =COUNTIFS('Opportunity Model'!$C$6:$C$138,$A10,'Opportunity Model'!$E$6:$E$138,1) -> 19 | C10: =COUNTIFS('Opportunity Model'!$C$6:$C$138,$A10,'Opportunity Model'!$E$6:$E$138,1,'Opportunity Model'!$D$6:$D$138,"On Nov 2026 ballot") -> 1 | D10: =COUNTIFS('Opportunity Model'!$C$6:$C$138,$A10,'Opportunity Model'!$E$6:$E$138,1,'Opportunity Model'!$D$6:$D$138,"Deferred, eyeing 2027") -> 4 | E10: =COUNTIFS('Opportunity Model'!$C$6:$C$138,$A10,'Opportunity Model'!$E$6:$E$138,1,'Opportunity Model'!$D$6:$D$138,"No public action found") -> 14 | F10: =COUNTIFS('Opportunity Model'!$C$6:$C$138,$A10,'Opportunity Model'!$E$6:$E$138,1,'Opportunity Model'!$D$6:$D$138,"Levying since 2020-23") -> 0 | G10: =SUMIFS('Opportunity Model'!$G$6:$G$138,'Opportunity Model'!$C$6:$C$138,$A10,'Opportunity Model'!$E$6:$E$138,1) -> 3.0282152e+09 | H10: =SUMIFS('Opportunity Model'!$F$6:$F$138,'Opportunity Model'!$C$6:$C$138,$A10,'Opportunity Model'!$E$6:$E$138,1) -> 1.0524604e+08 | I10: =IFERROR(AVERAGEIFS('Opportunity Model'!$O$6:$O$138,'Opportunity Model'!$C$6:$C$138,$A10,'Opportunity Model'!$E$6:$E$138,1),0) -> 14.947682 | J10: =IFERROR(SUMPRODUCT(MAX(('Opportunity Model'!$C$6:$C$138=$A10)*('Opportunity Model'!$E$6:$E$138=1)*'Opportunity Model'!$O$6:$O$138)),0) -> 26.348396
A11: Southside | B11: =COUNTIFS('Opportunity Model'!$C$6:$C$138,$A11,'Opportunity Model'!$E$6:$E$138,1) -> 14 | C11: =COUNTIFS('Opportunity Model'!$C$6:$C$138,$A11,'Opportunity Model'!$E$6:$E$138,1,'Opportunity Model'!$D$6:$D$138,"On Nov 2026 ballot") -> 2 | D11: =COUNTIFS('Opportunity Model'!$C$6:$C$138,$A11,'Opportunity Model'!$E$6:$E$138,1,'Opportunity Model'!$D$6:$D$138,"Deferred, eyeing 2027") -> 1 | E11: =COUNTIFS('Opportunity Model'!$C$6:$C$138,$A11,'Opportunity Model'!$E$6:$E$138,1,'Opportunity Model'!$D$6:$D$138,"No public action found") -> 6 | F11: =COUNTIFS('Opportunity Model'!$C$6:$C$138,$A11,'Opportunity Model'!$E$6:$E$138,1,'Opportunity Model'!$D$6:$D$138,"Levying since 2020-23") -> 5 | G11: =SUMIFS('Opportunity Model'!$G$6:$G$138,'Opportunity Model'!$C$6:$C$138,$A11,'Opportunity Model'!$E$6:$E$138,1) -> 2.3629148e+09 | H11: =SUMIFS('Opportunity Model'!$F$6:$F$138,'Opportunity Model'!$C$6:$C$138,$A11,'Opportunity Model'!$E$6:$E$138,1) -> 79615008 | I11: =IFERROR(AVERAGEIFS('Opportunity Model'!$O$6:$O$138,'Opportunity Model'!$C$6:$C$138,$A11,'Opportunity Model'!$E$6:$E$138,1),0) -> 13.956808 | J11: =IFERROR(SUMPRODUCT(MAX(('Opportunity Model'!$C$6:$C$138=$A11)*('Opportunity Model'!$E$6:$E$138=1)*'Opportunity Model'!$O$6:$O$138)),0) -> 27.2611
A12: Tri-Cities & Southside East | B12: =COUNTIFS('Opportunity Model'!$C$6:$C$138,$A12,'Opportunity Model'!$E$6:$E$138,1) -> 7 | C12: =COUNTIFS('Opportunity Model'!$C$6:$C$138,$A12,'Opportunity Model'!$E$6:$E$138,1,'Opportunity Model'!$D$6:$D$138,"On Nov 2026 ballot") -> 1 | D12: =COUNTIFS('Opportunity Model'!$C$6:$C$138,$A12,'Opportunity Model'!$E$6:$E$138,1,'Opportunity Model'!$D$6:$D$138,"Deferred, eyeing 2027") -> 0 | E12: =COUNTIFS('Opportunity Model'!$C$6:$C$138,$A12,'Opportunity Model'!$E$6:$E$138,1,'Opportunity Model'!$D$6:$D$138,"No public action found") -> 6 | F12: =COUNTIFS('Opportunity Model'!$C$6:$C$138,$A12,'Opportunity Model'!$E$6:$E$138,1,'Opportunity Model'!$D$6:$D$138,"Levying since 2020-23") -> 0 | G12: =SUMIFS('Opportunity Model'!$G$6:$G$138,'Opportunity Model'!$C$6:$C$138,$A12,'Opportunity Model'!$E$6:$E$138,1) -> 5.6315292e+08 | H12: =SUMIFS('Opportunity Model'!$F$6:$F$138,'Opportunity Model'!$C$6:$C$138,$A12,'Opportunity Model'!$E$6:$E$138,1) -> 18067450 | I12: =IFERROR(AVERAGEIFS('Opportunity Model'!$O$6:$O$138,'Opportunity Model'!$C$6:$C$138,$A12,'Opportunity Model'!$E$6:$E$138,1),0) -> 12.445868 | J12: =IFERROR(SUMPRODUCT(MAX(('Opportunity Model'!$C$6:$C$138=$A12)*('Opportunity Model'!$E$6:$E$138=1)*'Opportunity Model'!$O$6:$O$138)),0) -> 15.712241
A13: Northern Neck & Middle Peninsula | B13: =COUNTIFS('Opportunity Model'!$C$6:$C$138,$A13,'Opportunity Model'!$E$6:$E$138,1) -> 9 | C13: =COUNTIFS('Opportunity Model'!$C$6:$C$138,$A13,'Opportunity Model'!$E$6:$E$138,1,'Opportunity Model'!$D$6:$D$138,"On Nov 2026 ballot") -> 3 | D13: =COUNTIFS('Opportunity Model'!$C$6:$C$138,$A13,'Opportunity Model'!$E$6:$E$138,1,'Opportunity Model'!$D$6:$D$138,"Deferred, eyeing 2027") -> 0 | E13: =COUNTIFS('Opportunity Model'!$C$6:$C$138,$A13,'Opportunity Model'!$E$6:$E$138,1,'Opportunity Model'!$D$6:$D$138,"No public action found") -> 6 | F13: =COUNTIFS('Opportunity Model'!$C$6:$C$138,$A13,'Opportunity Model'!$E$6:$E$138,1,'Opportunity Model'!$D$6:$D$138,"Levying since 2020-23") -> 0 | G13: =SUMIFS('Opportunity Model'!$G$6:$G$138,'Opportunity Model'!$C$6:$C$138,$A13,'Opportunity Model'!$E$6:$E$138,1) -> 5.4531968e+08 | H13: =SUMIFS('Opportunity Model'!$F$6:$F$138,'Opportunity Model'!$C$6:$C$138,$A13,'Opportunity Model'!$E$6:$E$138,1) -> 18184981 | I13: =IFERROR(AVERAGEIFS('Opportunity Model'!$O$6:$O$138,'Opportunity Model'!$C$6:$C$138,$A13,'Opportunity Model'!$E$6:$E$138,1),0) -> 12.101868 | J13: =IFERROR(SUMPRODUCT(MAX(('Opportunity Model'!$C$6:$C$138=$A13)*('Opportunity Model'!$E$6:$E$138=1)*'Opportunity Model'!$O$6:$O$138)),0) -> 18.350621
A14: Eastern Shore | B14: =COUNTIFS('Opportunity Model'!$C$6:$C$138,$A14,'Opportunity Model'!$E$6:$E$138,1) -> 2 | C14: =COUNTIFS('Opportunity Model'!$C$6:$C$138,$A14,'Opportunity Model'!$E$6:$E$138,1,'Opportunity Model'!$D$6:$D$138,"On Nov 2026 ballot") -> 0 | D14: =COUNTIFS('Opportunity Model'!$C$6:$C$138,$A14,'Opportunity Model'!$E$6:$E$138,1,'Opportunity Model'!$D$6:$D$138,"Deferred, eyeing 2027") -> 0 | E14: =COUNTIFS('Opportunity Model'!$C$6:$C$138,$A14,'Opportunity Model'!$E$6:$E$138,1,'Opportunity Model'!$D$6:$D$138,"No public action found") -> 1 | F14: =COUNTIFS('Opportunity Model'!$C$6:$C$138,$A14,'Opportunity Model'!$E$6:$E$138,1,'Opportunity Model'!$D$6:$D$138,"Levying since 2020-23") -> 1 | G14: =SUMIFS('Opportunity Model'!$G$6:$G$138,'Opportunity Model'!$C$6:$C$138,$A14,'Opportunity Model'!$E$6:$E$138,1) -> 2.7723416e+08 | H14: =SUMIFS('Opportunity Model'!$F$6:$F$138,'Opportunity Model'!$C$6:$C$138,$A14,'Opportunity Model'!$E$6:$E$138,1) -> 9571604.7 | I14: =IFERROR(AVERAGEIFS('Opportunity Model'!$O$6:$O$138,'Opportunity Model'!$C$6:$C$138,$A14,'Opportunity Model'!$E$6:$E$138,1),0) -> 11.689021 | J14: =IFERROR(SUMPRODUCT(MAX(('Opportunity Model'!$C$6:$C$138=$A14)*('Opportunity Model'!$E$6:$E$138=1)*'Opportunity Model'!$O$6:$O$138)),0) -> 17.226801
A15: TOTAL | B15: =SUM(B5:B14) -> 95 | C15: =SUM(C5:C14) -> 13 | D15: =SUM(D5:D14) -> 7 | E15: =SUM(E5:E14) -> 68 | F15: =SUM(F5:F14) -> 7 | G15: =SUM(G5:G14) -> 4.0997029e+10 | H15: =SUM(H5:H14) -> 1.3608682e+09
A17: Ballot / Deferred counts reflect only what has been individually confirmed in reporting — see the Opportunity Controls tab.

Sheet Region Needs Profile
A1: School Facility Needs by VDOE Superintendent's Region
A2: Source: VDOE, Needs and Conditions of Virginia School Buildings, June 2021, prepared for the Commission on School Construction and Modernization. All values are region-level; VDOE holds the division detail.
A3: The lean score at right is derived, not published: it contrasts enrollment trajectory against building age and recent renovation activity. Positive leans toward new construction, negative toward retrofit.
A5: VDOE Region | B5: 5-yr enrollment change to 2026 | C5: Median building age (yrs) | D5: % buildings renovated since 2015 | E5: % ADA compliant | F5: New schools in division CIPs | G5: $ new schools in CIPs | H5: Renovation projects in CIPs | I5: $ renovations in CIPs | J5: HVAC projects in CIPs | K5: $ HVAC in CIPs | L5: Roof projects in CIPs | M5: $ roof in CIPs | N5: New-build index | O5: Retrofit index | P5: LEAN (+ new build / - retrofit)
A6: 1 Central Virginia | B6: 0.0584 | C6: 50 | D6: 0.1455 | E6: 0.6145 | F6: 17 | G6: 593967376 | H6: 36 | I6: 399192673 | J6: 34 | K6: 52386507 | L6: 38 | M6: 29923810 | N6: =($B6-MIN($B$6:$B$13))/(MAX($B$6:$B$13)-MIN($B$6:$B$13))*100 -> 75.154101 | O6: =($C6-MIN($C$6:$C$13))/(MAX($C$6:$C$13)-MIN($C$6:$C$13))*50+(MAX($D$6:$D$13)-$D6)/(MAX($D$6:$D$13)-MIN($D$6:$D$13))*50 -> 54.249874 | P6: =$N6-$O6 -> 20.904228
A7: 2 Tidewater | B7: 0.0143 | C7: 50 | D7: 0.1097 | E7: 0.9031 | F7: 16 | G7: 498484245 | H7: 99 | I7: 513973329 | J7: 91 | K7: 296016508 | L7: 64 | M7: 157071809 | N7: =($B7-MIN($B$6:$B$13))/(MAX($B$6:$B$13)-MIN($B$6:$B$13))*100 -> 54.243717 | O7: =($C7-MIN($C$6:$C$13))/(MAX($C$6:$C$13)-MIN($C$6:$C$13))*50+(MAX($D$6:$D$13)-$D7)/(MAX($D$6:$D$13)-MIN($D$6:$D$13))*50 -> 62.637878 | P7: =$N7-$O7 -> -8.3941602
A8: 3 Northern Neck | B8: 0.1108 | C8: 32 | D8: 0.1707 | E8: 0.6992 | F8: 5 | G8: 253122699 | H8: 52 | I8: 111081406 | J8: 44 | K8: 19452900 | L8: 24 | M8: 64342254 | N8: =($B8-MIN($B$6:$B$13))/(MAX($B$6:$B$13)-MIN($B$6:$B$13))*100 -> 100 | O8: =($C8-MIN($C$6:$C$13))/(MAX($C$6:$C$13)-MIN($C$6:$C$13))*50+(MAX($D$6:$D$13)-$D8)/(MAX($D$6:$D$13)-MIN($D$6:$D$13))*50 -> 13.730084 | P8: =$N8-$O8 -> 86.269916
A9: 4 Northern Virginia | B9: 0.0794 | C9: 48 | D9: 0.2293 | E9: 0.6949 | F9: 31 | G9: 2151449772 | H9: 170 | I9: 1808662674 | J9: 113 | K9: 52255045 | L9: 63 | M9: 139999837 | N9: =($B9-MIN($B$6:$B$13))/(MAX($B$6:$B$13)-MIN($B$6:$B$13))*100 -> 85.111427 | O9: =($C9-MIN($C$6:$C$13))/(MAX($C$6:$C$13)-MIN($C$6:$C$13))*50+(MAX($D$6:$D$13)-$D9)/(MAX($D$6:$D$13)-MIN($D$6:$D$13))*50 -> 30.769231 | P9: =$N9-$O9 -> 54.342196
A10: 5 Valley | B10: 0.0301 | C10: 55 | D10: 0.199 | E10: 0.966 | F10: 3 | G10: 85000000 | H10: 61 | I10: 196616603 | J10: 49 | K10: 75511912 | L10: 51 | M10: 25539379 | N10: =($B10-MIN($B$6:$B$13))/(MAX($B$6:$B$13)-MIN($B$6:$B$13))*100 -> 61.73542 | O10: =($C10-MIN($C$6:$C$13))/(MAX($C$6:$C$13)-MIN($C$6:$C$13))*50+(MAX($D$6:$D$13)-$D10)/(MAX($D$6:$D$13)-MIN($D$6:$D$13))*50 -> 51.330113 | P10: =$N10-$O10 -> 10.405306
A11: 6 Western Virginia | B11: -0.0678 | C11: 58 | D11: 0.0985 | E11: 0.8522 | F11: 0 | G11: 0 | H11: 59 | I11: 182347652 | J11: 39 | K11: 33071010 | L11: 31 | M11: 26994674 | N11: =($B11-MIN($B$6:$B$13))/(MAX($B$6:$B$13)-MIN($B$6:$B$13))*100 -> 15.315315 | O11: =($C11-MIN($C$6:$C$13))/(MAX($C$6:$C$13)-MIN($C$6:$C$13))*50+(MAX($D$6:$D$13)-$D11)/(MAX($D$6:$D$13)-MIN($D$6:$D$13))*50 -> 80.646673 | P11: =$N11-$O11 -> -65.331358
A12: 7 Southwest | B12: -0.1001 | C12: 58 | D12: 0.0455 | E12: 0.7898 | F12: 2 | G12: 37391934 | H12: 59 | I12: 61781135 | J12: 72 | K12: 78838541 | L12: 55 | M12: 20678848 | N12: =($B12-MIN($B$6:$B$13))/(MAX($B$6:$B$13)-MIN($B$6:$B$13))*100 -> 0 | O12: =($C12-MIN($C$6:$C$13))/(MAX($C$6:$C$13)-MIN($C$6:$C$13))*50+(MAX($D$6:$D$13)-$D12)/(MAX($D$6:$D$13)-MIN($D$6:$D$13))*50 -> 93.064667 | P12: =$N12-$O12 -> -93.064667
A13: 8 Southside | B13: -0.074 | C13: 58 | D13: 0.0159 | E13: 0.873 | F13: 7 | G13: 214660000 | H13: 30 | I13: 44549663 | J13: 21 | K13: 16467002 | L13: 18 | M13: 3394046 | N13: =($B13-MIN($B$6:$B$13))/(MAX($B$6:$B$13)-MIN($B$6:$B$13))*100 -> 12.375533 | O13: =($C13-MIN($C$6:$C$13))/(MAX($C$6:$C$13)-MIN($C$6:$C$13))*50+(MAX($D$6:$D$13)-$D13)/(MAX($D$6:$D$13)-MIN($D$6:$D$13))*50 -> 100 | P13: =$N13-$O13 -> -87.624467
A15: How to read the lean
A16: New-build index scales enrollment change across the eight regions: 100 = fastest growing, 0 = fastest shrinking.
A17: Retrofit index is half median building age and half the inverse of renovation activity since 2015 — old stock that
A18: nobody has touched scores highest. Both run 0-100, so the lean runs -100 to +100.
A19: Corroboration: Region 4 plans 31 new schools worth $2.15B. Region 6 plans none, and 59 renovations. Region 7 plans
A20: two new schools and 72 HVAC projects. The published CIPs point the same way the derived lean does.

Sheet Locality Play
A1: Locality Play — Levy Capacity against Facility Need
A2: Joins each locality's 1% levy capacity to its VDOE region's facility-need profile, and assigns a play. Region attributes are regional averages applied to every locality in that region — directional, not diagnostic.
A3: Region assignment is our own mapping and should be verified against VDOE's official region map before use.
A5: Locality | B5: Type | C5: VDOE Region | D5: Referendum status | E5: In scope | F5: 20-yr levy capacity ($) | G5: FY2027 levy yield ($) | H5: Region enrollment trend | I5: Region median bldg age | J5: Region lean | K5: Capital self-sufficiency | L5: Recommended play | M5: Primary funding stack | N5: Scope-share factor | O5: Timing factor | P5: Seller score | Q5: Seller priority | R5: Call wave | S5: Opening move | T5: Account owner | U5: Notes
A6: ='Opportunity Model'!A6 -> Accomack County | B6: ='Opportunity Model'!B6 -> County | C6: 2 Tidewater | D6: ='Opportunity Model'!D6 -> No public action found | E6: ='Opportunity Model'!E6 -> 1 | F6: ='Opportunity Model'!G6 -> 1.9629732e+08 | G6: ='Opportunity Model'!F6 -> 6888381.4 | H6: ='Region Needs Profile'!B7 -> 0.0143 | I6: ='Region Needs Profile'!C7 -> 50 | J6: ='Region Needs Profile'!P7 -> -8.3941602 | K6: =IF($F6>=PERCENTILE($F$6:$F$138,0.75),"High",IF($F6>=PERCENTILE($F$6:$F$138,0.4),"Moderate","Low")) -> Moderate | L6: =IF($J6>=40,"New build / PPEA",IF($J6<=-40,IF($K6="Low","Retrofit + state stack","Retrofit / ESPC"),IF($K6="High","Blended programme","Selective retrofit"))) -> Selective retrofit | M6: =IF($L6="New build / PPEA","Levy-backed debt + PPEA availability payment + SCAP 10%",IF($L6="Retrofit + state stack","SCAP 20-30% + Literary Fund + levy + guaranteed savings",IF($L6="Retrofit / ESPC","Levy + guaranteed savings + VPSA pooled bond",IF($L6="Blended programme","Levy-backed debt + ESPC on the retained estate","SCAP + Literary Fund + guaranteed savings")))) -> SCAP + Literary Fund + guaranteed savings | N6: =IF(OR($L6="Retrofit / ESPC",$L6="Retrofit + state stack"),$B$142,IF($L6="New build / PPEA",$B$144,$B$143)) -> 0.7 | O6: =IF($D6="On Nov 2026 ballot",$B$145,IF($D6="Levying since 2020-23",$B$147,IF($D6="Deferred, eyeing 2027",$B$148,$B$146))) -> 0.8 | P6: =IF($E6=0,"",($F6/MAX($F$6:$F$138))^0.38*100*$N6*$O6) -> 13.781441 | Q6: =IF($E6=0,"","P"&MIN(4,ROUNDUP(RANK($P6,$P$6:$P$138)/COUNT($P$6:$P$138)*4,0))) -> P2 | R6: =IF($D6="On Nov 2026 ballot","Wave 1 - position before the vote",IF($D6="Deferred, eyeing 2027","Wave 3 - 2027 referendum cycle",IF($D6="Levying since 2020-23","Wave 2 - next phase / displace incumbent","Wave 1 - VERIFY referendum status first"))) -> Wave 1 - VERIFY referendum status first | S6: =IF($L6="Retrofit + state stack","SCAP application support + no-cost condition assessment",IF($L6="Retrofit / ESPC","No-cost facility condition assessment",IF($L6="New build / PPEA","PPEA concept + capital sequencing review",IF($L6="Blended programme","Capital programme structuring review","Targeted HVAC and roof scope review")))) -> Targeted HVAC and roof scope review
A7: ='Opportunity Model'!A7 -> Albemarle County | B7: ='Opportunity Model'!B7 -> County | C7: 5 Valley | D7: ='Opportunity Model'!D7 -> No public action found | E7: ='Opportunity Model'!E7 -> 1 | F7: ='Opportunity Model'!G7 -> 9.0317202e+08 | G7: ='Opportunity Model'!F7 -> 28874529 | H7: ='Region Needs Profile'!B10 -> 0.0301 | I7: ='Region Needs Profile'!C10 -> 55 | J7: ='Region Needs Profile'!P10 -> 10.405306 | K7: =IF($F7>=PERCENTILE($F$6:$F$138,0.75),"High",IF($F7>=PERCENTILE($F$6:$F$138,0.4),"Moderate","Low")) -> High | L7: =IF($J7>=40,"New build / PPEA",IF($J7<=-40,IF($K7="Low","Retrofit + state stack","Retrofit / ESPC"),IF($K7="High","Blended programme","Selective retrofit"))) -> Blended programme | M7: =IF($L7="New build / PPEA","Levy-backed debt + PPEA availability payment + SCAP 10%",IF($L7="Retrofit + state stack","SCAP 20-30% + Literary Fund + levy + guaranteed savings",IF($L7="Retrofit / ESPC","Levy + guaranteed savings + VPSA pooled bond",IF($L7="Blended programme","Levy-backed debt + ESPC on the retained estate","SCAP + Literary Fund + guaranteed savings")))) -> Levy-backed debt + ESPC on the retained estate | N7: =IF(OR($L7="Retrofit / ESPC",$L7="Retrofit + state stack"),$B$142,IF($L7="New build / PPEA",$B$144,$B$143)) -> 0.7 | O7: =IF($D7="On Nov 2026 ballot",$B$145,IF($D7="Levying since 2020-23",$B$147,IF($D7="Deferred, eyeing 2027",$B$148,$B$146))) -> 0.8 | P7: =IF($E7=0,"",($F7/MAX($F$6:$F$138))^0.38*100*$N7*$O7) -> 24.613872 | Q7: =IF($E7=0,"","P"&MIN(4,ROUNDUP(RANK($P7,$P$6:$P$138)/COUNT($P$6:$P$138)*4,0))) -> P1 | R7: =IF($D7="On Nov 2026 ballot","Wave 1 - position before the vote",IF($D7="Deferred, eyeing 2027","Wave 3 - 2027 referendum cycle",IF($D7="Levying since 2020-23","Wave 2 - next phase / displace incumbent","Wave 1 - VERIFY referendum status first"))) -> Wave 1 - VERIFY referendum status first | S7: =IF($L7="Retrofit + state stack","SCAP application support + no-cost condition assessment",IF($L7="Retrofit / ESPC","No-cost facility condition assessment",IF($L7="New build / PPEA","PPEA concept + capital sequencing review",IF($L7="Blended programme","Capital programme structuring review","Targeted HVAC and roof scope review")))) -> Capital programme structuring review
A8: ='Opportunity Model'!A8 -> Alleghany County | B8: ='Opportunity Model'!B8 -> County | C8: 6 Western Virginia | D8: ='Opportunity Model'!D8 -> No public action found | E8: ='Opportunity Model'!E8 -> 1 | F8: ='Opportunity Model'!G8 -> 35851158 | G8: ='Opportunity Model'!F8 -> 1368536.1 | H8: ='Region Needs Profile'!B11 -> -0.0678 | I8: ='Region Needs Profile'!C11 -> 58 | J8: ='Region Needs Profile'!P11 -> -65.331358 | K8: =IF($F8>=PERCENTILE($F$6:$F$138,0.75),"High",IF($F8>=PERCENTILE($F$6:$F$138,0.4),"Moderate","Low")) -> Low | L8: =IF($J8>=40,"New build / PPEA",IF($J8<=-40,IF($K8="Low","Retrofit + state stack","Retrofit / ESPC"),IF($K8="High","Blended programme","Selective retrofit"))) -> Retrofit + state stack | M8: =IF($L8="New build / PPEA","Levy-backed debt + PPEA availability payment + SCAP 10%",IF($L8="Retrofit + state stack","SCAP 20-30% + Literary Fund + levy + guaranteed savings",IF($L8="Retrofit / ESPC","Levy + guaranteed savings + VPSA pooled bond",IF($L8="Blended programme","Levy-backed debt + ESPC on the retained estate","SCAP + Literary Fund + guaranteed savings")))) -> SCAP 20-30% + Literary Fund + levy + guaranteed savings | N8: =IF(OR($L8="Retrofit / ESPC",$L8="Retrofit + state stack"),$B$142,IF($L8="New build / PPEA",$B$144,$B$143)) -> 1 | O8: =IF($D8="On Nov 2026 ballot",$B$145,IF($D8="Levying since 2020-23",$B$147,IF($D8="Deferred, eyeing 2027",$B$148,$B$146))) -> 0.8 | P8: =IF($E8=0,"",($F8/MAX($F$6:$F$138))^0.38*100*$N8*$O8) -> 10.318114 | Q8: =IF($E8=0,"","P"&MIN(4,ROUNDUP(RANK($P8,$P$6:$P$138)/COUNT($P$6:$P$138)*4,0))) -> P3 | R8: =IF($D8="On Nov 2026 ballot","Wave 1 - position before the vote",IF($D8="Deferred, eyeing 2027","Wave 3 - 2027 referendum cycle",IF($D8="Levying since 2020-23","Wave 2 - next phase / displace incumbent","Wave 1 - VERIFY referendum status first"))) -> Wave 1 - VERIFY referendum status first | S8: =IF($L8="Retrofit + state stack","SCAP application support + no-cost condition assessment",IF($L8="Retrofit / ESPC","No-cost facility condition assessment",IF($L8="New build / PPEA","PPEA concept + capital sequencing review",IF($L8="Blended programme","Capital programme structuring review","Targeted HVAC and roof scope review")))) -> SCAP application support + no-cost condition assessment
A9: ='Opportunity Model'!A9 -> Amelia County | B9: ='Opportunity Model'!B9 -> County | C9: 8 Southside | D9: ='Opportunity Model'!D9 -> No public action found | E9: ='Opportunity Model'!E9 -> 1 | F9: ='Opportunity Model'!G9 -> 50578822 | G9: ='Opportunity Model'!F9 -> 1663744.2 | H9: ='Region Needs Profile'!B13 -> -0.074 | I9: ='Region Needs Profile'!C13 -> 58 | J9: ='Region Needs Profile'!P13 -> -87.624467 | K9: =IF($F9>=PERCENTILE($F$6:$F$138,0.75),"High",IF($F9>=PERCENTILE($F$6:$F$138,0.4),"Moderate","Low")) -> Low | L9: =IF($J9>=40,"New build / PPEA",IF($J9<=-40,IF($K9="Low","Retrofit + state stack","Retrofit / ESPC"),IF($K9="High","Blended programme","Selective retrofit"))) -> Retrofit + state stack | M9: =IF($L9="New build / PPEA","Levy-backed debt + PPEA availability payment + SCAP 10%",IF($L9="Retrofit + state stack","SCAP 20-30% + Literary Fund + levy + guaranteed savings",IF($L9="Retrofit / ESPC","Levy + guaranteed savings + VPSA pooled bond",IF($L9="Blended programme","Levy-backed debt + ESPC on the retained estate","SCAP + Literary Fund + guaranteed savings")))) -> SCAP 20-30% + Literary Fund + levy + guaranteed savings | N9: =IF(OR($L9="Retrofit / ESPC",$L9="Retrofit + state stack"),$B$142,IF($L9="New build / PPEA",$B$144,$B$143)) -> 1 | O9: =IF($D9="On Nov 2026 ballot",$B$145,IF($D9="Levying since 2020-23",$B$147,IF($D9="Deferred, eyeing 2027",$B$148,$B$146))) -> 0.8 | P9: =IF($E9=0,"",($F9/MAX($F$6:$F$138))^0.38*100*$N9*$O9) -> 11.759727 | Q9: =IF($E9=0,"","P"&MIN(4,ROUNDUP(RANK($P9,$P$6:$P$138)/COUNT($P$6:$P$138)*4,0))) -> P3 | R9: =IF($D9="On Nov 2026 ballot","Wave 1 - position before the vote",IF($D9="Deferred, eyeing 2027","Wave 3 - 2027 referendum cycle",IF($D9="Levying since 2020-23","Wave 2 - next phase / displace incumbent","Wave 1 - VERIFY referendum status first"))) -> Wave 1 - VERIFY referendum status first | S9: =IF($L9="Retrofit + state stack","SCAP application support + no-cost condition assessment",IF($L9="Retrofit / ESPC","No-cost facility condition assessment",IF($L9="New build / PPEA","PPEA concept + capital sequencing review",IF($L9="Blended programme","Capital programme structuring review","Targeted HVAC and roof scope review")))) -> SCAP application support + no-cost condition assessment
A10: ='Opportunity Model'!A10 -> Amherst County | B10: ='Opportunity Model'!B10 -> County | C10: 6 Western Virginia | D10: ='Opportunity Model'!D10 -> Deferred, eyeing 2027 | E10: ='Opportunity Model'!E10 -> 1 | F10: ='Opportunity Model'!G10 -> 1.5398921e+08 | G10: ='Opportunity Model'!F10 -> 5156295.1 | H10: ='Region Needs Profile'!B11 -> -0.0678 | I10: ='Region Needs Profile'!C11 -> 58 | J10: ='Region Needs Profile'!P11 -> -65.331358 | K10: =IF($F10>=PERCENTILE($F$6:$F$138,0.75),"High",IF($F10>=PERCENTILE($F$6:$F$138,0.4),"Moderate","Low")) -> Moderate | L10: =IF($J10>=40,"New build / PPEA",IF($J10<=-40,IF($K10="Low","Retrofit + state stack","Retrofit / ESPC"),IF($K10="High","Blended programme","Selective retrofit"))) -> Retrofit / ESPC | M10: =IF($L10="New build / PPEA","Levy-backed debt + PPEA availability payment + SCAP 10%",IF($L10="Retrofit + state stack","SCAP 20-30% + Literary Fund + levy + guaranteed savings",IF($L10="Retrofit / ESPC","Levy + guaranteed savings + VPSA pooled bond",IF($L10="Blended programme","Levy-backed debt + ESPC on the retained estate","SCAP + Literary Fund + guaranteed savings")))) -> Levy + guaranteed savings + VPSA pooled bond | N10: =IF(OR($L10="Retrofit / ESPC",$L10="Retrofit + state stack"),$B$142,IF($L10="New build / PPEA",$B$144,$B$143)) -> 1 | O10: =IF($D10="On Nov 2026 ballot",$B$145,IF($D10="Levying since 2020-23",$B$147,IF($D10="Deferred, eyeing 2027",$B$148,$B$146))) -> 0.55 | P10: =IF($E10=0,"",($F10/MAX($F$6:$F$138))^0.38*100*$N10*$O10) -> 12.342642 | Q10: =IF($E10=0,"","P"&MIN(4,ROUNDUP(RANK($P10,$P$6:$P$138)/COUNT($P$6:$P$138)*4,0))) -> P3 | R10: =IF($D10="On Nov 2026 ballot","Wave 1 - position before the vote",IF($D10="Deferred, eyeing 2027","Wave 3 - 2027 referendum cycle",IF($D10="Levying since 2020-23","Wave 2 - next phase / displace incumbent","Wave 1 - VERIFY referendum status first"))) -> Wave 3 - 2027 referendum cycle | S10: =IF($L10="Retrofit + state stack","SCAP application support + no-cost condition assessment",IF($L10="Retrofit / ESPC","No-cost facility condition assessment",IF($L10="New build / PPEA","PPEA concept + capital sequencing review",IF($L10="Blended programme","Capital programme structuring review","Targeted HVAC and roof scope review")))) -> No-cost facility condition assessment
A11: ='Opportunity Model'!A11 -> Appomattox County | B11: ='Opportunity Model'!B11 -> County | C11: 6 Western Virginia | D11: ='Opportunity Model'!D11 -> No public action found | E11: ='Opportunity Model'!E11 -> 1 | F11: ='Opportunity Model'!G11 -> 74351620 | G11: ='Opportunity Model'!F11 -> 2407487.2 | H11: ='Region Needs Profile'!B11 -> -0.0678 | I11: ='Region Needs Profile'!C11 -> 58 | J11: ='Region Needs Profile'!P11 -> -65.331358 | K11: =IF($F11>=PERCENTILE($F$6:$F$138,0.75),"High",IF($F11>=PERCENTILE($F$6:$F$138,0.4),"Moderate","Low")) -> Low | L11: =IF($J11>=40,"New build / PPEA",IF($J11<=-40,IF($K11="Low","Retrofit + state stack","Retrofit / ESPC"),IF($K11="High","Blended programme","Selective retrofit"))) -> Retrofit + state stack | M11: =IF($L11="New build / PPEA","Levy-backed debt + PPEA availability payment + SCAP 10%",IF($L11="Retrofit + state stack","SCAP 20-30% + Literary Fund + levy + guaranteed savings",IF($L11="Retrofit / ESPC","Levy + guaranteed savings + VPSA pooled bond",IF($L11="Blended programme","Levy-backed debt + ESPC on the retained estate","SCAP + Literary Fund + guaranteed savings")))) -> SCAP 20-30% + Literary Fund + levy + guaranteed savings | N11: =IF(OR($L11="Retrofit / ESPC",$L11="Retrofit + state stack"),$B$142,IF($L11="New build / PPEA",$B$144,$B$143)) -> 1 | O11: =IF($D11="On Nov 2026 ballot",$B$145,IF($D11="Levying since 2020-23",$B$147,IF($D11="Deferred, eyeing 2027",$B$148,$B$146))) -> 0.8 | P11: =IF($E11=0,"",($F11/MAX($F$6:$F$138))^0.38*100*$N11*$O11) -> 13.613804 | Q11: =IF($E11=0,"","P"&MIN(4,ROUNDUP(RANK($P11,$P$6:$P$138)/COUNT($P$6:$P$138)*4,0))) -> P2 | R11: =IF($D11="On Nov 2026 ballot","Wave 1 - position before the vote",IF($D11="Deferred, eyeing 2027","Wave 3 - 2027 referendum cycle",IF($D11="Levying since 2020-23","Wave 2 - next phase / displace incumbent","Wave 1 - VERIFY referendum status first"))) -> Wave 1 - VERIFY referendum status first | S11: =IF($L11="Retrofit + state stack","SCAP application support + no-cost condition assessment",IF($L11="Retrofit / ESPC","No-cost facility condition assessment",IF($L11="New build / PPEA","PPEA concept + capital sequencing review",IF($L11="Blended programme","Capital programme structuring review","Targeted HVAC and roof scope review")))) -> SCAP application support + no-cost condition assessment
A12: ='Opportunity Model'!A12 -> Arlington County | B12: ='Opportunity Model'!B12 -> County | C12: 4 Northern Virginia | D12: ='Opportunity Model'!D12 -> Deferred, eyeing 2027 | E12: ='Opportunity Model'!E12 -> 1 | F12: ='Opportunity Model'!G12 -> 1.7351332e+09 | G12: ='Opportunity Model'!F12 -> 59799662 | H12: ='Region Needs Profile'!B9 -> 0.0794 | I12: ='Region Needs Profile'!C9 -> 48 | J12: ='Region Needs Profile'!P9 -> 54.342196 | K12: =IF($F12>=PERCENTILE($F$6:$F$138,0.75),"High",IF($F12>=PERCENTILE($F$6:$F$138,0.4),"Moderate","Low")) -> High | L12: =IF($J12>=40,"New build / PPEA",IF($J12<=-40,IF($K12="Low","Retrofit + state stack","Retrofit / ESPC"),IF($K12="High","Blended programme","Selective retrofit"))) -> New build / PPEA | M12: =IF($L12="New build / PPEA","Levy-backed debt + PPEA availability payment + SCAP 10%",IF($L12="Retrofit + state stack","SCAP 20-30% + Literary Fund + levy + guaranteed savings",IF($L12="Retrofit / ESPC","Levy + guaranteed savings + VPSA pooled bond",IF($L12="Blended programme","Levy-backed debt + ESPC on the retained estate","SCAP + Literary Fund + guaranteed savings")))) -> Levy-backed debt + PPEA availability payment + SCAP 10% | N12: =IF(OR($L12="Retrofit / ESPC",$L12="Retrofit + state stack"),$B$142,IF($L12="New build / PPEA",$B$144,$B$143)) -> 0.45 | O12: =IF($D12="On Nov 2026 ballot",$B$145,IF($D12="Levying since 2020-23",$B$147,IF($D12="Deferred, eyeing 2027",$B$148,$B$146))) -> 0.55 | P12: =IF($E12=0,"",($F12/MAX($F$6:$F$138))^0.38*100*$N12*$O12) -> 13.941863 | Q12: =IF($E12=0,"","P"&MIN(4,ROUNDUP(RANK($P12,$P$6:$P$138)/COUNT($P$6:$P$138)*4,0))) -> P2 | R12: =IF($D12="On Nov 2026 ballot","Wave 1 - position before the vote",IF($D12="Deferred, eyeing 2027","Wave 3 - 2027 referendum cycle",IF($D12="Levying since 2020-23","Wave 2 - next phase / displace incumbent","Wave 1 - VERIFY referendum status first"))) -> Wave 3 - 2027 referendum cycle | S12: =IF($L12="Retrofit + state stack","SCAP application support + no-cost condition assessment",IF($L12="Retrofit / ESPC","No-cost facility condition assessment",IF($L12="New build / PPEA","PPEA concept + capital sequencing review",IF($L12="Blended programme","Capital programme structuring review","Targeted HVAC and roof scope review")))) -> PPEA concept + capital sequencing review
A13: ='Opportunity Model'!A13 -> Augusta County | B13: ='Opportunity Model'!B13 -> County | C13: 5 Valley | D13: ='Opportunity Model'!D13 -> No public action found | E13: ='Opportunity Model'!E13 -> 1 | F13: ='Opportunity Model'!G13 -> 3.3353249e+08 | G13: ='Opportunity Model'!F13 -> 10946275 | H13: ='Region Needs Profile'!B10 -> 0.0301 | I13: ='Region Needs Profile'!C10 -> 55 | J13: ='Region Needs Profile'!P10 -> 10.405306 | K13: =IF($F13>=PERCENTILE($F$6:$F$138,0.75),"High",IF($F13>=PERCENTILE($F$6:$F$138,0.4),"Moderate","Low")) -> Moderate | L13: =IF($J13>=40,"New build / PPEA",IF($J13<=-40,IF($K13="Low","Retrofit + state stack","Retrofit / ESPC"),IF($K13="High","Blended programme","Selective retrofit"))) -> Selective retrofit | M13: =IF($L13="New build / PPEA","Levy-backed debt + PPEA availability payment + SCAP 10%",IF($L13="Retrofit + state stack","SCAP 20-30% + Literary Fund + levy + guaranteed savings",IF($L13="Retrofit / ESPC","Levy + guaranteed savings + VPSA pooled bond",IF($L13="Blended programme","Levy-backed debt + ESPC on the retained estate","SCAP + Literary Fund + guaranteed savings")))) -> SCAP + Literary Fund + guaranteed savings | N13: =IF(OR($L13="Retrofit / ESPC",$L13="Retrofit + state stack"),$B$142,IF($L13="New build / PPEA",$B$144,$B$143)) -> 0.7 | O13: =IF($D13="On Nov 2026 ballot",$B$145,IF($D13="Levying since 2020-23",$B$147,IF($D13="Deferred, eyeing 2027",$B$148,$B$146))) -> 0.8 | P13: =IF($E13=0,"",($F13/MAX($F$6:$F$138))^0.38*100*$N13*$O13) -> 16.856976 | Q13: =IF($E13=0,"","P"&MIN(4,ROUNDUP(RANK($P13,$P$6:$P$138)/COUNT($P$6:$P$138)*4,0))) -> P2 | R13: =IF($D13="On Nov 2026 ballot","Wave 1 - position before the vote",IF($D13="Deferred, eyeing 2027","Wave 3 - 2027 referendum cycle",IF($D13="Levying since 2020-23","Wave 2 - next phase / displace incumbent","Wave 1 - VERIFY referendum status first"))) -> Wave 1 - VERIFY referendum status first | S13: =IF($L13="Retrofit + state stack","SCAP application support + no-cost condition assessment",IF($L13="Retrofit / ESPC","No-cost facility condition assessment",IF($L13="New build / PPEA","PPEA concept + capital sequencing review",IF($L13="Blended programme","Capital programme structuring review","Targeted HVAC and roof scope review")))) -> Targeted HVAC and roof scope review
A14: ='Opportunity Model'!A14 -> Bath County | B14: ='Opportunity Model'!B14 -> County | C14: 5 Valley | D14: ='Opportunity Model'!D14 -> No public action found | E14: ='Opportunity Model'!E14 -> 1 | F14: ='Opportunity Model'!G14 -> 44812189 | G14: ='Opportunity Model'!F14 -> 1443091.6 | H14: ='Region Needs Profile'!B10 -> 0.0301 | I14: ='Region Needs Profile'!C10 -> 55 | J14: ='Region Needs Profile'!P10 -> 10.405306 | K14: =IF($F14>=PERCENTILE($F$6:$F$138,0.75),"High",IF($F14>=PERCENTILE($F$6:$F$138,0.4),"Moderate","Low")) -> Low | L14: =IF($J14>=40,"New build / PPEA",IF($J14<=-40,IF($K14="Low","Retrofit + state stack","Retrofit / ESPC"),IF($K14="High","Blended programme","Selective retrofit"))) -> Selective retrofit | M14: =IF($L14="New build / PPEA","Levy-backed debt + PPEA availability payment + SCAP 10%",IF($L14="Retrofit + state stack","SCAP 20-30% + Literary Fund + levy + guaranteed savings",IF($L14="Retrofit / ESPC","Levy + guaranteed savings + VPSA pooled bond",IF($L14="Blended programme","Levy-backed debt + ESPC on the retained estate","SCAP + Literary Fund + guaranteed savings")))) -> SCAP + Literary Fund + guaranteed savings | N14: =IF(OR($L14="Retrofit / ESPC",$L14="Retrofit + state stack"),$B$142,IF($L14="New build / PPEA",$B$144,$B$143)) -> 0.7 | O14: =IF($D14="On Nov 2026 ballot",$B$145,IF($D14="Levying since 2020-23",$B$147,IF($D14="Deferred, eyeing 2027",$B$148,$B$146))) -> 0.8 | P14: =IF($E14=0,"",($F14/MAX($F$6:$F$138))^0.38*100*$N14*$O14) -> 7.8617224 | Q14: =IF($E14=0,"","P"&MIN(4,ROUNDUP(RANK($P14,$P$6:$P$138)/COUNT($P$6:$P$138)*4,0))) -> P4 | R14: =IF($D14="On Nov 2026 ballot","Wave 1 - position before the vote",IF($D14="Deferred, eyeing 2027","Wave 3 - 2027 referendum cycle",IF($D14="Levying since 2020-23","Wave 2 - next phase / displace incumbent","Wave 1 - VERIFY referendum status first"))) -> Wave 1 - VERIFY referendum status first | S14: =IF($L14="Retrofit + state stack","SCAP application support + no-cost condition assessment",IF($L14="Retrofit / ESPC","No-cost facility condition assessment",IF($L14="New build / PPEA","PPEA concept + capital sequencing review",IF($L14="Blended programme","Capital programme structuring review","Targeted HVAC and roof scope review")))) -> Targeted HVAC and roof scope review
A15: ='Opportunity Model'!A15 -> Bedford County | B15: ='Opportunity Model'!B15 -> County | C15: 6 Western Virginia | D15: ='Opportunity Model'!D15 -> No public action found | E15: ='Opportunity Model'!E15 -> 1 | F15: ='Opportunity Model'!G15 -> 3.5944069e+08 | G15: ='Opportunity Model'!F15 -> 11900162 | H15: ='Region Needs Profile'!B11 -> -0.0678 | I15: ='Region Needs Profile'!C11 -> 58 | J15: ='Region Needs Profile'!P11 -> -65.331358 | K15: =IF($F15>=PERCENTILE($F$6:$F$138,0.75),"High",IF($F15>=PERCENTILE($F$6:$F$138,0.4),"Moderate","Low")) -> Moderate | L15: =IF($J15>=40,"New build / PPEA",IF($J15<=-40,IF($K15="Low","Retrofit + state stack","Retrofit / ESPC"),IF($K15="High","Blended programme","Selective retrofit"))) -> Retrofit / ESPC | M15: =IF($L15="New build / PPEA","Levy-backed debt + PPEA availability payment + SCAP 10%",IF($L15="Retrofit + state stack","SCAP 20-30% + Literary Fund + levy + guaranteed savings",IF($L15="Retrofit / ESPC","Levy + guaranteed savings + VPSA pooled bond",IF($L15="Blended programme","Levy-backed debt + ESPC on the retained estate","SCAP + Literary Fund + guaranteed savings")))) -> Levy + guaranteed savings + VPSA pooled bond | N15: =IF(OR($L15="Retrofit / ESPC",$L15="Retrofit + state stack"),$B$142,IF($L15="New build / PPEA",$B$144,$B$143)) -> 1 | O15: =IF($D15="On Nov 2026 ballot",$B$145,IF($D15="Levying since 2020-23",$B$147,IF($D15="Deferred, eyeing 2027",$B$148,$B$146))) -> 0.8 | P15: =IF($E15=0,"",($F15/MAX($F$6:$F$138))^0.38*100*$N15*$O15) -> 24.775788 | Q15: =IF($E15=0,"","P"&MIN(4,ROUNDUP(RANK($P15,$P$6:$P$138)/COUNT($P$6:$P$138)*4,0))) -> P1 | R15: =IF($D15="On Nov 2026 ballot","Wave 1 - position before the vote",IF($D15="Deferred, eyeing 2027","Wave 3 - 2027 referendum cycle",IF($D15="Levying since 2020-23","Wave 2 - next phase / displace incumbent","Wave 1 - VERIFY referendum status first"))) -> Wave 1 - VERIFY referendum status first | S15: =IF($L15="Retrofit + state stack","SCAP application support + no-cost condition assessment",IF($L15="Retrofit / ESPC","No-cost facility condition assessment",IF($L15="New build / PPEA","PPEA concept + capital sequencing review",IF($L15="Blended programme","Capital programme structuring review","Targeted HVAC and roof scope review")))) -> No-cost facility condition assessment
A16: ='Opportunity Model'!A16 -> Bland County | B16: ='Opportunity Model'!B16 -> County | C16: 7 Southwest | D16: ='Opportunity Model'!D16 -> No public action found | E16: ='Opportunity Model'!E16 -> 1 | F16: ='Opportunity Model'!G16 -> 18004006 | G16: ='Opportunity Model'!F16 -> 652438.22 | H16: ='Region Needs Profile'!B12 -> -0.1001 | I16: ='Region Needs Profile'!C12 -> 58 | J16: ='Region Needs Profile'!P12 -> -93.064667 | K16: =IF($F16>=PERCENTILE($F$6:$F$138,0.75),"High",IF($F16>=PERCENTILE($F$6:$F$138,0.4),"Moderate","Low")) -> Low | L16: =IF($J16>=40,"New build / PPEA",IF($J16<=-40,IF($K16="Low","Retrofit + state stack","Retrofit / ESPC"),IF($K16="High","Blended programme","Selective retrofit"))) -> Retrofit + state stack | M16: =IF($L16="New build / PPEA","Levy-backed debt + PPEA availability payment + SCAP 10%",IF($L16="Retrofit + state stack","SCAP 20-30% + Literary Fund + levy + guaranteed savings",IF($L16="Retrofit / ESPC","Levy + guaranteed savings + VPSA pooled bond",IF($L16="Blended programme","Levy-backed debt + ESPC on the retained estate","SCAP + Literary Fund + guaranteed savings")))) -> SCAP 20-30% + Literary Fund + levy + guaranteed savings | N16: =IF(OR($L16="Retrofit / ESPC",$L16="Retrofit + state stack"),$B$142,IF($L16="New build / PPEA",$B$144,$B$143)) -> 1 | O16: =IF($D16="On Nov 2026 ballot",$B$145,IF($D16="Levying since 2020-23",$B$147,IF($D16="Deferred, eyeing 2027",$B$148,$B$146))) -> 0.8 | P16: =IF($E16=0,"",($F16/MAX($F$6:$F$138))^0.38*100*$N16*$O16) -> 7.9419913 | Q16: =IF($E16=0,"","P"&MIN(4,ROUNDUP(RANK($P16,$P$6:$P$138)/COUNT($P$6:$P$138)*4,0))) -> P4 | R16: =IF($D16="On Nov 2026 ballot","Wave 1 - position before the vote",IF($D16="Deferred, eyeing 2027","Wave 3 - 2027 referendum cycle",IF($D16="Levying since 2020-23","Wave 2 - next phase / displace incumbent","Wave 1 - VERIFY referendum status first"))) -> Wave 1 - VERIFY referendum status first | S16: =IF($L16="Retrofit + state stack","SCAP application support + no-cost condition assessment",IF($L16="Retrofit / ESPC","No-cost facility condition assessment",IF($L16="New build / PPEA","PPEA concept + capital sequencing review",IF($L16="Blended programme","Capital programme structuring review","Targeted HVAC and roof scope review")))) -> SCAP application support + no-cost condition assessment
A17: ='Opportunity Model'!A17 -> Botetourt County | B17: ='Opportunity Model'!B17 -> County | C17: 6 Western Virginia | D17: ='Opportunity Model'!D17 -> No public action found | E17: ='Opportunity Model'!E17 -> 1 | F17: ='Opportunity Model'!G17 -> 1.5106784e+08 | G17: ='Opportunity Model'!F17 -> 5151294.2 | H17: ='Region Needs Profile'!B11 -> -0.0678 | I17: ='Region Needs Profile'!C11 -> 58 | J17: ='Region Needs Profile'!P11 -> -65.331358 | K17: =IF($F17>=PERCENTILE($F$6:$F$138,0.75),"High",IF($F17>=PERCENTILE($F$6:$F$138,0.4),"Moderate","Low")) -> Moderate | L17: =IF($J17>=40,"New build / PPEA",IF($J17<=-40,IF($K17="Low","Retrofit + state stack","Retrofit / ESPC"),IF($K17="High","Blended programme","Selective retrofit"))) -> Retrofit / ESPC | M17: =IF($L17="New build / PPEA","Levy-backed debt + PPEA availability payment + SCAP 10%",IF($L17="Retrofit + state stack","SCAP 20-30% + Literary Fund + levy + guaranteed savings",IF($L17="Retrofit / ESPC","Levy + guaranteed savings + VPSA pooled bond",IF($L17="Blended programme","Levy-backed debt + ESPC on the retained estate","SCAP + Literary Fund + guaranteed savings")))) -> Levy + guaranteed savings + VPSA pooled bond | N17: =IF(OR($L17="Retrofit / ESPC",$L17="Retrofit + state stack"),$B$142,IF($L17="New build / PPEA",$B$144,$B$143)) -> 1 | O17: =IF($D17="On Nov 2026 ballot",$B$145,IF($D17="Levying since 2020-23",$B$147,IF($D17="Deferred, eyeing 2027",$B$148,$B$146))) -> 0.8 | P17: =IF($E17=0,"",($F17/MAX($F$6:$F$138))^0.38*100*$N17*$O17) -> 17.822741 | Q17: =IF($E17=0,"","P"&MIN(4,ROUNDUP(RANK($P17,$P$6:$P$138)/COUNT($P$6:$P$138)*4,0))) -> P1 | R17: =IF($D17="On Nov 2026 ballot","Wave 1 - position before the vote",IF($D17="Deferred, eyeing 2027","Wave 3 - 2027 referendum cycle",IF($D17="Levying since 2020-23","Wave 2 - next phase / displace incumbent","Wave 1 - VERIFY referendum status first"))) -> Wave 1 - VERIFY referendum status first | S17: =IF($L17="Retrofit + state stack","SCAP application support + no-cost condition assessment",IF($L17="Retrofit / ESPC","No-cost facility condition assessment",IF($L17="New build / PPEA","PPEA concept + capital sequencing review",IF($L17="Blended programme","Capital programme structuring review","Targeted HVAC and roof scope review")))) -> No-cost facility condition assessment
A18: ='Opportunity Model'!A18 -> Brunswick County | B18: ='Opportunity Model'!B18 -> County | C18: 8 Southside | D18: ='Opportunity Model'!D18 -> No public action found | E18: ='Opportunity Model'!E18 -> 1 | F18: ='Opportunity Model'!G18 -> 37848919 | G18: ='Opportunity Model'!F18 -> 1338577.1 | H18: ='Region Needs Profile'!B13 -> -0.074 | I18: ='Region Needs Profile'!C13 -> 58 | J18: ='Region Needs Profile'!P13 -> -87.624467 | K18: =IF($F18>=PERCENTILE($F$6:$F$138,0.75),"High",IF($F18>=PERCENTILE($F$6:$F$138,0.4),"Moderate","Low")) -> Low | L18: =IF($J18>=40,"New build / PPEA",IF($J18<=-40,IF($K18="Low","Retrofit + state stack","Retrofit / ESPC"),IF($K18="High","Blended programme","Selective retrofit"))) -> Retrofit + state stack | M18: =IF($L18="New build / PPEA","Levy-backed debt + PPEA availability payment + SCAP 10%",IF($L18="Retrofit + state stack","SCAP 20-30% + Literary Fund + levy + guaranteed savings",IF($L18="Retrofit / ESPC","Levy + guaranteed savings + VPSA pooled bond",IF($L18="Blended programme","Levy-backed debt + ESPC on the retained estate","SCAP + Literary Fund + guaranteed savings")))) -> SCAP 20-30% + Literary Fund + levy + guaranteed savings | N18: =IF(OR($L18="Retrofit / ESPC",$L18="Retrofit + state stack"),$B$142,IF($L18="New build / PPEA",$B$144,$B$143)) -> 1 | O18: =IF($D18="On Nov 2026 ballot",$B$145,IF($D18="Levying since 2020-23",$B$147,IF($D18="Deferred, eyeing 2027",$B$148,$B$146))) -> 0.8 | P18: =IF($E18=0,"",($F18/MAX($F$6:$F$138))^0.38*100*$N18*$O18) -> 10.532936 | Q18: =IF($E18=0,"","P"&MIN(4,ROUNDUP(RANK($P18,$P$6:$P$138)/COUNT($P$6:$P$138)*4,0))) -> P3 | R18: =IF($D18="On Nov 2026 ballot","Wave 1 - position before the vote",IF($D18="Deferred, eyeing 2027","Wave 3 - 2027 referendum cycle",IF($D18="Levying since 2020-23","Wave 2 - next phase / displace incumbent","Wave 1 - VERIFY referendum status first"))) -> Wave 1 - VERIFY referendum status first | S18: =IF($L18="Retrofit + state stack","SCAP application support + no-cost condition assessment",IF($L18="Retrofit / ESPC","No-cost facility condition assessment",IF($L18="New build / PPEA","PPEA concept + capital sequencing review",IF($L18="Blended programme","Capital programme structuring review","Targeted HVAC and roof scope review")))) -> SCAP application support + no-cost condition assessment
A19: ='Opportunity Model'!A19 -> Buchanan County | B19: ='Opportunity Model'!B19 -> County | C19: 7 Southwest | D19: ='Opportunity Model'!D19 -> Deferred, eyeing 2027 | E19: ='Opportunity Model'!E19 -> 1 | F19: ='Opportunity Model'!G19 -> 61764927 | G19: ='Opportunity Model'!F19 -> 2407004.7 | H19: ='Region Needs Profile'!B12 -> -0.1001 | I19: ='Region Needs Profile'!C12 -> 58 | J19: ='Region Needs Profile'!P12 -> -93.064667 | K19: =IF($F19>=PERCENTILE($F$6:$F$138,0.75),"High",IF($F19>=PERCENTILE($F$6:$F$138,0.4),"Moderate","Low")) -> Low | L19: =IF($J19>=40,"New build / PPEA",IF($J19<=-40,IF($K19="Low","Retrofit + state stack","Retrofit / ESPC"),IF($K19="High","Blended programme","Selective retrofit"))) -> Retrofit + state stack | M19: =IF($L19="New build / PPEA","Levy-backed debt + PPEA availability payment + SCAP 10%",IF($L19="Retrofit + state stack","SCAP 20-30% + Literary Fund + levy + guaranteed savings",IF($L19="Retrofit / ESPC","Levy + guaranteed savings + VPSA pooled bond",IF($L19="Blended programme","Levy-backed debt + ESPC on the retained estate","SCAP + Literary Fund + guaranteed savings")))) -> SCAP 20-30% + Literary Fund + levy + guaranteed savings | N19: =IF(OR($L19="Retrofit / ESPC",$L19="Retrofit + state stack"),$B$142,IF($L19="New build / PPEA",$B$144,$B$143)) -> 1 | O19: =IF($D19="On Nov 2026 ballot",$B$145,IF($D19="Levying since 2020-23",$B$147,IF($D19="Deferred, eyeing 2027",$B$148,$B$146))) -> 0.55 | P19: =IF($E19=0,"",($F19/MAX($F$6:$F$138))^0.38*100*$N19*$O19) -> 8.7225559 | Q19: =IF($E19=0,"","P"&MIN(4,ROUNDUP(RANK($P19,$P$6:$P$138)/COUNT($P$6:$P$138)*4,0))) -> P3 | R19: =IF($D19="On Nov 2026 ballot","Wave 1 - position before the vote",IF($D19="Deferred, eyeing 2027","Wave 3 - 2027 referendum cycle",IF($D19="Levying since 2020-23","Wave 2 - next phase / displace incumbent","Wave 1 - VERIFY referendum status first"))) -> Wave 3 - 2027 referendum cycle | S19: =IF($L19="Retrofit + state stack","SCAP application support + no-cost condition assessment",IF($L19="Retrofit / ESPC","No-cost facility condition assessment",IF($L19="New build / PPEA","PPEA concept + capital sequencing review",IF($L19="Blended programme","Capital programme structuring review","Targeted HVAC and roof scope review")))) -> SCAP application support + no-cost condition assessment
A20: ='Opportunity Model'!A20 -> Buckingham County | B20: ='Opportunity Model'!B20 -> County | C20: 8 Southside | D20: ='Opportunity Model'!D20 -> No public action found | E20: ='Opportunity Model'!E20 -> 1 | F20: ='Opportunity Model'!G20 -> 38350565 | G20: ='Opportunity Model'!F20 -> 1376346 | H20: ='Region Needs Profile'!B13 -> -0.074 | I20: ='Region Needs Profile'!C13 -> 58 | J20: ='Region Needs Profile'!P13 -> -87.624467 | K20: =IF($F20>=PERCENTILE($F$6:$F$138,0.75),"High",IF($F20>=PERCENTILE($F$6:$F$138,0.4),"Moderate","Low")) -> Low | L20: =IF($J20>=40,"New build / PPEA",IF($J20<=-40,IF($K20="Low","Retrofit + state stack","Retrofit / ESPC"),IF($K20="High","Blended programme","Selective retrofit"))) -> Retrofit + state stack | M20: =IF($L20="New build / PPEA","Levy-backed debt + PPEA availability payment + SCAP 10%",IF($L20="Retrofit + state stack","SCAP 20-30% + Literary Fund + levy + guaranteed savings",IF($L20="Retrofit / ESPC","Levy + guaranteed savings + VPSA pooled bond",IF($L20="Blended programme","Levy-backed debt + ESPC on the retained estate","SCAP + Literary Fund + guaranteed savings")))) -> SCAP 20-30% + Literary Fund + levy + guaranteed savings | N20: =IF(OR($L20="Retrofit / ESPC",$L20="Retrofit + state stack"),$B$142,IF($L20="New build / PPEA",$B$144,$B$143)) -> 1 | O20: =IF($D20="On Nov 2026 ballot",$B$145,IF($D20="Levying since 2020-23",$B$147,IF($D20="Deferred, eyeing 2027",$B$148,$B$146))) -> 0.8 | P20: =IF($E20=0,"",($F20/MAX($F$6:$F$138))^0.38*100*$N20*$O20) -> 10.585769 | Q20: =IF($E20=0,"","P"&MIN(4,ROUNDUP(RANK($P20,$P$6:$P$138)/COUNT($P$6:$P$138)*4,0))) -> P3 | R20: =IF($D20="On Nov 2026 ballot","Wave 1 - position before the vote",IF($D20="Deferred, eyeing 2027","Wave 3 - 2027 referendum cycle",IF($D20="Levying since 2020-23","Wave 2 - next phase / displace incumbent","Wave 1 - VERIFY referendum status first"))) -> Wave 1 - VERIFY referendum status first | S20: =IF($L20="Retrofit + state stack","SCAP application support + no-cost condition assessment",IF($L20="Retrofit / ESPC","No-cost facility condition assessment",IF($L20="New build / PPEA","PPEA concept + capital sequencing review",IF($L20="Blended programme","Capital programme structuring review","Targeted HVAC and roof scope review")))) -> SCAP application support + no-cost condition assessment
A21: ='Opportunity Model'!A21 -> Campbell County | B21: ='Opportunity Model'!B21 -> County | C21: 6 Western Virginia | D21: ='Opportunity Model'!D21 -> No public action found | E21: ='Opportunity Model'!E21 -> 1 | F21: ='Opportunity Model'!G21 -> 2.9924863e+08 | G21: ='Opportunity Model'!F21 -> 9953324 | H21: ='Region Needs Profile'!B11 -> -0.0678 | I21: ='Region Needs Profile'!C11 -> 58 | J21: ='Region Needs Profile'!P11 -> -65.331358 | K21: =IF($F21>=PERCENTILE($F$6:$F$138,0.75),"High",IF($F21>=PERCENTILE($F$6:$F$138,0.4),"Moderate","Low")) -> Moderate | L21: =IF($J21>=40,"New build / PPEA",IF($J21<=-40,IF($K21="Low","Retrofit + state stack","Retrofit / ESPC"),IF($K21="High","Blended programme","Selective retrofit"))) -> Retrofit / ESPC | M21: =IF($L21="New build / PPEA","Levy-backed debt + PPEA availability payment + SCAP 10%",IF($L21="Retrofit + state stack","SCAP 20-30% + Literary Fund + levy + guaranteed savings",IF($L21="Retrofit / ESPC","Levy + guaranteed savings + VPSA pooled bond",IF($L21="Blended programme","Levy-backed debt + ESPC on the retained estate","SCAP + Literary Fund + guaranteed savings")))) -> Levy + guaranteed savings + VPSA pooled bond | N21: =IF(OR($L21="Retrofit / ESPC",$L21="Retrofit + state stack"),$B$142,IF($L21="New build / PPEA",$B$144,$B$143)) -> 1 | O21: =IF($D21="On Nov 2026 ballot",$B$145,IF($D21="Levying since 2020-23",$B$147,IF($D21="Deferred, eyeing 2027",$B$148,$B$146))) -> 0.8 | P21: =IF($E21=0,"",($F21/MAX($F$6:$F$138))^0.38*100*$N21*$O21) -> 23.10901 | Q21: =IF($E21=0,"","P"&MIN(4,ROUNDUP(RANK($P21,$P$6:$P$138)/COUNT($P$6:$P$138)*4,0))) -> P1 | R21: =IF($D21="On Nov 2026 ballot","Wave 1 - position before the vote",IF($D21="Deferred, eyeing 2027","Wave 3 - 2027 referendum cycle",IF($D21="Levying since 2020-23","Wave 2 - next phase / displace incumbent","Wave 1 - VERIFY referendum status first"))) -> Wave 1 - VERIFY referendum status first | S21: =IF($L21="Retrofit + state stack","SCAP application support + no-cost condition assessment",IF($L21="Retrofit / ESPC","No-cost facility condition assessment",IF($L21="New build / PPEA","PPEA concept + capital sequencing review",IF($L21="Blended programme","Capital programme structuring review","Targeted HVAC and roof scope review")))) -> No-cost facility condition assessment
A22: ='Opportunity Model'!A22 -> Caroline County | B22: ='Opportunity Model'!B22 -> County | C22: 3 Northern Neck | D22: ='Opportunity Model'!D22 -> No public action found | E22: ='Opportunity Model'!E22 -> 1 | F22: ='Opportunity Model'!G22 -> 1.5773998e+08 | G22: ='Opportunity Model'!F22 -> 4790807.9 | H22: ='Region Needs Profile'!B8 -> 0.1108 | I22: ='Region Needs Profile'!C8 -> 32 | J22: ='Region Needs Profile'!P8 -> 86.269916 | K22: =IF($F22>=PERCENTILE($F$6:$F$138,0.75),"High",IF($F22>=PERCENTILE($F$6:$F$138,0.4),"Moderate","Low")) -> Moderate | L22: =IF($J22>=40,"New build / PPEA",IF($J22<=-40,IF($K22="Low","Retrofit + state stack","Retrofit / ESPC"),IF($K22="High","Blended programme","Selective retrofit"))) -> New build / PPEA | M22: =IF($L22="New build / PPEA","Levy-backed debt + PPEA availability payment + SCAP 10%",IF($L22="Retrofit + state stack","SCAP 20-30% + Literary Fund + levy + guaranteed savings",IF($L22="Retrofit / ESPC","Levy + guaranteed savings + VPSA pooled bond",IF($L22="Blended programme","Levy-backed debt + ESPC on the retained estate","SCAP + Literary Fund + guaranteed savings")))) -> Levy-backed debt + PPEA availability payment + SCAP 10% | N22: =IF(OR($L22="Retrofit / ESPC",$L22="Retrofit + state stack"),$B$142,IF($L22="New build / PPEA",$B$144,$B$143)) -> 0.45 | O22: =IF($D22="On Nov 2026 ballot",$B$145,IF($D22="Levying since 2020-23",$B$147,IF($D22="Deferred, eyeing 2027",$B$148,$B$146))) -> 0.8 | P22: =IF($E22=0,"",($F22/MAX($F$6:$F$138))^0.38*100*$N22*$O22) -> 8.153039 | Q22: =IF($E22=0,"","P"&MIN(4,ROUNDUP(RANK($P22,$P$6:$P$138)/COUNT($P$6:$P$138)*4,0))) -> P4 | R22: =IF($D22="On Nov 2026 ballot","Wave 1 - position before the vote",IF($D22="Deferred, eyeing 2027","Wave 3 - 2027 referendum cycle",IF($D22="Levying since 2020-23","Wave 2 - next phase / displace incumbent","Wave 1 - VERIFY referendum status first"))) -> Wave 1 - VERIFY referendum status first | S22: =IF($L22="Retrofit + state stack","SCAP application support + no-cost condition assessment",IF($L22="Retrofit / ESPC","No-cost facility condition assessment",IF($L22="New build / PPEA","PPEA concept + capital sequencing review",IF($L22="Blended programme","Capital programme structuring review","Targeted HVAC and roof scope review")))) -> PPEA concept + capital sequencing review
A23: ='Opportunity Model'!A23 -> Carroll County | B23: ='Opportunity Model'!B23 -> County | C23: 7 Southwest | D23: ='Opportunity Model'!D23 -> No public action found | E23: ='Opportunity Model'!E23 -> 1 | F23: ='Opportunity Model'!G23 -> 1.0271323e+08 | G23: ='Opportunity Model'!F23 -> 3566283.1 | H23: ='Region Needs Profile'!B12 -> -0.1001 | I23: ='Region Needs Profile'!C12 -> 58 | J23: ='Region Needs Profile'!P12 -> -93.064667 | K23: =IF($F23>=PERCENTILE($F$6:$F$138,0.75),"High",IF($F23>=PERCENTILE($F$6:$F$138,0.4),"Moderate","Low")) -> Moderate | L23: =IF($J23>=40,"New build / PPEA",IF($J23<=-40,IF($K23="Low","Retrofit + state stack","Retrofit / ESPC"),IF($K23="High","Blended programme","Selective retrofit"))) -> Retrofit / ESPC | M23: =IF($L23="New build / PPEA","Levy-backed debt + PPEA availability payment + SCAP 10%",IF($L23="Retrofit + state stack","SCAP 20-30% + Literary Fund + levy + guaranteed savings",IF($L23="Retrofit / ESPC","Levy + guaranteed savings + VPSA pooled bond",IF($L23="Blended programme","Levy-backed debt + ESPC on the retained estate","SCAP + Literary Fund + guaranteed savings")))) -> Levy + guaranteed savings + VPSA pooled bond | N23: =IF(OR($L23="Retrofit / ESPC",$L23="Retrofit + state stack"),$B$142,IF($L23="New build / PPEA",$B$144,$B$143)) -> 1 | O23: =IF($D23="On Nov 2026 ballot",$B$145,IF($D23="Levying since 2020-23",$B$147,IF($D23="Deferred, eyeing 2027",$B$148,$B$146))) -> 0.8 | P23: =IF($E23=0,"",($F23/MAX($F$6:$F$138))^0.38*100*$N23*$O23) -> 15.392429 | Q23: =IF($E23=0,"","P"&MIN(4,ROUNDUP(RANK($P23,$P$6:$P$138)/COUNT($P$6:$P$138)*4,0))) -> P2 | R23: =IF($D23="On Nov 2026 ballot","Wave 1 - position before the vote",IF($D23="Deferred, eyeing 2027","Wave 3 - 2027 referendum cycle",IF($D23="Levying since 2020-23","Wave 2 - next phase / displace incumbent","Wave 1 - VERIFY referendum status first"))) -> Wave 1 - VERIFY referendum status first | S23: =IF($L23="Retrofit + state stack","SCAP application support + no-cost condition assessment",IF($L23="Retrofit / ESPC","No-cost facility condition assessment",IF($L23="New build / PPEA","PPEA concept + capital sequencing review",IF($L23="Blended programme","Capital programme structuring review","Targeted HVAC and roof scope review")))) -> No-cost facility condition assessment
A24: ='Opportunity Model'!A24 -> Charles City County | B24: ='Opportunity Model'!B24 -> County | C24: 1 Central Virginia | D24: ='Opportunity Model'!D24 -> No public action found | E24: ='Opportunity Model'!E24 -> 1 | F24: ='Opportunity Model'!G24 -> 49881441 | G24: ='Opportunity Model'!F24 -> 1641347.7 | H24: ='Region Needs Profile'!B6 -> 0.0584 | I24: ='Region Needs Profile'!C6 -> 50 | J24: ='Region Needs Profile'!P6 -> 20.904228 | K24: =IF($F24>=PERCENTILE($F$6:$F$138,0.75),"High",IF($F24>=PERCENTILE($F$6:$F$138,0.4),"Moderate","Low")) -> Low | L24: =IF($J24>=40,"New build / PPEA",IF($J24<=-40,IF($K24="Low","Retrofit + state stack","Retrofit / ESPC"),IF($K24="High","Blended programme","Selective retrofit"))) -> Selective retrofit | M24: =IF($L24="New build / PPEA","Levy-backed debt + PPEA availability payment + SCAP 10%",IF($L24="Retrofit + state stack","SCAP 20-30% + Literary Fund + levy + guaranteed savings",IF($L24="Retrofit / ESPC","Levy + guaranteed savings + VPSA pooled bond",IF($L24="Blended programme","Levy-backed debt + ESPC on the retained estate","SCAP + Literary Fund + guaranteed savings")))) -> SCAP + Literary Fund + guaranteed savings | N24: =IF(OR($L24="Retrofit / ESPC",$L24="Retrofit + state stack"),$B$142,IF($L24="New build / PPEA",$B$144,$B$143)) -> 0.7 | O24: =IF($D24="On Nov 2026 ballot",$B$145,IF($D24="Levying since 2020-23",$B$147,IF($D24="Deferred, eyeing 2027",$B$148,$B$146))) -> 0.8 | P24: =IF($E24=0,"",($F24/MAX($F$6:$F$138))^0.38*100*$N24*$O24) -> 8.188493 | Q24: =IF($E24=0,"","P"&MIN(4,ROUNDUP(RANK($P24,$P$6:$P$138)/COUNT($P$6:$P$138)*4,0))) -> P4 | R24: =IF($D24="On Nov 2026 ballot","Wave 1 - position before the vote",IF($D24="Deferred, eyeing 2027","Wave 3 - 2027 referendum cycle",IF($D24="Levying since 2020-23","Wave 2 - next phase / displace incumbent","Wave 1 - VERIFY referendum status first"))) -> Wave 1 - VERIFY referendum status first | S24: =IF($L24="Retrofit + state stack","SCAP application support + no-cost condition assessment",IF($L24="Retrofit / ESPC","No-cost facility condition assessment",IF($L24="New build / PPEA","PPEA concept + capital sequencing review",IF($L24="Blended programme","Capital programme structuring review","Targeted HVAC and roof scope review")))) -> Targeted HVAC and roof scope review
A25: ='Opportunity Model'!A25 -> Charlotte County | B25: ='Opportunity Model'!B25 -> County | C25: 8 Southside | D25: ='Opportunity Model'!D25 -> Levying since 2020-23 | E25: ='Opportunity Model'!E25 -> 1 | F25: ='Opportunity Model'!G25 -> 30261480 | G25: ='Opportunity Model'!F25 -> 1132192.2 | H25: ='Region Needs Profile'!B13 -> -0.074 | I25: ='Region Needs Profile'!C13 -> 58 | J25: ='Region Needs Profile'!P13 -> -87.624467 | K25: =IF($F25>=PERCENTILE($F$6:$F$138,0.75),"High",IF($F25>=PERCENTILE($F$6:$F$138,0.4),"Moderate","Low")) -> Low | L25: =IF($J25>=40,"New build / PPEA",IF($J25<=-40,IF($K25="Low","Retrofit + state stack","Retrofit / ESPC"),IF($K25="High","Blended programme","Selective retrofit"))) -> Retrofit + state stack | M25: =IF($L25="New build / PPEA","Levy-backed debt + PPEA availability payment + SCAP 10%",IF($L25="Retrofit + state stack","SCAP 20-30% + Literary Fund + levy + guaranteed savings",IF($L25="Retrofit / ESPC","Levy + guaranteed savings + VPSA pooled bond",IF($L25="Blended programme","Levy-backed debt + ESPC on the retained estate","SCAP + Literary Fund + guaranteed savings")))) -> SCAP 20-30% + Literary Fund + levy + guaranteed savings | N25: =IF(OR($L25="Retrofit / ESPC",$L25="Retrofit + state stack"),$B$142,IF($L25="New build / PPEA",$B$144,$B$143)) -> 1 | O25: =IF($D25="On Nov 2026 ballot",$B$145,IF($D25="Levying since 2020-23",$B$147,IF($D25="Deferred, eyeing 2027",$B$148,$B$146))) -> 0.65 | P25: =IF($E25=0,"",($F25/MAX($F$6:$F$138))^0.38*100*$N25*$O25) -> 7.8605106 | Q25: =IF($E25=0,"","P"&MIN(4,ROUNDUP(RANK($P25,$P$6:$P$138)/COUNT($P$6:$P$138)*4,0))) -> P4 | R25: =IF($D25="On Nov 2026 ballot","Wave 1 - position before the vote",IF($D25="Deferred, eyeing 2027","Wave 3 - 2027 referendum cycle",IF($D25="Levying since 2020-23","Wave 2 - next phase / displace incumbent","Wave 1 - VERIFY referendum status first"))) -> Wave 2 - next phase / displace incumbent | S25: =IF($L25="Retrofit + state stack","SCAP application support + no-cost condition assessment",IF($L25="Retrofit / ESPC","No-cost facility condition assessment",IF($L25="New build / PPEA","PPEA concept + capital sequencing review",IF($L25="Blended programme","Capital programme structuring review","Targeted HVAC and roof scope review")))) -> SCAP application support + no-cost condition assessment
A26: ='Opportunity Model'!A26 -> Chesterfield County | B26: ='Opportunity Model'!B26 -> County | C26: 1 Central Virginia | D26: ='Opportunity Model'!D26 -> On Nov 2026 ballot | E26: ='Opportunity Model'!E26 -> 1 | F26: ='Opportunity Model'!G26 -> 2.7806966e+09 | G26: ='Opportunity Model'!F26 -> 87966826 | H26: ='Region Needs Profile'!B6 -> 0.0584 | I26: ='Region Needs Profile'!C6 -> 50 | J26: ='Region Needs Profile'!P6 -> 20.904228 | K26: =IF($F26>=PERCENTILE($F$6:$F$138,0.75),"High",IF($F26>=PERCENTILE($F$6:$F$138,0.4),"Moderate","Low")) -> High | L26: =IF($J26>=40,"New build / PPEA",IF($J26<=-40,IF($K26="Low","Retrofit + state stack","Retrofit / ESPC"),IF($K26="High","Blended programme","Selective retrofit"))) -> Blended programme | M26: =IF($L26="New build / PPEA","Levy-backed debt + PPEA availability payment + SCAP 10%",IF($L26="Retrofit + state stack","SCAP 20-30% + Literary Fund + levy + guaranteed savings",IF($L26="Retrofit / ESPC","Levy + guaranteed savings + VPSA pooled bond",IF($L26="Blended programme","Levy-backed debt + ESPC on the retained estate","SCAP + Literary Fund + guaranteed savings")))) -> Levy-backed debt + ESPC on the retained estate | N26: =IF(OR($L26="Retrofit / ESPC",$L26="Retrofit + state stack"),$B$142,IF($L26="New build / PPEA",$B$144,$B$143)) -> 0.7 | O26: =IF($D26="On Nov 2026 ballot",$B$145,IF($D26="Levying since 2020-23",$B$147,IF($D26="Deferred, eyeing 2027",$B$148,$B$146))) -> 1 | P26: =IF($E26=0,"",($F26/MAX($F$6:$F$138))^0.38*100*$N26*$O26) -> 47.171051 | Q26: =IF($E26=0,"","P"&MIN(4,ROUNDUP(RANK($P26,$P$6:$P$138)/COUNT($P$6:$P$138)*4,0))) -> P1 | R26: =IF($D26="On Nov 2026 ballot","Wave 1 - position before the vote",IF($D26="Deferred, eyeing 2027","Wave 3 - 2027 referendum cycle",IF($D26="Levying since 2020-23","Wave 2 - next phase / displace incumbent","Wave 1 - VERIFY referendum status first"))) -> Wave 1 - position before the vote | S26: =IF($L26="Retrofit + state stack","SCAP application support + no-cost condition assessment",IF($L26="Retrofit / ESPC","No-cost facility condition assessment",IF($L26="New build / PPEA","PPEA concept + capital sequencing review",IF($L26="Blended programme","Capital programme structuring review","Targeted HVAC and roof scope review")))) -> Capital programme structuring review
A27: ='Opportunity Model'!A27 -> Clarke County | B27: ='Opportunity Model'!B27 -> County | C27: 4 Northern Virginia | D27: ='Opportunity Model'!D27 -> No public action found | E27: ='Opportunity Model'!E27 -> 1 | F27: ='Opportunity Model'!G27 -> 72024100 | G27: ='Opportunity Model'!F27 -> 2322500.6 | H27: ='Region Needs Profile'!B9 -> 0.0794 | I27: ='Region Needs Profile'!C9 -> 48 | J27: ='Region Needs Profile'!P9 -> 54.342196 | K27: =IF($F27>=PERCENTILE($F$6:$F$138,0.75),"High",IF($F27>=PERCENTILE($F$6:$F$138,0.4),"Moderate","Low")) -> Low | L27: =IF($J27>=40,"New build / PPEA",IF($J27<=-40,IF($K27="Low","Retrofit + state stack","Retrofit / ESPC"),IF($K27="High","Blended programme","Selective retrofit"))) -> New build / PPEA | M27: =IF($L27="New build / PPEA","Levy-backed debt + PPEA availability payment + SCAP 10%",IF($L27="Retrofit + state stack","SCAP 20-30% + Literary Fund + levy + guaranteed savings",IF($L27="Retrofit / ESPC","Levy + guaranteed savings + VPSA pooled bond",IF($L27="Blended programme","Levy-backed debt + ESPC on the retained estate","SCAP + Literary Fund + guaranteed savings")))) -> Levy-backed debt + PPEA availability payment + SCAP 10% | N27: =IF(OR($L27="Retrofit / ESPC",$L27="Retrofit + state stack"),$B$142,IF($L27="New build / PPEA",$B$144,$B$143)) -> 0.45 | O27: =IF($D27="On Nov 2026 ballot",$B$145,IF($D27="Levying since 2020-23",$B$147,IF($D27="Deferred, eyeing 2027",$B$148,$B$146))) -> 0.8 | P27: =IF($E27=0,"",($F27/MAX($F$6:$F$138))^0.38*100*$N27*$O27) -> 6.0526174 | Q27: =IF($E27=0,"","P"&MIN(4,ROUNDUP(RANK($P27,$P$6:$P$138)/COUNT($P$6:$P$138)*4,0))) -> P4 | R27: =IF($D27="On Nov 2026 ballot","Wave 1 - position before the vote",IF($D27="Deferred, eyeing 2027","Wave 3 - 2027 referendum cycle",IF($D27="Levying since 2020-23","Wave 2 - next phase / displace incumbent","Wave 1 - VERIFY referendum status first"))) -> Wave 1 - VERIFY referendum status first | S27: =IF($L27="Retrofit + state stack","SCAP application support + no-cost condition assessment",IF($L27="Retrofit / ESPC","No-cost facility condition assessment",IF($L27="New build / PPEA","PPEA concept + capital sequencing review",IF($L27="Blended programme","Capital programme structuring review","Targeted HVAC and roof scope review")))) -> PPEA concept + capital sequencing review
A28: ='Opportunity Model'!A28 -> Craig County | B28: ='Opportunity Model'!B28 -> County | C28: 7 Southwest | D28: ='Opportunity Model'!D28 -> No public action found | E28: ='Opportunity Model'!E28 -> 1 | F28: ='Opportunity Model'!G28 -> 9330012.1 | G28: ='Opportunity Model'!F28 -> 343384.14 | H28: ='Region Needs Profile'!B12 -> -0.1001 | I28: ='Region Needs Profile'!C12 -> 58 | J28: ='Region Needs Profile'!P12 -> -93.064667 | K28: =IF($F28>=PERCENTILE($F$6:$F$138,0.75),"High",IF($F28>=PERCENTILE($F$6:$F$138,0.4),"Moderate","Low")) -> Low | L28: =IF($J28>=40,"New build / PPEA",IF($J28<=-40,IF($K28="Low","Retrofit + state stack","Retrofit / ESPC"),IF($K28="High","Blended programme","Selective retrofit"))) -> Retrofit + state stack | M28: =IF($L28="New build / PPEA","Levy-backed debt + PPEA availability payment + SCAP 10%",IF($L28="Retrofit + state stack","SCAP 20-30% + Literary Fund + levy + guaranteed savings",IF($L28="Retrofit / ESPC","Levy + guaranteed savings + VPSA pooled bond",IF($L28="Blended programme","Levy-backed debt + ESPC on the retained estate","SCAP + Literary Fund + guaranteed savings")))) -> SCAP 20-30% + Literary Fund + levy + guaranteed savings | N28: =IF(OR($L28="Retrofit / ESPC",$L28="Retrofit + state stack"),$B$142,IF($L28="New build / PPEA",$B$144,$B$143)) -> 1 | O28: =IF($D28="On Nov 2026 ballot",$B$145,IF($D28="Levying since 2020-23",$B$147,IF($D28="Deferred, eyeing 2027",$B$148,$B$146))) -> 0.8 | P28: =IF($E28=0,"",($F28/MAX($F$6:$F$138))^0.38*100*$N28*$O28) -> 6.1864907 | Q28: =IF($E28=0,"","P"&MIN(4,ROUNDUP(RANK($P28,$P$6:$P$138)/COUNT($P$6:$P$138)*4,0))) -> P4 | R28: =IF($D28="On Nov 2026 ballot","Wave 1 - position before the vote",IF($D28="Deferred, eyeing 2027","Wave 3 - 2027 referendum cycle",IF($D28="Levying since 2020-23","Wave 2 - next phase / displace incumbent","Wave 1 - VERIFY referendum status first"))) -> Wave 1 - VERIFY referendum status first | S28: =IF($L28="Retrofit + state stack","SCAP application support + no-cost condition assessment",IF($L28="Retrofit / ESPC","No-cost facility condition assessment",IF($L28="New build / PPEA","PPEA concept + capital sequencing review",IF($L28="Blended programme","Capital programme structuring review","Targeted HVAC and roof scope review")))) -> SCAP application support + no-cost condition assessment
A29: ='Opportunity Model'!A29 -> Culpeper County | B29: ='Opportunity Model'!B29 -> County | C29: 4 Northern Virginia | D29: ='Opportunity Model'!D29 -> No public action found | E29: ='Opportunity Model'!E29 -> 1 | F29: ='Opportunity Model'!G29 -> 4.1390852e+08 | G29: ='Opportunity Model'!F29 -> 13458092 | H29: ='Region Needs Profile'!B9 -> 0.0794 | I29: ='Region Needs Profile'!C9 -> 48 | J29: ='Region Needs Profile'!P9 -> 54.342196 | K29: =IF($F29>=PERCENTILE($F$6:$F$138,0.75),"High",IF($F29>=PERCENTILE($F$6:$F$138,0.4),"Moderate","Low")) -> Moderate | L29: =IF($J29>=40,"New build / PPEA",IF($J29<=-40,IF($K29="Low","Retrofit + state stack","Retrofit / ESPC"),IF($K29="High","Blended programme","Selective retrofit"))) -> New build / PPEA | M29: =IF($L29="New build / PPEA","Levy-backed debt + PPEA availability payment + SCAP 10%",IF($L29="Retrofit + state stack","SCAP 20-30% + Literary Fund + levy + guaranteed savings",IF($L29="Retrofit / ESPC","Levy + guaranteed savings + VPSA pooled bond",IF($L29="Blended programme","Levy-backed debt + ESPC on the retained estate","SCAP + Literary Fund + guaranteed savings")))) -> Levy-backed debt + PPEA availability payment + SCAP 10% | N29: =IF(OR($L29="Retrofit / ESPC",$L29="Retrofit + state stack"),$B$142,IF($L29="New build / PPEA",$B$144,$B$143)) -> 0.45 | O29: =IF($D29="On Nov 2026 ballot",$B$145,IF($D29="Levying since 2020-23",$B$147,IF($D29="Deferred, eyeing 2027",$B$148,$B$146))) -> 0.8 | P29: =IF($E29=0,"",($F29/MAX($F$6:$F$138))^0.38*100*$N29*$O29) -> 11.763195 | Q29: =IF($E29=0,"","P"&MIN(4,ROUNDUP(RANK($P29,$P$6:$P$138)/COUNT($P$6:$P$138)*4,0))) -> P3 | R29: =IF($D29="On Nov 2026 ballot","Wave 1 - position before the vote",IF($D29="Deferred, eyeing 2027","Wave 3 - 2027 referendum cycle",IF($D29="Levying since 2020-23","Wave 2 - next phase / displace incumbent","Wave 1 - VERIFY referendum status first"))) -> Wave 1 - VERIFY referendum status first | S29: =IF($L29="Retrofit + state stack","SCAP application support + no-cost condition assessment",IF($L29="Retrofit / ESPC","No-cost facility condition assessment",IF($L29="New build / PPEA","PPEA concept + capital sequencing review",IF($L29="Blended programme","Capital programme structuring review","Targeted HVAC and roof scope review")))) -> PPEA concept + capital sequencing review
A30: ='Opportunity Model'!A30 -> Cumberland County | B30: ='Opportunity Model'!B30 -> County | C30: 8 Southside | D30: ='Opportunity Model'!D30 -> No public action found | E30: ='Opportunity Model'!E30 -> 1 | F30: ='Opportunity Model'!G30 -> 24998931 | G30: ='Opportunity Model'!F30 -> 881824.52 | H30: ='Region Needs Profile'!B13 -> -0.074 | I30: ='Region Needs Profile'!C13 -> 58 | J30: ='Region Needs Profile'!P13 -> -87.624467 | K30: =IF($F30>=PERCENTILE($F$6:$F$138,0.75),"High",IF($F30>=PERCENTILE($F$6:$F$138,0.4),"Moderate","Low")) -> Low | L30: =IF($J30>=40,"New build / PPEA",IF($J30<=-40,IF($K30="Low","Retrofit + state stack","Retrofit / ESPC"),IF($K30="High","Blended programme","Selective retrofit"))) -> Retrofit + state stack | M30: =IF($L30="New build / PPEA","Levy-backed debt + PPEA availability payment + SCAP 10%",IF($L30="Retrofit + state stack","SCAP 20-30% + Literary Fund + levy + guaranteed savings",IF($L30="Retrofit / ESPC","Levy + guaranteed savings + VPSA pooled bond",IF($L30="Blended programme","Levy-backed debt + ESPC on the retained estate","SCAP + Literary Fund + guaranteed savings")))) -> SCAP 20-30% + Literary Fund + levy + guaranteed savings | N30: =IF(OR($L30="Retrofit / ESPC",$L30="Retrofit + state stack"),$B$142,IF($L30="New build / PPEA",$B$144,$B$143)) -> 1 | O30: =IF($D30="On Nov 2026 ballot",$B$145,IF($D30="Levying since 2020-23",$B$147,IF($D30="Deferred, eyeing 2027",$B$148,$B$146))) -> 0.8 | P30: =IF($E30=0,"",($F30/MAX($F$6:$F$138))^0.38*100*$N30*$O30) -> 8.9970321 | Q30: =IF($E30=0,"","P"&MIN(4,ROUNDUP(RANK($P30,$P$6:$P$138)/COUNT($P$6:$P$138)*4,0))) -> P3 | R30: =IF($D30="On Nov 2026 ballot","Wave 1 - position before the vote",IF($D30="Deferred, eyeing 2027","Wave 3 - 2027 referendum cycle",IF($D30="Levying since 2020-23","Wave 2 - next phase / displace incumbent","Wave 1 - VERIFY referendum status first"))) -> Wave 1 - VERIFY referendum status first | S30: =IF($L30="Retrofit + state stack","SCAP application support + no-cost condition assessment",IF($L30="Retrofit / ESPC","No-cost facility condition assessment",IF($L30="New build / PPEA","PPEA concept + capital sequencing review",IF($L30="Blended programme","Capital programme structuring review","Targeted HVAC and roof scope review")))) -> SCAP application support + no-cost condition assessment
A31: ='Opportunity Model'!A31 -> Dickenson County | B31: ='Opportunity Model'!B31 -> County | C31: 7 Southwest | D31: ='Opportunity Model'!D31 -> Deferred, eyeing 2027 | E31: ='Opportunity Model'!E31 -> 1 | F31: ='Opportunity Model'!G31 -> 33000877 | G31: ='Opportunity Model'!F31 -> 1207586 | H31: ='Region Needs Profile'!B12 -> -0.1001 | I31: ='Region Needs Profile'!C12 -> 58 | J31: ='Region Needs Profile'!P12 -> -93.064667 | K31: =IF($F31>=PERCENTILE($F$6:$F$138,0.75),"High",IF($F31>=PERCENTILE($F$6:$F$138,0.4),"Moderate","Low")) -> Low | L31: =IF($J31>=40,"New build / PPEA",IF($J31<=-40,IF($K31="Low","Retrofit + state stack","Retrofit / ESPC"),IF($K31="High","Blended programme","Selective retrofit"))) -> Retrofit + state stack | M31: =IF($L31="New build / PPEA","Levy-backed debt + PPEA availability payment + SCAP 10%",IF($L31="Retrofit + state stack","SCAP 20-30% + Literary Fund + levy + guaranteed savings",IF($L31="Retrofit / ESPC","Levy + guaranteed savings + VPSA pooled bond",IF($L31="Blended programme","Levy-backed debt + ESPC on the retained estate","SCAP + Literary Fund + guaranteed savings")))) -> SCAP 20-30% + Literary Fund + levy + guaranteed savings | N31: =IF(OR($L31="Retrofit / ESPC",$L31="Retrofit + state stack"),$B$142,IF($L31="New build / PPEA",$B$144,$B$143)) -> 1 | O31: =IF($D31="On Nov 2026 ballot",$B$145,IF($D31="Levying since 2020-23",$B$147,IF($D31="Deferred, eyeing 2027",$B$148,$B$146))) -> 0.55 | P31: =IF($E31=0,"",($F31/MAX($F$6:$F$138))^0.38*100*$N31*$O31) -> 6.8738732 | Q31: =IF($E31=0,"","P"&MIN(4,ROUNDUP(RANK($P31,$P$6:$P$138)/COUNT($P$6:$P$138)*4,0))) -> P4 | R31: =IF($D31="On Nov 2026 ballot","Wave 1 - position before the vote",IF($D31="Deferred, eyeing 2027","Wave 3 - 2027 referendum cycle",IF($D31="Levying since 2020-23","Wave 2 - next phase / displace incumbent","Wave 1 - VERIFY referendum status first"))) -> Wave 3 - 2027 referendum cycle | S31: =IF($L31="Retrofit + state stack","SCAP application support + no-cost condition assessment",IF($L31="Retrofit / ESPC","No-cost facility condition assessment",IF($L31="New build / PPEA","PPEA concept + capital sequencing review",IF($L31="Blended programme","Capital programme structuring review","Targeted HVAC and roof scope review")))) -> SCAP application support + no-cost condition assessment
A32: ='Opportunity Model'!A32 -> Dinwiddie County | B32: ='Opportunity Model'!B32 -> County | C32: 8 Southside | D32: ='Opportunity Model'!D32 -> No public action found | E32: ='Opportunity Model'!E32 -> 1 | F32: ='Opportunity Model'!G32 -> 1.2484112e+08 | G32: ='Opportunity Model'!F32 -> 3951951.4 | H32: ='Region Needs Profile'!B13 -> -0.074 | I32: ='Region Needs Profile'!C13 -> 58 | J32: ='Region Needs Profile'!P13 -> -87.624467 | K32: =IF($F32>=PERCENTILE($F$6:$F$138,0.75),"High",IF($F32>=PERCENTILE($F$6:$F$138,0.4),"Moderate","Low")) -> Moderate | L32: =IF($J32>=40,"New build / PPEA",IF($J32<=-40,IF($K32="Low","Retrofit + state stack","Retrofit / ESPC"),IF($K32="High","Blended programme","Selective retrofit"))) -> Retrofit / ESPC | M32: =IF($L32="New build / PPEA","Levy-backed debt + PPEA availability payment + SCAP 10%",IF($L32="Retrofit + state stack","SCAP 20-30% + Literary Fund + levy + guaranteed savings",IF($L32="Retrofit / ESPC","Levy + guaranteed savings + VPSA pooled bond",IF($L32="Blended programme","Levy-backed debt + ESPC on the retained estate","SCAP + Literary Fund + guaranteed savings")))) -> Levy + guaranteed savings + VPSA pooled bond | N32: =IF(OR($L32="Retrofit / ESPC",$L32="Retrofit + state stack"),$B$142,IF($L32="New build / PPEA",$B$144,$B$143)) -> 1 | O32: =IF($D32="On Nov 2026 ballot",$B$145,IF($D32="Levying since 2020-23",$B$147,IF($D32="Deferred, eyeing 2027",$B$148,$B$146))) -> 0.8 | P32: =IF($E32=0,"",($F32/MAX($F$6:$F$138))^0.38*100*$N32*$O32) -> 16.576966 | Q32: =IF($E32=0,"","P"&MIN(4,ROUNDUP(RANK($P32,$P$6:$P$138)/COUNT($P$6:$P$138)*4,0))) -> P2 | R32: =IF($D32="On Nov 2026 ballot","Wave 1 - position before the vote",IF($D32="Deferred, eyeing 2027","Wave 3 - 2027 referendum cycle",IF($D32="Levying since 2020-23","Wave 2 - next phase / displace incumbent","Wave 1 - VERIFY referendum status first"))) -> Wave 1 - VERIFY referendum status first | S32: =IF($L32="Retrofit + state stack","SCAP application support + no-cost condition assessment",IF($L32="Retrofit / ESPC","No-cost facility condition assessment",IF($L32="New build / PPEA","PPEA concept + capital sequencing review",IF($L32="Blended programme","Capital programme structuring review","Targeted HVAC and roof scope review")))) -> No-cost facility condition assessment
A33: ='Opportunity Model'!A33 -> Essex County | B33: ='Opportunity Model'!B33 -> County | C33: 3 Northern Neck | D33: ='Opportunity Model'!D33 -> On Nov 2026 ballot | E33: ='Opportunity Model'!E33 -> 1 | F33: ='Opportunity Model'!G33 -> 90678494 | G33: ='Opportunity Model'!F33 -> 3150819.8 | H33: ='Region Needs Profile'!B8 -> 0.1108 | I33: ='Region Needs Profile'!C8 -> 32 | J33: ='Region Needs Profile'!P8 -> 86.269916 | K33: =IF($F33>=PERCENTILE($F$6:$F$138,0.75),"High",IF($F33>=PERCENTILE($F$6:$F$138,0.4),"Moderate","Low")) -> Low | L33: =IF($J33>=40,"New build / PPEA",IF($J33<=-40,IF($K33="Low","Retrofit + state stack","Retrofit / ESPC"),IF($K33="High","Blended programme","Selective retrofit"))) -> New build / PPEA | M33: =IF($L33="New build / PPEA","Levy-backed debt + PPEA availability payment + SCAP 10%",IF($L33="Retrofit + state stack","SCAP 20-30% + Literary Fund + levy + guaranteed savings",IF($L33="Retrofit / ESPC","Levy + guaranteed savings + VPSA pooled bond",IF($L33="Blended programme","Levy-backed debt + ESPC on the retained estate","SCAP + Literary Fund + guaranteed savings")))) -> Levy-backed debt + PPEA availability payment + SCAP 10% | N33: =IF(OR($L33="Retrofit / ESPC",$L33="Retrofit + state stack"),$B$142,IF($L33="New build / PPEA",$B$144,$B$143)) -> 0.45 | O33: =IF($D33="On Nov 2026 ballot",$B$145,IF($D33="Levying since 2020-23",$B$147,IF($D33="Deferred, eyeing 2027",$B$148,$B$146))) -> 1 | P33: =IF($E33=0,"",($F33/MAX($F$6:$F$138))^0.38*100*$N33*$O33) -> 8.2577796 | Q33: =IF($E33=0,"","P"&MIN(4,ROUNDUP(RANK($P33,$P$6:$P$138)/COUNT($P$6:$P$138)*4,0))) -> P4 | R33: =IF($D33="On Nov 2026 ballot","Wave 1 - position before the vote",IF($D33="Deferred, eyeing 2027","Wave 3 - 2027 referendum cycle",IF($D33="Levying since 2020-23","Wave 2 - next phase / displace incumbent","Wave 1 - VERIFY referendum status first"))) -> Wave 1 - position before the vote | S33: =IF($L33="Retrofit + state stack","SCAP application support + no-cost condition assessment",IF($L33="Retrofit / ESPC","No-cost facility condition assessment",IF($L33="New build / PPEA","PPEA concept + capital sequencing review",IF($L33="Blended programme","Capital programme structuring review","Targeted HVAC and roof scope review")))) -> PPEA concept + capital sequencing review
A34: ='Opportunity Model'!A34 -> Fairfax County | B34: ='Opportunity Model'!B34 -> County | C34: 4 Northern Virginia | D34: ='Opportunity Model'!D34 -> No public action found | E34: ='Opportunity Model'!E34 -> 1 | F34: ='Opportunity Model'!G34 -> 7.8571568e+09 | G34: ='Opportunity Model'!F34 -> 2.7527494e+08 | H34: ='Region Needs Profile'!B9 -> 0.0794 | I34: ='Region Needs Profile'!C9 -> 48 | J34: ='Region Needs Profile'!P9 -> 54.342196 | K34: =IF($F34>=PERCENTILE($F$6:$F$138,0.75),"High",IF($F34>=PERCENTILE($F$6:$F$138,0.4),"Moderate","Low")) -> High | L34: =IF($J34>=40,"New build / PPEA",IF($J34<=-40,IF($K34="Low","Retrofit + state stack","Retrofit / ESPC"),IF($K34="High","Blended programme","Selective retrofit"))) -> New build / PPEA | M34: =IF($L34="New build / PPEA","Levy-backed debt + PPEA availability payment + SCAP 10%",IF($L34="Retrofit + state stack","SCAP 20-30% + Literary Fund + levy + guaranteed savings",IF($L34="Retrofit / ESPC","Levy + guaranteed savings + VPSA pooled bond",IF($L34="Blended programme","Levy-backed debt + ESPC on the retained estate","SCAP + Literary Fund + guaranteed savings")))) -> Levy-backed debt + PPEA availability payment + SCAP 10% | N34: =IF(OR($L34="Retrofit / ESPC",$L34="Retrofit + state stack"),$B$142,IF($L34="New build / PPEA",$B$144,$B$143)) -> 0.45 | O34: =IF($D34="On Nov 2026 ballot",$B$145,IF($D34="Levying since 2020-23",$B$147,IF($D34="Deferred, eyeing 2027",$B$148,$B$146))) -> 0.8 | P34: =IF($E34=0,"",($F34/MAX($F$6:$F$138))^0.38*100*$N34*$O34) -> 36 | Q34: =IF($E34=0,"","P"&MIN(4,ROUNDUP(RANK($P34,$P$6:$P$138)/COUNT($P$6:$P$138)*4,0))) -> P1 | R34: =IF($D34="On Nov 2026 ballot","Wave 1 - position before the vote",IF($D34="Deferred, eyeing 2027","Wave 3 - 2027 referendum cycle",IF($D34="Levying since 2020-23","Wave 2 - next phase / displace incumbent","Wave 1 - VERIFY referendum status first"))) -> Wave 1 - VERIFY referendum status first | S34: =IF($L34="Retrofit + state stack","SCAP application support + no-cost condition assessment",IF($L34="Retrofit / ESPC","No-cost facility condition assessment",IF($L34="New build / PPEA","PPEA concept + capital sequencing review",IF($L34="Blended programme","Capital programme structuring review","Targeted HVAC and roof scope review")))) -> PPEA concept + capital sequencing review
A35: ='Opportunity Model'!A35 -> Fauquier County | B35: ='Opportunity Model'!B35 -> County | C35: 4 Northern Virginia | D35: ='Opportunity Model'!D35 -> No public action found | E35: ='Opportunity Model'!E35 -> 1 | F35: ='Opportunity Model'!G35 -> 6.1971295e+08 | G35: ='Opportunity Model'!F35 -> 19235007 | H35: ='Region Needs Profile'!B9 -> 0.0794 | I35: ='Region Needs Profile'!C9 -> 48 | J35: ='Region Needs Profile'!P9 -> 54.342196 | K35: =IF($F35>=PERCENTILE($F$6:$F$138,0.75),"High",IF($F35>=PERCENTILE($F$6:$F$138,0.4),"Moderate","Low")) -> High | L35: =IF($J35>=40,"New build / PPEA",IF($J35<=-40,IF($K35="Low","Retrofit + state stack","Retrofit / ESPC"),IF($K35="High","Blended programme","Selective retrofit"))) -> New build / PPEA | M35: =IF($L35="New build / PPEA","Levy-backed debt + PPEA availability payment + SCAP 10%",IF($L35="Retrofit + state stack","SCAP 20-30% + Literary Fund + levy + guaranteed savings",IF($L35="Retrofit / ESPC","Levy + guaranteed savings + VPSA pooled bond",IF($L35="Blended programme","Levy-backed debt + ESPC on the retained estate","SCAP + Literary Fund + guaranteed savings")))) -> Levy-backed debt + PPEA availability payment + SCAP 10% | N35: =IF(OR($L35="Retrofit / ESPC",$L35="Retrofit + state stack"),$B$142,IF($L35="New build / PPEA",$B$144,$B$143)) -> 0.45 | O35: =IF($D35="On Nov 2026 ballot",$B$145,IF($D35="Levying since 2020-23",$B$147,IF($D35="Deferred, eyeing 2027",$B$148,$B$146))) -> 0.8 | P35: =IF($E35=0,"",($F35/MAX($F$6:$F$138))^0.38*100*$N35*$O35) -> 13.71305 | Q35: =IF($E35=0,"","P"&MIN(4,ROUNDUP(RANK($P35,$P$6:$P$138)/COUNT($P$6:$P$138)*4,0))) -> P2 | R35: =IF($D35="On Nov 2026 ballot","Wave 1 - position before the vote",IF($D35="Deferred, eyeing 2027","Wave 3 - 2027 referendum cycle",IF($D35="Levying since 2020-23","Wave 2 - next phase / displace incumbent","Wave 1 - VERIFY referendum status first"))) -> Wave 1 - VERIFY referendum status first | S35: =IF($L35="Retrofit + state stack","SCAP application support + no-cost condition assessment",IF($L35="Retrofit / ESPC","No-cost facility condition assessment",IF($L35="New build / PPEA","PPEA concept + capital sequencing review",IF($L35="Blended programme","Capital programme structuring review","Targeted HVAC and roof scope review")))) -> PPEA concept + capital sequencing review
A36: ='Opportunity Model'!A36 -> Floyd County | B36: ='Opportunity Model'!B36 -> County | C36: 7 Southwest | D36: ='Opportunity Model'!D36 -> No public action found | E36: ='Opportunity Model'!E36 -> 1 | F36: ='Opportunity Model'!G36 -> 60988680 | G36: ='Opportunity Model'!F36 -> 2023165.7 | H36: ='Region Needs Profile'!B12 -> -0.1001 | I36: ='Region Needs Profile'!C12 -> 58 | J36: ='Region Needs Profile'!P12 -> -93.064667 | K36: =IF($F36>=PERCENTILE($F$6:$F$138,0.75),"High",IF($F36>=PERCENTILE($F$6:$F$138,0.4),"Moderate","Low")) -> Low | L36: =IF($J36>=40,"New build / PPEA",IF($J36<=-40,IF($K36="Low","Retrofit + state stack","Retrofit / ESPC"),IF($K36="High","Blended programme","Selective retrofit"))) -> Retrofit + state stack | M36: =IF($L36="New build / PPEA","Levy-backed debt + PPEA availability payment + SCAP 10%",IF($L36="Retrofit + state stack","SCAP 20-30% + Literary Fund + levy + guaranteed savings",IF($L36="Retrofit / ESPC","Levy + guaranteed savings + VPSA pooled bond",IF($L36="Blended programme","Levy-backed debt + ESPC on the retained estate","SCAP + Literary Fund + guaranteed savings")))) -> SCAP 20-30% + Literary Fund + levy + guaranteed savings | N36: =IF(OR($L36="Retrofit / ESPC",$L36="Retrofit + state stack"),$B$142,IF($L36="New build / PPEA",$B$144,$B$143)) -> 1 | O36: =IF($D36="On Nov 2026 ballot",$B$145,IF($D36="Levying since 2020-23",$B$147,IF($D36="Deferred, eyeing 2027",$B$148,$B$146))) -> 0.8 | P36: =IF($E36=0,"",($F36/MAX($F$6:$F$138))^0.38*100*$N36*$O36) -> 12.626525 | Q36: =IF($E36=0,"","P"&MIN(4,ROUNDUP(RANK($P36,$P$6:$P$138)/COUNT($P$6:$P$138)*4,0))) -> P3 | R36: =IF($D36="On Nov 2026 ballot","Wave 1 - position before the vote",IF($D36="Deferred, eyeing 2027","Wave 3 - 2027 referendum cycle",IF($D36="Levying since 2020-23","Wave 2 - next phase / displace incumbent","Wave 1 - VERIFY referendum status first"))) -> Wave 1 - VERIFY referendum status first | S36: =IF($L36="Retrofit + state stack","SCAP application support + no-cost condition assessment",IF($L36="Retrofit / ESPC","No-cost facility condition assessment",IF($L36="New build / PPEA","PPEA concept + capital sequencing review",IF($L36="Blended programme","Capital programme structuring review","Targeted HVAC and roof scope review")))) -> SCAP application support + no-cost condition assessment
A37: ='Opportunity Model'!A37 -> Fluvanna County | B37: ='Opportunity Model'!B37 -> County | C37: 5 Valley | D37: ='Opportunity Model'!D37 -> No public action found | E37: ='Opportunity Model'!E37 -> 1 | F37: ='Opportunity Model'!G37 -> 93288804 | G37: ='Opportunity Model'!F37 -> 3177069.3 | H37: ='Region Needs Profile'!B10 -> 0.0301 | I37: ='Region Needs Profile'!C10 -> 55 | J37: ='Region Needs Profile'!P10 -> 10.405306 | K37: =IF($F37>=PERCENTILE($F$6:$F$138,0.75),"High",IF($F37>=PERCENTILE($F$6:$F$138,0.4),"Moderate","Low")) -> Low | L37: =IF($J37>=40,"New build / PPEA",IF($J37<=-40,IF($K37="Low","Retrofit + state stack","Retrofit / ESPC"),IF($K37="High","Blended programme","Selective retrofit"))) -> Selective retrofit | M37: =IF($L37="New build / PPEA","Levy-backed debt + PPEA availability payment + SCAP 10%",IF($L37="Retrofit + state stack","SCAP 20-30% + Literary Fund + levy + guaranteed savings",IF($L37="Retrofit / ESPC","Levy + guaranteed savings + VPSA pooled bond",IF($L37="Blended programme","Levy-backed debt + ESPC on the retained estate","SCAP + Literary Fund + guaranteed savings")))) -> SCAP + Literary Fund + guaranteed savings | N37: =IF(OR($L37="Retrofit / ESPC",$L37="Retrofit + state stack"),$B$142,IF($L37="New build / PPEA",$B$144,$B$143)) -> 0.7 | O37: =IF($D37="On Nov 2026 ballot",$B$145,IF($D37="Levying since 2020-23",$B$147,IF($D37="Deferred, eyeing 2027",$B$148,$B$146))) -> 0.8 | P37: =IF($E37=0,"",($F37/MAX($F$6:$F$138))^0.38*100*$N37*$O37) -> 10.387771 | Q37: =IF($E37=0,"","P"&MIN(4,ROUNDUP(RANK($P37,$P$6:$P$138)/COUNT($P$6:$P$138)*4,0))) -> P3 | R37: =IF($D37="On Nov 2026 ballot","Wave 1 - position before the vote",IF($D37="Deferred, eyeing 2027","Wave 3 - 2027 referendum cycle",IF($D37="Levying since 2020-23","Wave 2 - next phase / displace incumbent","Wave 1 - VERIFY referendum status first"))) -> Wave 1 - VERIFY referendum status first | S37: =IF($L37="Retrofit + state stack","SCAP application support + no-cost condition assessment",IF($L37="Retrofit / ESPC","No-cost facility condition assessment",IF($L37="New build / PPEA","PPEA concept + capital sequencing review",IF($L37="Blended programme","Capital programme structuring review","Targeted HVAC and roof scope review")))) -> Targeted HVAC and roof scope review
A38: ='Opportunity Model'!A38 -> Franklin County | B38: ='Opportunity Model'!B38 -> County | C38: 6 Western Virginia | D38: ='Opportunity Model'!D38 -> On Nov 2026 ballot | E38: ='Opportunity Model'!E38 -> 1 | F38: ='Opportunity Model'!G38 -> 2.5695274e+08 | G38: ='Opportunity Model'!F38 -> 9154045.1 | H38: ='Region Needs Profile'!B11 -> -0.0678 | I38: ='Region Needs Profile'!C11 -> 58 | J38: ='Region Needs Profile'!P11 -> -65.331358 | K38: =IF($F38>=PERCENTILE($F$6:$F$138,0.75),"High",IF($F38>=PERCENTILE($F$6:$F$138,0.4),"Moderate","Low")) -> Moderate | L38: =IF($J38>=40,"New build / PPEA",IF($J38<=-40,IF($K38="Low","Retrofit + state stack","Retrofit / ESPC"),IF($K38="High","Blended programme","Selective retrofit"))) -> Retrofit / ESPC | M38: =IF($L38="New build / PPEA","Levy-backed debt + PPEA availability payment + SCAP 10%",IF($L38="Retrofit + state stack","SCAP 20-30% + Literary Fund + levy + guaranteed savings",IF($L38="Retrofit / ESPC","Levy + guaranteed savings + VPSA pooled bond",IF($L38="Blended programme","Levy-backed debt + ESPC on the retained estate","SCAP + Literary Fund + guaranteed savings")))) -> Levy + guaranteed savings + VPSA pooled bond | N38: =IF(OR($L38="Retrofit / ESPC",$L38="Retrofit + state stack"),$B$142,IF($L38="New build / PPEA",$B$144,$B$143)) -> 1 | O38: =IF($D38="On Nov 2026 ballot",$B$145,IF($D38="Levying since 2020-23",$B$147,IF($D38="Deferred, eyeing 2027",$B$148,$B$146))) -> 1 | P38: =IF($E38=0,"",($F38/MAX($F$6:$F$138))^0.38*100*$N38*$O38) -> 27.2611 | Q38: =IF($E38=0,"","P"&MIN(4,ROUNDUP(RANK($P38,$P$6:$P$138)/COUNT($P$6:$P$138)*4,0))) -> P1 | R38: =IF($D38="On Nov 2026 ballot","Wave 1 - position before the vote",IF($D38="Deferred, eyeing 2027","Wave 3 - 2027 referendum cycle",IF($D38="Levying since 2020-23","Wave 2 - next phase / displace incumbent","Wave 1 - VERIFY referendum status first"))) -> Wave 1 - position before the vote | S38: =IF($L38="Retrofit + state stack","SCAP application support + no-cost condition assessment",IF($L38="Retrofit / ESPC","No-cost facility condition assessment",IF($L38="New build / PPEA","PPEA concept + capital sequencing review",IF($L38="Blended programme","Capital programme structuring review","Targeted HVAC and roof scope review")))) -> No-cost facility condition assessment
A39: ='Opportunity Model'!A39 -> Frederick County | B39: ='Opportunity Model'!B39 -> County | C39: 4 Northern Virginia | D39: ='Opportunity Model'!D39 -> No public action found | E39: ='Opportunity Model'!E39 -> 1 | F39: ='Opportunity Model'!G39 -> 8.345602e+08 | G39: ='Opportunity Model'!F39 -> 25833960 | H39: ='Region Needs Profile'!B9 -> 0.0794 | I39: ='Region Needs Profile'!C9 -> 48 | J39: ='Region Needs Profile'!P9 -> 54.342196 | K39: =IF($F39>=PERCENTILE($F$6:$F$138,0.75),"High",IF($F39>=PERCENTILE($F$6:$F$138,0.4),"Moderate","Low")) -> High | L39: =IF($J39>=40,"New build / PPEA",IF($J39<=-40,IF($K39="Low","Retrofit + state stack","Retrofit / ESPC"),IF($K39="High","Blended programme","Selective retrofit"))) -> New build / PPEA | M39: =IF($L39="New build / PPEA","Levy-backed debt + PPEA availability payment + SCAP 10%",IF($L39="Retrofit + state stack","SCAP 20-30% + Literary Fund + levy + guaranteed savings",IF($L39="Retrofit / ESPC","Levy + guaranteed savings + VPSA pooled bond",IF($L39="Blended programme","Levy-backed debt + ESPC on the retained estate","SCAP + Literary Fund + guaranteed savings")))) -> Levy-backed debt + PPEA availability payment + SCAP 10% | N39: =IF(OR($L39="Retrofit / ESPC",$L39="Retrofit + state stack"),$B$142,IF($L39="New build / PPEA",$B$144,$B$143)) -> 0.45 | O39: =IF($D39="On Nov 2026 ballot",$B$145,IF($D39="Levying since 2020-23",$B$147,IF($D39="Deferred, eyeing 2027",$B$148,$B$146))) -> 0.8 | P39: =IF($E39=0,"",($F39/MAX($F$6:$F$138))^0.38*100*$N39*$O39) -> 15.355203 | Q39: =IF($E39=0,"","P"&MIN(4,ROUNDUP(RANK($P39,$P$6:$P$138)/COUNT($P$6:$P$138)*4,0))) -> P2 | R39: =IF($D39="On Nov 2026 ballot","Wave 1 - position before the vote",IF($D39="Deferred, eyeing 2027","Wave 3 - 2027 referendum cycle",IF($D39="Levying since 2020-23","Wave 2 - next phase / displace incumbent","Wave 1 - VERIFY referendum status first"))) -> Wave 1 - VERIFY referendum status first | S39: =IF($L39="Retrofit + state stack","SCAP application support + no-cost condition assessment",IF($L39="Retrofit / ESPC","No-cost facility condition assessment",IF($L39="New build / PPEA","PPEA concept + capital sequencing review",IF($L39="Blended programme","Capital programme structuring review","Targeted HVAC and roof scope review")))) -> PPEA concept + capital sequencing review
A40: ='Opportunity Model'!A40 -> Giles County | B40: ='Opportunity Model'!B40 -> County | C40: 7 Southwest | D40: ='Opportunity Model'!D40 -> No public action found | E40: ='Opportunity Model'!E40 -> 1 | F40: ='Opportunity Model'!G40 -> 84035613 | G40: ='Opportunity Model'!F40 -> 3024840.2 | H40: ='Region Needs Profile'!B12 -> -0.1001 | I40: ='Region Needs Profile'!C12 -> 58 | J40: ='Region Needs Profile'!P12 -> -93.064667 | K40: =IF($F40>=PERCENTILE($F$6:$F$138,0.75),"High",IF($F40>=PERCENTILE($F$6:$F$138,0.4),"Moderate","Low")) -> Low | L40: =IF($J40>=40,"New build / PPEA",IF($J40<=-40,IF($K40="Low","Retrofit + state stack","Retrofit / ESPC"),IF($K40="High","Blended programme","Selective retrofit"))) -> Retrofit + state stack | M40: =IF($L40="New build / PPEA","Levy-backed debt + PPEA availability payment + SCAP 10%",IF($L40="Retrofit + state stack","SCAP 20-30% + Literary Fund + levy + guaranteed savings",IF($L40="Retrofit / ESPC","Levy + guaranteed savings + VPSA pooled bond",IF($L40="Blended programme","Levy-backed debt + ESPC on the retained estate","SCAP + Literary Fund + guaranteed savings")))) -> SCAP 20-30% + Literary Fund + levy + guaranteed savings | N40: =IF(OR($L40="Retrofit / ESPC",$L40="Retrofit + state stack"),$B$142,IF($L40="New build / PPEA",$B$144,$B$143)) -> 1 | O40: =IF($D40="On Nov 2026 ballot",$B$145,IF($D40="Levying since 2020-23",$B$147,IF($D40="Deferred, eyeing 2027",$B$148,$B$146))) -> 0.8 | P40: =IF($E40=0,"",($F40/MAX($F$6:$F$138))^0.38*100*$N40*$O40) -> 14.262157 | Q40: =IF($E40=0,"","P"&MIN(4,ROUNDUP(RANK($P40,$P$6:$P$138)/COUNT($P$6:$P$138)*4,0))) -> P2 | R40: =IF($D40="On Nov 2026 ballot","Wave 1 - position before the vote",IF($D40="Deferred, eyeing 2027","Wave 3 - 2027 referendum cycle",IF($D40="Levying since 2020-23","Wave 2 - next phase / displace incumbent","Wave 1 - VERIFY referendum status first"))) -> Wave 1 - VERIFY referendum status first | S40: =IF($L40="Retrofit + state stack","SCAP application support + no-cost condition assessment",IF($L40="Retrofit / ESPC","No-cost facility condition assessment",IF($L40="New build / PPEA","PPEA concept + capital sequencing review",IF($L40="Blended programme","Capital programme structuring review","Targeted HVAC and roof scope review")))) -> SCAP application support + no-cost condition assessment
A41: ='Opportunity Model'!A41 -> Gloucester County | B41: ='Opportunity Model'!B41 -> County | C41: 3 Northern Neck | D41: ='Opportunity Model'!D41 -> Levying since 2020-23 | E41: ='Opportunity Model'!E41 -> 1 | F41: ='Opportunity Model'!G41 -> 2.5501879e+08 | G41: ='Opportunity Model'!F41 -> 8293160.4 | H41: ='Region Needs Profile'!B8 -> 0.1108 | I41: ='Region Needs Profile'!C8 -> 32 | J41: ='Region Needs Profile'!P8 -> 86.269916 | K41: =IF($F41>=PERCENTILE($F$6:$F$138,0.75),"High",IF($F41>=PERCENTILE($F$6:$F$138,0.4),"Moderate","Low")) -> Moderate | L41: =IF($J41>=40,"New build / PPEA",IF($J41<=-40,IF($K41="Low","Retrofit + state stack","Retrofit / ESPC"),IF($K41="High","Blended programme","Selective retrofit"))) -> New build / PPEA | M41: =IF($L41="New build / PPEA","Levy-backed debt + PPEA availability payment + SCAP 10%",IF($L41="Retrofit + state stack","SCAP 20-30% + Literary Fund + levy + guaranteed savings",IF($L41="Retrofit / ESPC","Levy + guaranteed savings + VPSA pooled bond",IF($L41="Blended programme","Levy-backed debt + ESPC on the retained estate","SCAP + Literary Fund + guaranteed savings")))) -> Levy-backed debt + PPEA availability payment + SCAP 10% | N41: =IF(OR($L41="Retrofit / ESPC",$L41="Retrofit + state stack"),$B$142,IF($L41="New build / PPEA",$B$144,$B$143)) -> 0.45 | O41: =IF($D41="On Nov 2026 ballot",$B$145,IF($D41="Levying since 2020-23",$B$147,IF($D41="Deferred, eyeing 2027",$B$148,$B$146))) -> 0.65 | P41: =IF($E41=0,"",($F41/MAX($F$6:$F$138))^0.38*100*$N41*$O41) -> 7.9510125 | Q41: =IF($E41=0,"","P"&MIN(4,ROUNDUP(RANK($P41,$P$6:$P$138)/COUNT($P$6:$P$138)*4,0))) -> P4 | R41: =IF($D41="On Nov 2026 ballot","Wave 1 - position before the vote",IF($D41="Deferred, eyeing 2027","Wave 3 - 2027 referendum cycle",IF($D41="Levying since 2020-23","Wave 2 - next phase / displace incumbent","Wave 1 - VERIFY referendum status first"))) -> Wave 2 - next phase / displace incumbent | S41: =IF($L41="Retrofit + state stack","SCAP application support + no-cost condition assessment",IF($L41="Retrofit / ESPC","No-cost facility condition assessment",IF($L41="New build / PPEA","PPEA concept + capital sequencing review",IF($L41="Blended programme","Capital programme structuring review","Targeted HVAC and roof scope review")))) -> PPEA concept + capital sequencing review
A42: ='Opportunity Model'!A42 -> Goochland County | B42: ='Opportunity Model'!B42 -> County | C42: 1 Central Virginia | D42: ='Opportunity Model'!D42 -> No public action found | E42: ='Opportunity Model'!E42 -> 1 | F42: ='Opportunity Model'!G42 -> 2.2509562e+08 | G42: ='Opportunity Model'!F42 -> 6655066.8 | H42: ='Region Needs Profile'!B6 -> 0.0584 | I42: ='Region Needs Profile'!C6 -> 50 | J42: ='Region Needs Profile'!P6 -> 20.904228 | K42: =IF($F42>=PERCENTILE($F$6:$F$138,0.75),"High",IF($F42>=PERCENTILE($F$6:$F$138,0.4),"Moderate","Low")) -> Moderate | L42: =IF($J42>=40,"New build / PPEA",IF($J42<=-40,IF($K42="Low","Retrofit + state stack","Retrofit / ESPC"),IF($K42="High","Blended programme","Selective retrofit"))) -> Selective retrofit | M42: =IF($L42="New build / PPEA","Levy-backed debt + PPEA availability payment + SCAP 10%",IF($L42="Retrofit + state stack","SCAP 20-30% + Literary Fund + levy + guaranteed savings",IF($L42="Retrofit / ESPC","Levy + guaranteed savings + VPSA pooled bond",IF($L42="Blended programme","Levy-backed debt + ESPC on the retained estate","SCAP + Literary Fund + guaranteed savings")))) -> SCAP + Literary Fund + guaranteed savings | N42: =IF(OR($L42="Retrofit / ESPC",$L42="Retrofit + state stack"),$B$142,IF($L42="New build / PPEA",$B$144,$B$143)) -> 0.7 | O42: =IF($D42="On Nov 2026 ballot",$B$145,IF($D42="Levying since 2020-23",$B$147,IF($D42="Deferred, eyeing 2027",$B$148,$B$146))) -> 0.8 | P42: =IF($E42=0,"",($F42/MAX($F$6:$F$138))^0.38*100*$N42*$O42) -> 14.517326 | Q42: =IF($E42=0,"","P"&MIN(4,ROUNDUP(RANK($P42,$P$6:$P$138)/COUNT($P$6:$P$138)*4,0))) -> P2 | R42: =IF($D42="On Nov 2026 ballot","Wave 1 - position before the vote",IF($D42="Deferred, eyeing 2027","Wave 3 - 2027 referendum cycle",IF($D42="Levying since 2020-23","Wave 2 - next phase / displace incumbent","Wave 1 - VERIFY referendum status first"))) -> Wave 1 - VERIFY referendum status first | S42: =IF($L42="Retrofit + state stack","SCAP application support + no-cost condition assessment",IF($L42="Retrofit / ESPC","No-cost facility condition assessment",IF($L42="New build / PPEA","PPEA concept + capital sequencing review",IF($L42="Blended programme","Capital programme structuring review","Targeted HVAC and roof scope review")))) -> Targeted HVAC and roof scope review
A43: ='Opportunity Model'!A43 -> Grayson County | B43: ='Opportunity Model'!B43 -> County | C43: 7 Southwest | D43: ='Opportunity Model'!D43 -> No public action found | E43: ='Opportunity Model'!E43 -> 1 | F43: ='Opportunity Model'!G43 -> 27161124 | G43: ='Opportunity Model'!F43 -> 995125.93 | H43: ='Region Needs Profile'!B12 -> -0.1001 | I43: ='Region Needs Profile'!C12 -> 58 | J43: ='Region Needs Profile'!P12 -> -93.064667 | K43: =IF($F43>=PERCENTILE($F$6:$F$138,0.75),"High",IF($F43>=PERCENTILE($F$6:$F$138,0.4),"Moderate","Low")) -> Low | L43: =IF($J43>=40,"New build / PPEA",IF($J43<=-40,IF($K43="Low","Retrofit + state stack","Retrofit / ESPC"),IF($K43="High","Blended programme","Selective retrofit"))) -> Retrofit + state stack | M43: =IF($L43="New build / PPEA","Levy-backed debt + PPEA availability payment + SCAP 10%",IF($L43="Retrofit + state stack","SCAP 20-30% + Literary Fund + levy + guaranteed savings",IF($L43="Retrofit / ESPC","Levy + guaranteed savings + VPSA pooled bond",IF($L43="Blended programme","Levy-backed debt + ESPC on the retained estate","SCAP + Literary Fund + guaranteed savings")))) -> SCAP 20-30% + Literary Fund + levy + guaranteed savings | N43: =IF(OR($L43="Retrofit / ESPC",$L43="Retrofit + state stack"),$B$142,IF($L43="New build / PPEA",$B$144,$B$143)) -> 1 | O43: =IF($D43="On Nov 2026 ballot",$B$145,IF($D43="Levying since 2020-23",$B$147,IF($D43="Deferred, eyeing 2027",$B$148,$B$146))) -> 0.8 | P43: =IF($E43=0,"",($F43/MAX($F$6:$F$138))^0.38*100*$N43*$O43) -> 9.2851573 | Q43: =IF($E43=0,"","P"&MIN(4,ROUNDUP(RANK($P43,$P$6:$P$138)/COUNT($P$6:$P$138)*4,0))) -> P3 | R43: =IF($D43="On Nov 2026 ballot","Wave 1 - position before the vote",IF($D43="Deferred, eyeing 2027","Wave 3 - 2027 referendum cycle",IF($D43="Levying since 2020-23","Wave 2 - next phase / displace incumbent","Wave 1 - VERIFY referendum status first"))) -> Wave 1 - VERIFY referendum status first | S43: =IF($L43="Retrofit + state stack","SCAP application support + no-cost condition assessment",IF($L43="Retrofit / ESPC","No-cost facility condition assessment",IF($L43="New build / PPEA","PPEA concept + capital sequencing review",IF($L43="Blended programme","Capital programme structuring review","Targeted HVAC and roof scope review")))) -> SCAP application support + no-cost condition assessment
A44: ='Opportunity Model'!A44 -> Greene County | B44: ='Opportunity Model'!B44 -> County | C44: 5 Valley | D44: ='Opportunity Model'!D44 -> No public action found | E44: ='Opportunity Model'!E44 -> 1 | F44: ='Opportunity Model'!G44 -> 1.2368059e+08 | G44: ='Opportunity Model'!F44 -> 3979612.7 | H44: ='Region Needs Profile'!B10 -> 0.0301 | I44: ='Region Needs Profile'!C10 -> 55 | J44: ='Region Needs Profile'!P10 -> 10.405306 | K44: =IF($F44>=PERCENTILE($F$6:$F$138,0.75),"High",IF($F44>=PERCENTILE($F$6:$F$138,0.4),"Moderate","Low")) -> Moderate | L44: =IF($J44>=40,"New build / PPEA",IF($J44<=-40,IF($K44="Low","Retrofit + state stack","Retrofit / ESPC"),IF($K44="High","Blended programme","Selective retrofit"))) -> Selective retrofit | M44: =IF($L44="New build / PPEA","Levy-backed debt + PPEA availability payment + SCAP 10%",IF($L44="Retrofit + state stack","SCAP 20-30% + Literary Fund + levy + guaranteed savings",IF($L44="Retrofit / ESPC","Levy + guaranteed savings + VPSA pooled bond",IF($L44="Blended programme","Levy-backed debt + ESPC on the retained estate","SCAP + Literary Fund + guaranteed savings")))) -> SCAP + Literary Fund + guaranteed savings | N44: =IF(OR($L44="Retrofit / ESPC",$L44="Retrofit + state stack"),$B$142,IF($L44="New build / PPEA",$B$144,$B$143)) -> 0.7 | O44: =IF($D44="On Nov 2026 ballot",$B$145,IF($D44="Levying since 2020-23",$B$147,IF($D44="Deferred, eyeing 2027",$B$148,$B$146))) -> 0.8 | P44: =IF($E44=0,"",($F44/MAX($F$6:$F$138))^0.38*100*$N44*$O44) -> 11.562767 | Q44: =IF($E44=0,"","P"&MIN(4,ROUNDUP(RANK($P44,$P$6:$P$138)/COUNT($P$6:$P$138)*4,0))) -> P3 | R44: =IF($D44="On Nov 2026 ballot","Wave 1 - position before the vote",IF($D44="Deferred, eyeing 2027","Wave 3 - 2027 referendum cycle",IF($D44="Levying since 2020-23","Wave 2 - next phase / displace incumbent","Wave 1 - VERIFY referendum status first"))) -> Wave 1 - VERIFY referendum status first | S44: =IF($L44="Retrofit + state stack","SCAP application support + no-cost condition assessment",IF($L44="Retrofit / ESPC","No-cost facility condition assessment",IF($L44="New build / PPEA","PPEA concept + capital sequencing review",IF($L44="Blended programme","Capital programme structuring review","Targeted HVAC and roof scope review")))) -> Targeted HVAC and roof scope review
A45: ='Opportunity Model'!A45 -> Greensville County | B45: ='Opportunity Model'!B45 -> County | C45: 8 Southside | D45: ='Opportunity Model'!D45 -> No public action found | E45: ='Opportunity Model'!E45 -> 1 | F45: ='Opportunity Model'!G45 -> 29522935 | G45: ='Opportunity Model'!F45 -> 1262084.9 | H45: ='Region Needs Profile'!B13 -> -0.074 | I45: ='Region Needs Profile'!C13 -> 58 | J45: ='Region Needs Profile'!P13 -> -87.624467 | K45: =IF($F45>=PERCENTILE($F$6:$F$138,0.75),"High",IF($F45>=PERCENTILE($F$6:$F$138,0.4),"Moderate","Low")) -> Low | L45: =IF($J45>=40,"New build / PPEA",IF($J45<=-40,IF($K45="Low","Retrofit + state stack","Retrofit / ESPC"),IF($K45="High","Blended programme","Selective retrofit"))) -> Retrofit + state stack | M45: =IF($L45="New build / PPEA","Levy-backed debt + PPEA availability payment + SCAP 10%",IF($L45="Retrofit + state stack","SCAP 20-30% + Literary Fund + levy + guaranteed savings",IF($L45="Retrofit / ESPC","Levy + guaranteed savings + VPSA pooled bond",IF($L45="Blended programme","Levy-backed debt + ESPC on the retained estate","SCAP + Literary Fund + guaranteed savings")))) -> SCAP 20-30% + Literary Fund + levy + guaranteed savings | N45: =IF(OR($L45="Retrofit / ESPC",$L45="Retrofit + state stack"),$B$142,IF($L45="New build / PPEA",$B$144,$B$143)) -> 1 | O45: =IF($D45="On Nov 2026 ballot",$B$145,IF($D45="Levying since 2020-23",$B$147,IF($D45="Deferred, eyeing 2027",$B$148,$B$146))) -> 0.8 | P45: =IF($E45=0,"",($F45/MAX($F$6:$F$138))^0.38*100*$N45*$O45) -> 9.5840649 | Q45: =IF($E45=0,"","P"&MIN(4,ROUNDUP(RANK($P45,$P$6:$P$138)/COUNT($P$6:$P$138)*4,0))) -> P3 | R45: =IF($D45="On Nov 2026 ballot","Wave 1 - position before the vote",IF($D45="Deferred, eyeing 2027","Wave 3 - 2027 referendum cycle",IF($D45="Levying since 2020-23","Wave 2 - next phase / displace incumbent","Wave 1 - VERIFY referendum status first"))) -> Wave 1 - VERIFY referendum status first | S45: =IF($L45="Retrofit + state stack","SCAP application support + no-cost condition assessment",IF($L45="Retrofit / ESPC","No-cost facility condition assessment",IF($L45="New build / PPEA","PPEA concept + capital sequencing review",IF($L45="Blended programme","Capital programme structuring review","Targeted HVAC and roof scope review")))) -> SCAP application support + no-cost condition assessment
A46: ='Opportunity Model'!A46 -> Halifax County | B46: ='Opportunity Model'!B46 -> County | C46: 8 Southside | D46: ='Opportunity Model'!D46 -> Levying since 2020-23 | E46: ='Opportunity Model'!E46 -> 1 | F46: ='Opportunity Model'!G46 -> 1.8490452e+08 | G46: ='Opportunity Model'!F46 -> 6367472.4 | H46: ='Region Needs Profile'!B13 -> -0.074 | I46: ='Region Needs Profile'!C13 -> 58 | J46: ='Region Needs Profile'!P13 -> -87.624467 | K46: =IF($F46>=PERCENTILE($F$6:$F$138,0.75),"High",IF($F46>=PERCENTILE($F$6:$F$138,0.4),"Moderate","Low")) -> Moderate | L46: =IF($J46>=40,"New build / PPEA",IF($J46<=-40,IF($K46="Low","Retrofit + state stack","Retrofit / ESPC"),IF($K46="High","Blended programme","Selective retrofit"))) -> Retrofit / ESPC | M46: =IF($L46="New build / PPEA","Levy-backed debt + PPEA availability payment + SCAP 10%",IF($L46="Retrofit + state stack","SCAP 20-30% + Literary Fund + levy + guaranteed savings",IF($L46="Retrofit / ESPC","Levy + guaranteed savings + VPSA pooled bond",IF($L46="Blended programme","Levy-backed debt + ESPC on the retained estate","SCAP + Literary Fund + guaranteed savings")))) -> Levy + guaranteed savings + VPSA pooled bond | N46: =IF(OR($L46="Retrofit / ESPC",$L46="Retrofit + state stack"),$B$142,IF($L46="New build / PPEA",$B$144,$B$143)) -> 1 | O46: =IF($D46="On Nov 2026 ballot",$B$145,IF($D46="Levying since 2020-23",$B$147,IF($D46="Deferred, eyeing 2027",$B$148,$B$146))) -> 0.65 | P46: =IF($E46=0,"",($F46/MAX($F$6:$F$138))^0.38*100*$N46*$O46) -> 15.636968 | Q46: =IF($E46=0,"","P"&MIN(4,ROUNDUP(RANK($P46,$P$6:$P$138)/COUNT($P$6:$P$138)*4,0))) -> P2 | R46: =IF($D46="On Nov 2026 ballot","Wave 1 - position before the vote",IF($D46="Deferred, eyeing 2027","Wave 3 - 2027 referendum cycle",IF($D46="Levying since 2020-23","Wave 2 - next phase / displace incumbent","Wave 1 - VERIFY referendum status first"))) -> Wave 2 - next phase / displace incumbent | S46: =IF($L46="Retrofit + state stack","SCAP application support + no-cost condition assessment",IF($L46="Retrofit / ESPC","No-cost facility condition assessment",IF($L46="New build / PPEA","PPEA concept + capital sequencing review",IF($L46="Blended programme","Capital programme structuring review","Targeted HVAC and roof scope review")))) -> No-cost facility condition assessment
A47: ='Opportunity Model'!A47 -> Hanover County | B47: ='Opportunity Model'!B47 -> County | C47: 1 Central Virginia | D47: ='Opportunity Model'!D47 -> No public action found | E47: ='Opportunity Model'!E47 -> 1 | F47: ='Opportunity Model'!G47 -> 1.2604641e+09 | G47: ='Opportunity Model'!F47 -> 40147138 | H47: ='Region Needs Profile'!B6 -> 0.0584 | I47: ='Region Needs Profile'!C6 -> 50 | J47: ='Region Needs Profile'!P6 -> 20.904228 | K47: =IF($F47>=PERCENTILE($F$6:$F$138,0.75),"High",IF($F47>=PERCENTILE($F$6:$F$138,0.4),"Moderate","Low")) -> High | L47: =IF($J47>=40,"New build / PPEA",IF($J47<=-40,IF($K47="Low","Retrofit + state stack","Retrofit / ESPC"),IF($K47="High","Blended programme","Selective retrofit"))) -> Blended programme | M47: =IF($L47="New build / PPEA","Levy-backed debt + PPEA availability payment + SCAP 10%",IF($L47="Retrofit + state stack","SCAP 20-30% + Literary Fund + levy + guaranteed savings",IF($L47="Retrofit / ESPC","Levy + guaranteed savings + VPSA pooled bond",IF($L47="Blended programme","Levy-backed debt + ESPC on the retained estate","SCAP + Literary Fund + guaranteed savings")))) -> Levy-backed debt + ESPC on the retained estate | N47: =IF(OR($L47="Retrofit / ESPC",$L47="Retrofit + state stack"),$B$142,IF($L47="New build / PPEA",$B$144,$B$143)) -> 0.7 | O47: =IF($D47="On Nov 2026 ballot",$B$145,IF($D47="Levying since 2020-23",$B$147,IF($D47="Deferred, eyeing 2027",$B$148,$B$146))) -> 0.8 | P47: =IF($E47=0,"",($F47/MAX($F$6:$F$138))^0.38*100*$N47*$O47) -> 27.937577 | Q47: =IF($E47=0,"","P"&MIN(4,ROUNDUP(RANK($P47,$P$6:$P$138)/COUNT($P$6:$P$138)*4,0))) -> P1 | R47: =IF($D47="On Nov 2026 ballot","Wave 1 - position before the vote",IF($D47="Deferred, eyeing 2027","Wave 3 - 2027 referendum cycle",IF($D47="Levying since 2020-23","Wave 2 - next phase / displace incumbent","Wave 1 - VERIFY referendum status first"))) -> Wave 1 - VERIFY referendum status first | S47: =IF($L47="Retrofit + state stack","SCAP application support + no-cost condition assessment",IF($L47="Retrofit / ESPC","No-cost facility condition assessment",IF($L47="New build / PPEA","PPEA concept + capital sequencing review",IF($L47="Blended programme","Capital programme structuring review","Targeted HVAC and roof scope review")))) -> Capital programme structuring review
A48: ='Opportunity Model'!A48 -> Henrico County | B48: ='Opportunity Model'!B48 -> County | C48: 1 Central Virginia | D48: ='Opportunity Model'!D48 -> No public action found | E48: ='Opportunity Model'!E48 -> 1 | F48: ='Opportunity Model'!G48 -> 3.115375e+09 | G48: ='Opportunity Model'!F48 -> 1.0516627e+08 | H48: ='Region Needs Profile'!B6 -> 0.0584 | I48: ='Region Needs Profile'!C6 -> 50 | J48: ='Region Needs Profile'!P6 -> 20.904228 | K48: =IF($F48>=PERCENTILE($F$6:$F$138,0.75),"High",IF($F48>=PERCENTILE($F$6:$F$138,0.4),"Moderate","Low")) -> High | L48: =IF($J48>=40,"New build / PPEA",IF($J48<=-40,IF($K48="Low","Retrofit + state stack","Retrofit / ESPC"),IF($K48="High","Blended programme","Selective retrofit"))) -> Blended programme | M48: =IF($L48="New build / PPEA","Levy-backed debt + PPEA availability payment + SCAP 10%",IF($L48="Retrofit + state stack","SCAP 20-30% + Literary Fund + levy + guaranteed savings",IF($L48="Retrofit / ESPC","Levy + guaranteed savings + VPSA pooled bond",IF($L48="Blended programme","Levy-backed debt + ESPC on the retained estate","SCAP + Literary Fund + guaranteed savings")))) -> Levy-backed debt + ESPC on the retained estate | N48: =IF(OR($L48="Retrofit / ESPC",$L48="Retrofit + state stack"),$B$142,IF($L48="New build / PPEA",$B$144,$B$143)) -> 0.7 | O48: =IF($D48="On Nov 2026 ballot",$B$145,IF($D48="Levying since 2020-23",$B$147,IF($D48="Deferred, eyeing 2027",$B$148,$B$146))) -> 0.8 | P48: =IF($E48=0,"",($F48/MAX($F$6:$F$138))^0.38*100*$N48*$O48) -> 39.402256 | Q48: =IF($E48=0,"","P"&MIN(4,ROUNDUP(RANK($P48,$P$6:$P$138)/COUNT($P$6:$P$138)*4,0))) -> P1 | R48: =IF($D48="On Nov 2026 ballot","Wave 1 - position before the vote",IF($D48="Deferred, eyeing 2027","Wave 3 - 2027 referendum cycle",IF($D48="Levying since 2020-23","Wave 2 - next phase / displace incumbent","Wave 1 - VERIFY referendum status first"))) -> Wave 1 - VERIFY referendum status first | S48: =IF($L48="Retrofit + state stack","SCAP application support + no-cost condition assessment",IF($L48="Retrofit / ESPC","No-cost facility condition assessment",IF($L48="New build / PPEA","PPEA concept + capital sequencing review",IF($L48="Blended programme","Capital programme structuring review","Targeted HVAC and roof scope review")))) -> Capital programme structuring review
A49: ='Opportunity Model'!A49 -> Henry County | B49: ='Opportunity Model'!B49 -> County | C49: 6 Western Virginia | D49: ='Opportunity Model'!D49 -> Levying since 2020-23 | E49: ='Opportunity Model'!E49 -> 1 | F49: ='Opportunity Model'!G49 -> 2.1069014e+08 | G49: ='Opportunity Model'!F49 -> 7429840.1 | H49: ='Region Needs Profile'!B11 -> -0.0678 | I49: ='Region Needs Profile'!C11 -> 58 | J49: ='Region Needs Profile'!P11 -> -65.331358 | K49: =IF($F49>=PERCENTILE($F$6:$F$138,0.75),"High",IF($F49>=PERCENTILE($F$6:$F$138,0.4),"Moderate","Low")) -> Moderate | L49: =IF($J49>=40,"New build / PPEA",IF($J49<=-40,IF($K49="Low","Retrofit + state stack","Retrofit / ESPC"),IF($K49="High","Blended programme","Selective retrofit"))) -> Retrofit / ESPC | M49: =IF($L49="New build / PPEA","Levy-backed debt + PPEA availability payment + SCAP 10%",IF($L49="Retrofit + state stack","SCAP 20-30% + Literary Fund + levy + guaranteed savings",IF($L49="Retrofit / ESPC","Levy + guaranteed savings + VPSA pooled bond",IF($L49="Blended programme","Levy-backed debt + ESPC on the retained estate","SCAP + Literary Fund + guaranteed savings")))) -> Levy + guaranteed savings + VPSA pooled bond | N49: =IF(OR($L49="Retrofit / ESPC",$L49="Retrofit + state stack"),$B$142,IF($L49="New build / PPEA",$B$144,$B$143)) -> 1 | O49: =IF($D49="On Nov 2026 ballot",$B$145,IF($D49="Levying since 2020-23",$B$147,IF($D49="Deferred, eyeing 2027",$B$148,$B$146))) -> 0.65 | P49: =IF($E49=0,"",($F49/MAX($F$6:$F$138))^0.38*100*$N49*$O49) -> 16.43226 | Q49: =IF($E49=0,"","P"&MIN(4,ROUNDUP(RANK($P49,$P$6:$P$138)/COUNT($P$6:$P$138)*4,0))) -> P2 | R49: =IF($D49="On Nov 2026 ballot","Wave 1 - position before the vote",IF($D49="Deferred, eyeing 2027","Wave 3 - 2027 referendum cycle",IF($D49="Levying since 2020-23","Wave 2 - next phase / displace incumbent","Wave 1 - VERIFY referendum status first"))) -> Wave 2 - next phase / displace incumbent | S49: =IF($L49="Retrofit + state stack","SCAP application support + no-cost condition assessment",IF($L49="Retrofit / ESPC","No-cost facility condition assessment",IF($L49="New build / PPEA","PPEA concept + capital sequencing review",IF($L49="Blended programme","Capital programme structuring review","Targeted HVAC and roof scope review")))) -> No-cost facility condition assessment
A50: ='Opportunity Model'!A50 -> Highland County | B50: ='Opportunity Model'!B50 -> County | C50: 5 Valley | D50: ='Opportunity Model'!D50 -> No public action found | E50: ='Opportunity Model'!E50 -> 1 | F50: ='Opportunity Model'!G50 -> 8031372.3 | G50: ='Opportunity Model'!F50 -> 258755.64 | H50: ='Region Needs Profile'!B10 -> 0.0301 | I50: ='Region Needs Profile'!C10 -> 55 | J50: ='Region Needs Profile'!P10 -> 10.405306 | K50: =IF($F50>=PERCENTILE($F$6:$F$138,0.75),"High",IF($F50>=PERCENTILE($F$6:$F$138,0.4),"Moderate","Low")) -> Low | L50: =IF($J50>=40,"New build / PPEA",IF($J50<=-40,IF($K50="Low","Retrofit + state stack","Retrofit / ESPC"),IF($K50="High","Blended programme","Selective retrofit"))) -> Selective retrofit | M50: =IF($L50="New build / PPEA","Levy-backed debt + PPEA availability payment + SCAP 10%",IF($L50="Retrofit + state stack","SCAP 20-30% + Literary Fund + levy + guaranteed savings",IF($L50="Retrofit / ESPC","Levy + guaranteed savings + VPSA pooled bond",IF($L50="Blended programme","Levy-backed debt + ESPC on the retained estate","SCAP + Literary Fund + guaranteed savings")))) -> SCAP + Literary Fund + guaranteed savings | N50: =IF(OR($L50="Retrofit / ESPC",$L50="Retrofit + state stack"),$B$142,IF($L50="New build / PPEA",$B$144,$B$143)) -> 0.7 | O50: =IF($D50="On Nov 2026 ballot",$B$145,IF($D50="Levying since 2020-23",$B$147,IF($D50="Deferred, eyeing 2027",$B$148,$B$146))) -> 0.8 | P50: =IF($E50=0,"",($F50/MAX($F$6:$F$138))^0.38*100*$N50*$O50) -> 4.0907908 | Q50: =IF($E50=0,"","P"&MIN(4,ROUNDUP(RANK($P50,$P$6:$P$138)/COUNT($P$6:$P$138)*4,0))) -> P4 | R50: =IF($D50="On Nov 2026 ballot","Wave 1 - position before the vote",IF($D50="Deferred, eyeing 2027","Wave 3 - 2027 referendum cycle",IF($D50="Levying since 2020-23","Wave 2 - next phase / displace incumbent","Wave 1 - VERIFY referendum status first"))) -> Wave 1 - VERIFY referendum status first | S50: =IF($L50="Retrofit + state stack","SCAP application support + no-cost condition assessment",IF($L50="Retrofit / ESPC","No-cost facility condition assessment",IF($L50="New build / PPEA","PPEA concept + capital sequencing review",IF($L50="Blended programme","Capital programme structuring review","Targeted HVAC and roof scope review")))) -> Targeted HVAC and roof scope review
A51: ='Opportunity Model'!A51 -> Isle of Wight County | B51: ='Opportunity Model'!B51 -> County | C51: 2 Tidewater | D51: ='Opportunity Model'!D51 -> No public action found | E51: ='Opportunity Model'!E51 -> 1 | F51: ='Opportunity Model'!G51 -> 2.2447809e+08 | G51: ='Opportunity Model'!F51 -> 6594427 | H51: ='Region Needs Profile'!B7 -> 0.0143 | I51: ='Region Needs Profile'!C7 -> 50 | J51: ='Region Needs Profile'!P7 -> -8.3941602 | K51: =IF($F51>=PERCENTILE($F$6:$F$138,0.75),"High",IF($F51>=PERCENTILE($F$6:$F$138,0.4),"Moderate","Low")) -> Moderate | L51: =IF($J51>=40,"New build / PPEA",IF($J51<=-40,IF($K51="Low","Retrofit + state stack","Retrofit / ESPC"),IF($K51="High","Blended programme","Selective retrofit"))) -> Selective retrofit | M51: =IF($L51="New build / PPEA","Levy-backed debt + PPEA availability payment + SCAP 10%",IF($L51="Retrofit + state stack","SCAP 20-30% + Literary Fund + levy + guaranteed savings",IF($L51="Retrofit / ESPC","Levy + guaranteed savings + VPSA pooled bond",IF($L51="Blended programme","Levy-backed debt + ESPC on the retained estate","SCAP + Literary Fund + guaranteed savings")))) -> SCAP + Literary Fund + guaranteed savings | N51: =IF(OR($L51="Retrofit / ESPC",$L51="Retrofit + state stack"),$B$142,IF($L51="New build / PPEA",$B$144,$B$143)) -> 0.7 | O51: =IF($D51="On Nov 2026 ballot",$B$145,IF($D51="Levying since 2020-23",$B$147,IF($D51="Deferred, eyeing 2027",$B$148,$B$146))) -> 0.8 | P51: =IF($E51=0,"",($F51/MAX($F$6:$F$138))^0.38*100*$N51*$O51) -> 14.502179 | Q51: =IF($E51=0,"","P"&MIN(4,ROUNDUP(RANK($P51,$P$6:$P$138)/COUNT($P$6:$P$138)*4,0))) -> P2 | R51: =IF($D51="On Nov 2026 ballot","Wave 1 - position before the vote",IF($D51="Deferred, eyeing 2027","Wave 3 - 2027 referendum cycle",IF($D51="Levying since 2020-23","Wave 2 - next phase / displace incumbent","Wave 1 - VERIFY referendum status first"))) -> Wave 1 - VERIFY referendum status first | S51: =IF($L51="Retrofit + state stack","SCAP application support + no-cost condition assessment",IF($L51="Retrofit / ESPC","No-cost facility condition assessment",IF($L51="New build / PPEA","PPEA concept + capital sequencing review",IF($L51="Blended programme","Capital programme structuring review","Targeted HVAC and roof scope review")))) -> Targeted HVAC and roof scope review
A52: ='Opportunity Model'!A52 -> James City County | B52: ='Opportunity Model'!B52 -> County | C52: 2 Tidewater | D52: ='Opportunity Model'!D52 -> No public action found | E52: ='Opportunity Model'!E52 -> 1 | F52: ='Opportunity Model'!G52 -> 5.065895e+08 | G52: ='Opportunity Model'!F52 -> 17083775 | H52: ='Region Needs Profile'!B7 -> 0.0143 | I52: ='Region Needs Profile'!C7 -> 50 | J52: ='Region Needs Profile'!P7 -> -8.3941602 | K52: =IF($F52>=PERCENTILE($F$6:$F$138,0.75),"High",IF($F52>=PERCENTILE($F$6:$F$138,0.4),"Moderate","Low")) -> High | L52: =IF($J52>=40,"New build / PPEA",IF($J52<=-40,IF($K52="Low","Retrofit + state stack","Retrofit / ESPC"),IF($K52="High","Blended programme","Selective retrofit"))) -> Blended programme | M52: =IF($L52="New build / PPEA","Levy-backed debt + PPEA availability payment + SCAP 10%",IF($L52="Retrofit + state stack","SCAP 20-30% + Literary Fund + levy + guaranteed savings",IF($L52="Retrofit / ESPC","Levy + guaranteed savings + VPSA pooled bond",IF($L52="Blended programme","Levy-backed debt + ESPC on the retained estate","SCAP + Literary Fund + guaranteed savings")))) -> Levy-backed debt + ESPC on the retained estate | N52: =IF(OR($L52="Retrofit / ESPC",$L52="Retrofit + state stack"),$B$142,IF($L52="New build / PPEA",$B$144,$B$143)) -> 0.7 | O52: =IF($D52="On Nov 2026 ballot",$B$145,IF($D52="Levying since 2020-23",$B$147,IF($D52="Deferred, eyeing 2027",$B$148,$B$146))) -> 0.8 | P52: =IF($E52=0,"",($F52/MAX($F$6:$F$138))^0.38*100*$N52*$O52) -> 19.758616 | Q52: =IF($E52=0,"","P"&MIN(4,ROUNDUP(RANK($P52,$P$6:$P$138)/COUNT($P$6:$P$138)*4,0))) -> P1 | R52: =IF($D52="On Nov 2026 ballot","Wave 1 - position before the vote",IF($D52="Deferred, eyeing 2027","Wave 3 - 2027 referendum cycle",IF($D52="Levying since 2020-23","Wave 2 - next phase / displace incumbent","Wave 1 - VERIFY referendum status first"))) -> Wave 1 - VERIFY referendum status first | S52: =IF($L52="Retrofit + state stack","SCAP application support + no-cost condition assessment",IF($L52="Retrofit / ESPC","No-cost facility condition assessment",IF($L52="New build / PPEA","PPEA concept + capital sequencing review",IF($L52="Blended programme","Capital programme structuring review","Targeted HVAC and roof scope review")))) -> Capital programme structuring review
A53: ='Opportunity Model'!A53 -> King George County | B53: ='Opportunity Model'!B53 -> County | C53: 3 Northern Neck | D53: ='Opportunity Model'!D53 -> No public action found | E53: ='Opportunity Model'!E53 -> 1 | F53: ='Opportunity Model'!G53 -> 1.7539275e+08 | G53: ='Opportunity Model'!F53 -> 5282676.7 | H53: ='Region Needs Profile'!B8 -> 0.1108 | I53: ='Region Needs Profile'!C8 -> 32 | J53: ='Region Needs Profile'!P8 -> 86.269916 | K53: =IF($F53>=PERCENTILE($F$6:$F$138,0.75),"High",IF($F53>=PERCENTILE($F$6:$F$138,0.4),"Moderate","Low")) -> Moderate | L53: =IF($J53>=40,"New build / PPEA",IF($J53<=-40,IF($K53="Low","Retrofit + state stack","Retrofit / ESPC"),IF($K53="High","Blended programme","Selective retrofit"))) -> New build / PPEA | M53: =IF($L53="New build / PPEA","Levy-backed debt + PPEA availability payment + SCAP 10%",IF($L53="Retrofit + state stack","SCAP 20-30% + Literary Fund + levy + guaranteed savings",IF($L53="Retrofit / ESPC","Levy + guaranteed savings + VPSA pooled bond",IF($L53="Blended programme","Levy-backed debt + ESPC on the retained estate","SCAP + Literary Fund + guaranteed savings")))) -> Levy-backed debt + PPEA availability payment + SCAP 10% | N53: =IF(OR($L53="Retrofit / ESPC",$L53="Retrofit + state stack"),$B$142,IF($L53="New build / PPEA",$B$144,$B$143)) -> 0.45 | O53: =IF($D53="On Nov 2026 ballot",$B$145,IF($D53="Levying since 2020-23",$B$147,IF($D53="Deferred, eyeing 2027",$B$148,$B$146))) -> 0.8 | P53: =IF($E53=0,"",($F53/MAX($F$6:$F$138))^0.38*100*$N53*$O53) -> 8.4884045 | Q53: =IF($E53=0,"","P"&MIN(4,ROUNDUP(RANK($P53,$P$6:$P$138)/COUNT($P$6:$P$138)*4,0))) -> P3 | R53: =IF($D53="On Nov 2026 ballot","Wave 1 - position before the vote",IF($D53="Deferred, eyeing 2027","Wave 3 - 2027 referendum cycle",IF($D53="Levying since 2020-23","Wave 2 - next phase / displace incumbent","Wave 1 - VERIFY referendum status first"))) -> Wave 1 - VERIFY referendum status first | S53: =IF($L53="Retrofit + state stack","SCAP application support + no-cost condition assessment",IF($L53="Retrofit / ESPC","No-cost facility condition assessment",IF($L53="New build / PPEA","PPEA concept + capital sequencing review",IF($L53="Blended programme","Capital programme structuring review","Targeted HVAC and roof scope review")))) -> PPEA concept + capital sequencing review
A54: ='Opportunity Model'!A54 -> King William County | B54: ='Opportunity Model'!B54 -> County | C54: 3 Northern Neck | D54: ='Opportunity Model'!D54 -> No public action found | E54: ='Opportunity Model'!E54 -> 1 | F54: ='Opportunity Model'!G54 -> 83835728 | G54: ='Opportunity Model'!F54 -> 2667715.8 | H54: ='Region Needs Profile'!B8 -> 0.1108 | I54: ='Region Needs Profile'!C8 -> 32 | J54: ='Region Needs Profile'!P8 -> 86.269916 | K54: =IF($F54>=PERCENTILE($F$6:$F$138,0.75),"High",IF($F54>=PERCENTILE($F$6:$F$138,0.4),"Moderate","Low")) -> Low | L54: =IF($J54>=40,"New build / PPEA",IF($J54<=-40,IF($K54="Low","Retrofit + state stack","Retrofit / ESPC"),IF($K54="High","Blended programme","Selective retrofit"))) -> New build / PPEA | M54: =IF($L54="New build / PPEA","Levy-backed debt + PPEA availability payment + SCAP 10%",IF($L54="Retrofit + state stack","SCAP 20-30% + Literary Fund + levy + guaranteed savings",IF($L54="Retrofit / ESPC","Levy + guaranteed savings + VPSA pooled bond",IF($L54="Blended programme","Levy-backed debt + ESPC on the retained estate","SCAP + Literary Fund + guaranteed savings")))) -> Levy-backed debt + PPEA availability payment + SCAP 10% | N54: =IF(OR($L54="Retrofit / ESPC",$L54="Retrofit + state stack"),$B$142,IF($L54="New build / PPEA",$B$144,$B$143)) -> 0.45 | O54: =IF($D54="On Nov 2026 ballot",$B$145,IF($D54="Levying since 2020-23",$B$147,IF($D54="Deferred, eyeing 2027",$B$148,$B$146))) -> 0.8 | P54: =IF($E54=0,"",($F54/MAX($F$6:$F$138))^0.38*100*$N54*$O54) -> 6.4121654 | Q54: =IF($E54=0,"","P"&MIN(4,ROUNDUP(RANK($P54,$P$6:$P$138)/COUNT($P$6:$P$138)*4,0))) -> P4 | R54: =IF($D54="On Nov 2026 ballot","Wave 1 - position before the vote",IF($D54="Deferred, eyeing 2027","Wave 3 - 2027 referendum cycle",IF($D54="Levying since 2020-23","Wave 2 - next phase / displace incumbent","Wave 1 - VERIFY referendum status first"))) -> Wave 1 - VERIFY referendum status first | S54: =IF($L54="Retrofit + state stack","SCAP application support + no-cost condition assessment",IF($L54="Retrofit / ESPC","No-cost facility condition assessment",IF($L54="New build / PPEA","PPEA concept + capital sequencing review",IF($L54="Blended programme","Capital programme structuring review","Targeted HVAC and roof scope review")))) -> PPEA concept + capital sequencing review
